Workbook

Sheet Nike_Sales_Uncleaned
A1: Order_ID | B1: Gender_Category | C1: Product_Line | D1: Product_Name | E1: Size | F1: Units_Sold | G1: MRP | H1: Discount_Applied | I1: Revenue | J1: Order_Date | K1: Sales_Channel | L1: Region | M1: Profit
A2: 2000 | B2: Kids | C2: Training | D2: SuperRep Go | E2: M | H2: 0.47 | I2: 0 | J2: 45360 | K2: Online | L2: bengaluru | M2: -770.45
A3: 2001 | B3: Women | C3: Soccer | D3: Tiempo Legend | E3: M | F3: 3 | G3: 4957.93 | I3: 0 | J3: 45482 | K3: Retail | L3: Hyd | M3: -112.53
A4: 2002 | B4: Women | C4: Soccer | D4: Premier III | E4: M | F4: 4 | I4: 0 | K4: Retail | L4: Mumbai | M4: 3337.34
A5: 2003 | B5: Kids | C5: Lifestyle | D5: Blazer Mid | E5: L | G5: 9673.57 | I5: 0 | J5: 45569 | K5: Online | L5: Pune | M5: 3376.85
A6: 2004 | B6: Kids | C6: Running | D6: React Infinity | E6: XL | I6: 0 | J6: 45547 | K6: Retail | L6: Delhi | M6: 187.89
A7: 2005 | B7: Women | C7: Training | D7: Flex Trainer | E7: M | F7: 1 | G7: 7363.96 | I7: 0 | K7: Retail | L7: Delhi | M7: 1415.98
A8: 2006 | B8: Men | C8: Training | D8: SuperRep Go | E8: M | G8: 6819.78 | I8: 0 | J8: 45812 | K8: Online | L8: Bangalore | M8: 1802.09
A9: 2007 | B9: Kids | C9: Training | D9: SuperRep Go | E9: M | F9: 1 | H9: 0.32 | I9: 0 | K9: Retail | L9: Bangalore | M9: 2928.36
A10: 2008 | B10: Women | C10: Soccer | D10: Premier III | E10: 11 | F10: -1 | I10: 0 | J10: 45576 | K10: Online | L10: Hyderabad | M10: -731.18
A11: 2009 | B11: Men | C11: Soccer | D11: Mercurial Superfly | E11: M | F11: 4 | I11: 0 | K11: Online | L11: Pune | M11: 3929.61
A12: 2010 | B12: Kids | C12: Lifestyle | D12: Waffle One | E12: L | F12: 1 | G12: 7949.83 | I12: 0 | J12: 45673 | K12: Online | L12: Pune | M12: 1965.56
A13: 2011 | B13: Women | C13: Training | D13: Flex Trainer | E13: L | F13: -1 | G13: 9586.08 | I13: 0 | K13: Retail | L13: Hyd | M13: 1667.08
A14: 2018 | B14: Kids | C14: Lifestyle | D14: Blazer Mid | F14: -1 | H14: 0.86 | I14: 0 | J14: 45609 | K14: Online | L14: Delhi | M14: 2109.48
A15: 2013 | B15: Kids | C15: Training | D15: SuperRep Go | G15: 9671.05 | I15: 0 | J15: 45554 | K15: Online | L15: hyderbad | M15: 299.34
A16: 2014 | B16: Women | C16: Running | D16: React Infinity | E16: 11 | I16: 0 | J16: 45759 | K16: Online | L16: Bangalore | M16: -1044.4
A17: 2015 | B17: Kids | C17: Basketball | D17: Air Jordan | G17: 3285.52 | I17: 0 | J17: 45808 | K17: Retail | L17: Kolkata | M17: 1193.21
A18: 2016 | B18: Women | C18: Basketball | D18: Air Jordan | E18: M | F18: 1 | G18: 9871.75 | H18: 0.3 | I18: 6910.22 | K18: Retail | L18: hyderbad | M18: 2452.69
A19: 2017 | B19: Women | C19: Basketball | D19: Air Jordan | E19: 9 | F19: 4 | I19: 0 | J19: 45733 | K19: Retail | L19: Delhi | M19: 1946.24
A20: 2018 | B20: Men | C20: Training | D20: Metcon 7 | E20: XL | F20: 0 | H20: 1.17 | I20: 0 | K20: Online | L20: bengaluru | M20: -966.89
A21: 2019 | B21: Kids | C21: Running | D21: Air Zoom | E21: 6 | F21: 0 | G21: 3424.06 | H21: 0.32 | I21: 0 | J21: 45674 | K21: Online | L21: Hyderabad | M21: 1915.24
A22: 2020 | B22: Kids | C22: Soccer | D22: Tiempo Legend | E22: L | F22: -1 | H22: 0.67 | I22: 0 | J22: 45744 | K22: Retail | L22: Mumbai | M22: 439.96
A23: 2021 | B23: Men | C23: Running | D23: Free RN | E23: L | F23: -1 | G23: 7086.7 | H23: 0.66 | I23: -2409.48 | J23: 45615 | K23: Retail | L23: Hyd | M23: -1120.49
A24: 2022 | B24: Women | C24: Soccer | D24: Premier III | E24: M | I24: 0 | J24: 45559 | K24: Online | L24: Pune | M24: 3427.16
A25: 2023 | B25: Men | C25: Lifestyle | D25: Waffle One | E25: M | G25: 5003.95 | I25: 0 | J25: 45667 | K25: Online | L25: Mumbai | M25: 1498.37
A26: 2024 | B26: Kids | C26: Training | D26: SuperRep Go | E26: XL | F26: 0 | H26: 0.5 | I26: 0 | J26: 45654 | K26: Retail | L26: Bangalore | M26: 1842.35
A27: 2025 | B27: Women | C27: Basketball | D27: Kyrie Flytrap | E27: M | F27: 3 | G27: 9820.5 | I27: 0 | K27: Retail | L27: Mumbai | M27: 1900.15
A28: 2026 | B28: Kids | C28: Lifestyle | D28: Blazer Mid | E28: XL | F28: 1 | H28: 0.16 | I28: 0 | J28: 45514 | K28: Retail | L28: Kolkata | M28: 2301.64
A29: 2027 | B29: Men | C29: Basketball | D29: Zoom Freak | E29: XL | H29: 0.22 | I29: 0 | K29: Online | L29: Pune | M29: -138.74
A30: 2028 | B30: Men | C30: Training | D30: Flex Trainer | E30: 12 | G30: 3270.23 | I30: 0 | K30: Retail | L30: Delhi | M30: -946.86
A31: 2029 | B31: Men | C31: Training | D31: ZoomX Invincible | E31: 12 | F31: 0 | I31: 0 | J31: 45227 | K31: Online | L31: Bangalore | M31: -185.67
A32: 2030 | B32: Men | C32: Soccer | D32: Phantom GT | E32: XL | H32: 1.05 | I32: 0 | J32: 45852 | K32: Retail | L32: Hyd | M32: -122.93
A33: 2031 | B33: Men | C33: Soccer | D33: Premier III | F33: 4 | G33: 3493.04 | H33: 0.82 | I33: 2514.99 | J33: 45421 | K33: Online | L33: Delhi | M33: 350.7
A34: 2032 | B34: Women | C34: Lifestyle | D34: Blazer Mid | E34: XL | F34: 1 | H34: 1.07 | I34: 0 | J34: 45758 | K34: Retail | L34: Mumbai | M34: -555.16
A35: 2033 | B35: Men | C35: Soccer | D35: Mercurial Superfly | E35: XL | F35: -1 | I35: 0 | K35: Retail | L35: Kolkata | M35: -1005.71
A36: 2034 | B36: Men | C36: Basketball | D36: Air Jordan | E36: 6 | G36: 6235.71 | I36: 0 | J36: 45777 | K36: Retail | L36: Delhi | M36: -267.37
A37: 2035 | B37: Kids | C37: Basketball | D37: Zoom Freak | F37: 4 | H37: 0.38 | I37: 0 | J37: 45613 | K37: Online | L37: Bangalore | M37: 2914.83
A38: 2036 | B38: Men | C38: Training | D38: Metcon 7 | F38: 3 | I38: 0 | J38: 45703 | K38: Retail | L38: Bangalore | M38: -143.8
A39: 2037 | B39: Kids | C39: Running | D39: Pegasus Turbo | E39: 7 | F39: 3 | G39: 5653.14 | H39: 1.01 | I39: -169.59 | K39: Retail | L39: Pune | M39: 2776.96
A40: 2038 | B40: Kids | C40: Running | D40: Free RN | F40: 0 | H40: 0.83 | I40: 0 | K40: Online | L40: Delhi | M40: 1163.21
A41: 2039 | B41: Women | C41: Training | D41: Flex Trainer | E41: M | G41: 2767.7 | H41: 0.63 | I41: 0 | J41: 45769 | K41: Retail | L41: hyderbad | M41: -336.3
A42: 2002 | B42: Women | C42: Basketball | D42: Zoom Freak | E42: XL | F42: 3 | G42: 5075.22 | I42: 0 | J42: 45723 | K42: Retail | L42: Delhi | M42: 145.08
A43: 2041 | B43: Kids | C43: Soccer | D43: Tiempo Legend | E43: 12 | G43: 5553.88 | I43: 0 | J43: 45721 | K43: Online | L43: Hyd | M43: 2371.66
A44: 2042 | B44: Women | C44: Basketball | D44: Kyrie Flytrap | E44: L | I44: 0 | J44: 45766 | K44: Online | L44: hyderbad | M44: -862.16
A45: 2043 | B45: Men | C45: Soccer | D45: Premier III | E45: XL | G45: 3492.89 | H45: 0.77 | I45: 0 | J45: 45414 | K45: Retail | L45: Delhi | M45: 3770.75
A46: 2044 | B46: Kids | C46: Training | D46: SuperRep Go | I46: 0 | J46: 45175 | K46: Online | L46: Delhi | M46: 2174.71
A47: 2045 | B47: Kids | C47: Lifestyle | D47: Dunk Low | E47: XL | F47: 4 | I47: 0 | J47: 45753 | K47: Retail | L47: Delhi | M47: 1833.94
A48: 2046 | B48: Kids | C48: Running | D48: Air Zoom | E48: 12 | H48: 1.04 | I48: 0 | K48: Online | L48: Kolkata | M48: 1284.33
A49: 2047 | B49: Women | C49: Training | D49: SuperRep Go | E49: 10 | F49: 1 | G49: 8577.75 | I49: 0 | J49: 45456 | K49: Retail | L49: Bangalore | M49: 2888.68
A50: 2048 | B50: Women | C50: Basketball | D50: Air Jordan | E50: XL | I50: 0 | J50: 45592 | K50: Online | L50: Bangalore | M50: 2875.86
A51: 2049 | B51: Kids | C51: Soccer | D51: Tiempo Legend | E51: L | F51: 1 | G51: 7767.2 | I51: 0 | K51: Retail | L51: Pune | M51: 311.48
A52: 2050 | B52: Men | C52: Running | D52: Air Zoom | E52: L | F52: 1 | H52: 0.57 | I52: 0 | K52: Retail | L52: Kolkata | M52: 682.12
A53: 2051 | B53: Women | C53: Basketball | D53: Air Jordan | E53: XL | H53: 0.37 | I53: 0 | J53: 45296 | K53: Retail | L53: Delhi | M53: 3135.98
A54: 2052 | B54: Men | C54: Training | D54: Flex Trainer | E54: 10 | F54: 3 | G54: 9155.96 | I54: 0 | J54: 45573 | K54: Retail | L54: Pune | M54: 2184.8
A55: 2053 | B55: Men | C55: Lifestyle | D55: Air Force 1 | E55: XL | F55: 3 | G55: 6009.58 | I55: 0 | J55: 45567 | K55: Online | L55: Delhi | M55: 3384.92
A56: 2054 | B56: Women | C56: Training | D56: Flex Trainer | E56: 11 | F56: -1 | I56: 0 | J56: 45831 | K56: Online | L56: Mumbai | M56: -549.76
A57: 2055 | B57: Men | C57: Basketball | D57: Kyrie Flytrap | E57: L | I57: 0 | J57: 45591 | K57: Online | L57: hyderbad | M57: -1078.76
A58: 2056 | B58: Men | C58: Running | D58: React Infinity | E58: L | F58: 3 | I58: 0 | J58: 45443 | K58: Retail | L58: Bangalore | M58: -244.44
A59: 2048 | B59: Men | C59: Lifestyle | D59: Waffle One | E59: M | F59: 3 | G59: 6216.29 | H59: 0.94 | I59: 1118.93 | J59: 45549 | K59: Online | L59: Mumbai | M59: -642.02
A60: 2058 | B60: Women | C60: Training | D60: Flex Trainer | E60: 11 | G60: 4985.92 | I60: 0 | K60: Online | L60: Kolkata | M60: 361.54
A61: 2059 | B61: Kids | C61: Soccer | D61: Phantom GT | F61: -1 | G61: 9507.54 | I61: 0 | J61: 45287 | K61: Retail | L61: Delhi | M61: 291.28
A62: 2060 | B62: Men | C62: Lifestyle | D62: Waffle One | E62: L | F62: 2 | G62: 7979.26 | I62: 0 | J62: 45484 | K62: Online | L62: bengaluru | M62: 2821.59
A63: 2061 | B63: Women | C63: Basketball | D63: LeBron 20 | E63: L | I63: 0 | J63: 45545 | K63: Online | L63: Mumbai | M63: -501.68
A64: 2062 | B64: Men | C64: Basketball | D64: Air Jordan | F64: 2 | I64: 0 | J64: 45814 | K64: Online | L64: Bangalore | M64: 1823.91
A65: 2063 | B65: Women | C65: Basketball | D65: Air Jordan | E65: M | F65: 1 | G65: 9751 | H65: 0.16 | I65: 8190.84 | J65: 45541 | K65: Retail | L65: Pune | M65: 1130.31
A66: 2064 | B66: Kids | C66: Running | D66: React Infinity | E66: L | F66: 2 | G66: 7557.71 | I66: 0 | J66: 45718 | K66: Online | L66: Bangalore | M66: 3277.44
A67: 2065 | B67: Women | C67: Lifestyle | D67: Waffle One | E67: 10 | H67: 0.78 | I67: 0 | J67: 45333 | K67: Retail | L67: Hyd | M67: 21.58
A68: 2066 | B68: Men | C68: Soccer | D68: Phantom GT | E68: XL | F68: -1 | G68: 5259.05 | I68: 0 | J68: 45636 | K68: Online | L68: Mumbai | M68: 1022.82
A69: 2067 | B69: Kids | C69: Basketball | D69: LeBron 20 | E69: L | F69: 4 | G69: 3588.38 | I69: 0 | J69: 45783 | K69: Online | L69: Kolkata | M69: 161.5
A70: 2068 | B70: Men | C70: Running | D70: Free RN | F70: 4 | G70: 2553.29 | I70: 0 | J70: 45631 | K70: Retail | L70: Mumbai | M70: 984.9
A71: 2069 | B71: Women | C71: Training | D71: SuperRep Go | G71: 7502.24 | I71: 0 | J71: 45852 | K71: Online | L71: Pune | M71: 3554.58
A72: 2070 | B72: Kids | C72: Running | D72: React Infinity | E72: L | I72: 0 | K72: Retail | L72: Mumbai | M72: 1112.43
A73: 2071 | B73: Kids | C73: Lifestyle | D73: Blazer Mid | E73: M | F73: 3 | G73: 7849.81 | H73: 0.49 | I73: 12010.21 | J73: 45669 | K73: Retail | L73: Pune | M73: -882.96
A74: 2072 | B74: Men | C74: Training | D74: Flex Trainer | F74: 3 | I74: 0 | K74: Retail | L74: Pune | M74: 3639.2
A75: 2073 | B75: Women | C75: Lifestyle | D75: Blazer Mid | E75: 12 | F75: 4 | H75: 0.85 | I75: 0 | J75: 45599 | K75: Online | L75: Hyd | M75: 443.86
A76: 2074 | B76: Men | C76: Training | D76: Flex Trainer | E76: L | F76: -1 | H76: 0.57 | I76: 0 | K76: Online | L76: Kolkata | M76: 1958.47
A77: 2075 | B77: Kids | C77: Basketball | D77: Air Jordan | E77: L | F77: 4 | G77: 4251.74 | I77: 0 | J77: 45852 | K77: Online | L77: Pune | M77: 2345.35
A78: 2076 | B78: Women | C78: Training | D78: ZoomX Invincible | E78: 11 | I78: 0 | J78: 45578 | K78: Retail | L78: bengaluru | M78: 2011.25
A79: 2077 | B79: Men | C79: Training | D79: ZoomX Invincible | E79: L | I79: 0 | J79: 45251 | K79: Online | L79: Pune | M79: 3332.66
A80: 2078 | B80: Women | C80: Basketball | D80: LeBron 20 | F80: 0 | G80: 6970.47 | I80: 0 | K80: Online | L80: Mumbai | M80: 262.79
A81: 2079 | B81: Men | C81: Running | D81: Pegasus Turbo | E81: XL | F81: -1 | G81: 4322.06 | I81: 0 | J81: 45676 | K81: Online | L81: bengaluru | M81: 279.78
A82: 2080 | B82: Men | C82: Lifestyle | D82: Blazer Mid | E82: L | I82: 0 | J82: 45747 | K82: Online | L82: Bangalore | M82: -1005.89
A83: 2081 | B83: Men | C83: Training | D83: ZoomX Invincible | E83: L | I83: 0 | K83: Online | L83: Mumbai | M83: 2810.49
A84: 2028 | B84: Men | C84: Running | D84: Free RN | F84: -1 | H84: 0.21 | I84: 0 | J84: 45336 | K84: Online | L84: Hyderabad | M84: 3303.01
A85: 2083 | B85: Men | C85: Running | D85: Free RN | G85: 9291.74 | I85: 0 | J85: 45579 | K85: Retail | L85: Delhi | M85: -981.21
A86: 2084 | B86: Men | C86: Training | D86: Metcon 7 | E86: M | F86: 2 | I86: 0 | J86: 45284 | K86: Online | L86: Mumbai | M86: 408.39
A87: 2085 | B87: Men | C87: Basketball | D87: Kyrie Flytrap | G87: 7561.85 | I87: 0 | J87: 45643 | K87: Retail | L87: Kolkata | M87: 98.72
A88: 2086 | B88: Men | C88: Soccer | D88: Mercurial Superfly | E88: L | F88: 0 | H88: 0.45 | I88: 0 | J88: 45576 | K88: Online | L88: Kolkata | M88: 1742.66
A89: 2087 | B89: Kids | C89: Basketball | D89: Zoom Freak | G89: 4656.28 | I89: 0 | J89: 45597 | K89: Online | L89: Kolkata | M89: 3777.5
A90: 2088 | B90: Women | C90: Running | D90: Free RN | E90: XL | F90: 4 | I90: 0 | J90: 45773 | K90: Online | L90: Bangalore | M90: 2702.93
A91: 2089 | B91: Women | C91: Training | D91: Flex Trainer | E91: L | F91: 2 | G91: 6874.77 | H91: 0.6 | I91: 5499.82 | J91: 45628 | K91: Online | L91: Mumbai | M91: -1076.66
A92: 2090 | B92: Kids | C92: Lifestyle | D92: Dunk Low | E92: 8 | I92: 0 | K92: Retail | L92: Bangalore | M92: 163.15
A93: 2091 | B93: Kids | C93: Running | D93: Air Zoom | E93: 11 | G93: 9246.88 | I93: 0 | K93: Retail | L93: Mumbai | M93: 1917.55
A94: 2092 | B94: Kids | C94: Basketball | D94: Zoom Freak | E94: XL | F94: 2 | H94: 1.13 | I94: 0 | K94: Online | L94: Delhi | M94: 207.2
A95: 2093 | B95: Men | C95: Running | D95: Free RN | E95: XL | F95: 0 | H95: 0.29 | I95: 0 | K95: Online | L95: Kolkata | M95: -146.73
A96: 2094 | B96: Kids | C96: Training | D96: Flex Trainer | E96: 10 | F96: 1 | G96: 4276.36 | I96: 0 | J96: 45606 | K96: Retail | L96: Delhi | M96: 2974.58
A97: 2095 | B97: Men | C97: Lifestyle | D97: Waffle One | E97: M | I97: 0 | J97: 45581 | K97: Online | L97: Delhi | M97: 880.57
A98: 2096 | B98: Men | C98: Running | D98: Pegasus Turbo | E98: XL | F98: 2 | I98: 0 | J98: 45650 | K98: Online | L98: Kolkata | M98: 288.66
A99: 2097 | B99: Women | C99: Training | D99: ZoomX Invincible | E99: XL | G99: 7978.89 | I99: 0 | K99: Online | L99: Bangalore | M99: 769.05
A100: 2098 | B100: Men | C100: Training | D100: ZoomX Invincible | E100: L | G100: 5690.69 | H100: 0.69 | I100: 0 | J100: 45315 | K100: Online | L100: hyderbad | M100: 98.3
...

Sheet Cleaned Data
A1: Order_ID | B1: Gender_Category | C1: Product_Line | D1: Product_Name | E1: Size | F1: Units_Sold | G1: MRP | H1: Discount_Applied | I1: Revenue | J1: Order_Date | K1: Sales_Channel | L1: Region | M1: Profit
A2: 2000 | B2: Kids | C2: Training | D2: SuperRep Go | E2: =IF(Nike_Sales_Uncleaned!E2="","NA",IF(OR(Nike_Sales_Uncleaned!E2=0,Nike_Sales_Uncleaned!E2=-1),"NA",UPPER(Nike_Sales_Uncleaned!E2))) -> M | F2: {=IF(Nike_Sales_Uncleaned!F2="",MEDIAN(_xlfn._xlws.FILTER(Nike_Sales_Uncleaned!$F$2:$F$2501,Nike_Sales_Uncleaned!$F$2:$F$2501>0)),Nike_Sales_Uncleaned!F2)} -> 2 | G2: {=IF(OR(Nike_Sales_Uncleaned!G2="",Nike_Sales_Uncleaned!G2<=0),MEDIAN(_xlfn._xlws.FILTER(Nike_Sales_Uncleaned!$G$2:$G$2501,Nike_Sales_Uncleaned!$G$2:$G$2501>0)),Nike_Sales_Uncleaned!G2)} -> 6110.03 | H2: =IF(Nike_Sales_Uncleaned!H2="",0,IF(AND(Nike_Sales_Uncleaned!H2>=0,Nike_Sales_Uncleaned!H2<=1),Nike_Sales_Uncleaned!H2,0)) -> 0.47 | I2: 0 | J2: =IF(Nike_Sales_Uncleaned[[#This Row],[Order_Date]]="","",Nike_Sales_Uncleaned[[#This Row],[Order_Date]]) -> 45360 | K2: Online | L2: Bangalore | M2: -770.45
A3: 2001 | B3: Women | C3: Soccer | D3: Tiempo Legend | E3: =IF(Nike_Sales_Uncleaned!E3="","NA",IF(OR(Nike_Sales_Uncleaned!E3=0,Nike_Sales_Uncleaned!E3=-1),"NA",UPPER(Nike_Sales_Uncleaned!E3))) -> M | F3: {=IF(Nike_Sales_Uncleaned!F3="",MEDIAN(_xlfn._xlws.FILTER(Nike_Sales_Uncleaned!$F$2:$F$2501,Nike_Sales_Uncleaned!$F$2:$F$2501>0)),Nike_Sales_Uncleaned!F3)} -> 3 | G3: {=IF(OR(Nike_Sales_Uncleaned!G3="",Nike_Sales_Uncleaned!G3<=0),MEDIAN(_xlfn._xlws.FILTER(Nike_Sales_Uncleaned!$G$2:$G$2501,Nike_Sales_Uncleaned!$G$2:$G$2501>0)),Nike_Sales_Uncleaned!G3)} -> 4957.93 | H3: =IF(Nike_Sales_Uncleaned!H3="",0,IF(AND(Nike_Sales_Uncleaned!H3>=0,Nike_Sales_Uncleaned!H3<=1),Nike_Sales_Uncleaned!H3,0)) -> 0 | I3: 0 | J3: =IF(Nike_Sales_Uncleaned[[#This Row],[Order_Date]]="","",Nike_Sales_Uncleaned[[#This Row],[Order_Date]]) -> 45482 | K3: Retail | L3: Hyderabad | M3: -112.53
A4: 2002 | B4: Women | C4: Soccer | D4: Premier III | E4: =IF(Nike_Sales_Uncleaned!E4="","NA",IF(OR(Nike_Sales_Uncleaned!E4=0,Nike_Sales_Uncleaned!E4=-1),"NA",UPPER(Nike_Sales_Uncleaned!E4))) -> M | F4: {=IF(Nike_Sales_Uncleaned!F4="",MEDIAN(_xlfn._xlws.FILTER(Nike_Sales_Uncleaned!$F$2:$F$2501,Nike_Sales_Uncleaned!$F$2:$F$2501>0)),Nike_Sales_Uncleaned!F4)} -> 4 | G4: {=IF(OR(Nike_Sales_Uncleaned!G4="",Nike_Sales_Uncleaned!G4<=0),MEDIAN(_xlfn._xlws.FILTER(Nike_Sales_Uncleaned!$G$2:$G$2501,Nike_Sales_Uncleaned!$G$2:$G$2501>0)),Nike_Sales_Uncleaned!G4)} -> 6110.03 | H4: =IF(Nike_Sales_Uncleaned!H4="",0,IF(AND(Nike_Sales_Uncleaned!H4>=0,Nike_Sales_Uncleaned!H4<=1),Nike_Sales_Uncleaned!H4,0)) -> 0 | I4: 0 | J4: =IF(Nike_Sales_Uncleaned[[#This Row],[Order_Date]]="","",Nike_Sales_Uncleaned[[#This Row],[Order_Date]]) | K4: Retail | L4: Mumbai | M4: 3337.34
A5: 2003 | B5: Kids | C5: Lifestyle | D5: Blazer Mid | E5: =IF(Nike_Sales_Uncleaned!E5="","NA",IF(OR(Nike_Sales_Uncleaned!E5=0,Nike_Sales_Uncleaned!E5=-1),"NA",UPPER(Nike_Sales_Uncleaned!E5))) -> L | F5: {=IF(Nike_Sales_Uncleaned!F5="",MEDIAN(_xlfn._xlws.FILTER(Nike_Sales_Uncleaned!$F$2:$F$2501,Nike_Sales_Uncleaned!$F$2:$F$2501>0)),Nike_Sales_Uncleaned!F5)} -> 2 | G5: {=IF(OR(Nike_Sales_Uncleaned!G5="",Nike_Sales_Uncleaned!G5<=0),MEDIAN(_xlfn._xlws.FILTER(Nike_Sales_Uncleaned!$G$2:$G$2501,Nike_Sales_Uncleaned!$G$2:$G$2501>0)),Nike_Sales_Uncleaned!G5)} -> 9673.57 | H5: =IF(Nike_Sales_Uncleaned!H5="",0,IF(AND(Nike_Sales_Uncleaned!H5>=0,Nike_Sales_Uncleaned!H5<=1),Nike_Sales_Uncleaned!H5,0)) -> 0 | I5: 0 | J5: =IF(Nike_Sales_Uncleaned[[#This Row],[Order_Date]]="","",Nike_Sales_Uncleaned[[#This Row],[Order_Date]]) -> 45569 | K5: Online | L5: Pune | M5: 3376.85
A6: 2004 | B6: Kids | C6: Running | D6: React Infinity | E6: =IF(Nike_Sales_Uncleaned!E6="","NA",IF(OR(Nike_Sales_Uncleaned!E6=0,Nike_Sales_Uncleaned!E6=-1),"NA",UPPER(Nike_Sales_Uncleaned!E6))) -> XL | F6: {=IF(Nike_Sales_Uncleaned!F6="",MEDIAN(_xlfn._xlws.FILTER(Nike_Sales_Uncleaned!$F$2:$F$2501,Nike_Sales_Uncleaned!$F$2:$F$2501>0)),Nike_Sales_Uncleaned!F6)} -> 2 | G6: {=IF(OR(Nike_Sales_Uncleaned!G6="",Nike_Sales_Uncleaned!G6<=0),MEDIAN(_xlfn._xlws.FILTER(Nike_Sales_Uncleaned!$G$2:$G$2501,Nike_Sales_Uncleaned!$G$2:$G$2501>0)),Nike_Sales_Uncleaned!G6)} -> 6110.03 | H6: =IF(Nike_Sales_Uncleaned!H6="",0,IF(AND(Nike_Sales_Uncleaned!H6>=0,Nike_Sales_Uncleaned!H6<=1),Nike_Sales_Uncleaned!H6,0)) -> 0 | I6: 0 | J6: =IF(Nike_Sales_Uncleaned[[#This Row],[Order_Date]]="","",Nike_Sales_Uncleaned[[#This Row],[Order_Date]]) -> 45547 | K6: Retail | L6: Delhi | M6: 187.89
A7: 2005 | B7: Women | C7: Training | D7: Flex Trainer | E7: =IF(Nike_Sales_Uncleaned!E7="","NA",IF(OR(Nike_Sales_Uncleaned!E7=0,Nike_Sales_Uncleaned!E7=-1),"NA",UPPER(Nike_Sales_Uncleaned!E7))) -> M | F7: {=IF(Nike_Sales_Uncleaned!F7="",MEDIAN(_xlfn._xlws.FILTER(Nike_Sales_Uncleaned!$F$2:$F$2501,Nike_Sales_Uncleaned!$F$2:$F$2501>0)),Nike_Sales_Uncleaned!F7)} -> 1 | G7: {=IF(OR(Nike_Sales_Uncleaned!G7="",Nike_Sales_Uncleaned!G7<=0),MEDIAN(_xlfn._xlws.FILTER(Nike_Sales_Uncleaned!$G$2:$G$2501,Nike_Sales_Uncleaned!$G$2:$G$2501>0)),Nike_Sales_Uncleaned!G7)} -> 7363.96 | H7: =IF(Nike_Sales_Uncleaned!H7="",0,IF(AND(Nike_Sales_Uncleaned!H7>=0,Nike_Sales_Uncleaned!H7<=1),Nike_Sales_Uncleaned!H7,0)) -> 0 | I7: 0 | J7: =IF(Nike_Sales_Uncleaned[[#This Row],[Order_Date]]="","",Nike_Sales_Uncleaned[[#This Row],[Order_Date]]) | K7: Retail | L7: Delhi | M7: 1415.98
A8: 2006 | B8: Men | C8: Training | D8: SuperRep Go | E8: =IF(Nike_Sales_Uncleaned!E8="","NA",IF(OR(Nike_Sales_Uncleaned!E8=0,Nike_Sales_Uncleaned!E8=-1),"NA",UPPER(Nike_Sales_Uncleaned!E8))) -> M | F8: {=IF(Nike_Sales_Uncleaned!F8="",MEDIAN(_xlfn._xlws.FILTER(Nike_Sales_Uncleaned!$F$2:$F$2501,Nike_Sales_Uncleaned!$F$2:$F$2501>0)),Nike_Sales_Uncleaned!F8)} -> 2 | G8: {=IF(OR(Nike_Sales_Uncleaned!G8="",Nike_Sales_Uncleaned!G8<=0),MEDIAN(_xlfn._xlws.FILTER(Nike_Sales_Uncleaned!$G$2:$G$2501,Nike_Sales_Uncleaned!$G$2:$G$2501>0)),Nike_Sales_Uncleaned!G8)} -> 6819.78 | H8: =IF(Nike_Sales_Uncleaned!H8="",0,IF(AND(Nike_Sales_Uncleaned!H8>=0,Nike_Sales_Uncleaned!H8<=1),Nike_Sales_Uncleaned!H8,0)) -> 0 | I8: 0 | J8: =IF(Nike_Sales_Uncleaned[[#This Row],[Order_Date]]="","",Nike_Sales_Uncleaned[[#This Row],[Order_Date]]) -> 45812 | K8: Online | L8: Bangalore | M8: 1802.09
A9: 2007 | B9: Kids | C9: Training | D9: SuperRep Go | E9: =IF(Nike_Sales_Uncleaned!E9="","NA",IF(OR(Nike_Sales_Uncleaned!E9=0,Nike_Sales_Uncleaned!E9=-1),"NA",UPPER(Nike_Sales_Uncleaned!E9))) -> M | F9: {=IF(Nike_Sales_Uncleaned!F9="",MEDIAN(_xlfn._xlws.FILTER(Nike_Sales_Uncleaned!$F$2:$F$2501,Nike_Sales_Uncleaned!$F$2:$F$2501>0)),Nike_Sales_Uncleaned!F9)} -> 1 | G9: {=IF(OR(Nike_Sales_Uncleaned!G9="",Nike_Sales_Uncleaned!G9<=0),MEDIAN(_xlfn._xlws.FILTER(Nike_Sales_Uncleaned!$G$2:$G$2501,Nike_Sales_Uncleaned!$G$2:$G$2501>0)),Nike_Sales_Uncleaned!G9)} -> 6110.03 | H9: =IF(Nike_Sales_Uncleaned!H9="",0,IF(AND(Nike_Sales_Uncleaned!H9>=0,Nike_Sales_Uncleaned!H9<=1),Nike_Sales_Uncleaned!H9,0)) -> 0.32 | I9: 0 | J9: =IF(Nike_Sales_Uncleaned[[#This Row],[Order_Date]]="","",Nike_Sales_Uncleaned[[#This Row],[Order_Date]]) | K9: Retail | L9: Bangalore | M9: 2928.36
A10: 2008 | B10: Women | C10: Soccer | D10: Premier III | E10: =IF(Nike_Sales_Uncleaned!E10="","NA",IF(OR(Nike_Sales_Uncleaned!E10=0,Nike_Sales_Uncleaned!E10=-1),"NA",UPPER(Nike_Sales_Uncleaned!E10))) -> 11 | F10: {=IF(Nike_Sales_Uncleaned!F10="",MEDIAN(_xlfn._xlws.FILTER(Nike_Sales_Uncleaned!$F$2:$F$2501,Nike_Sales_Uncleaned!$F$2:$F$2501>0)),Nike_Sales_Uncleaned!F10)} -> -1 | G10: {=IF(OR(Nike_Sales_Uncleaned!G10="",Nike_Sales_Uncleaned!G10<=0),MEDIAN(_xlfn._xlws.FILTER(Nike_Sales_Uncleaned!$G$2:$G$2501,Nike_Sales_Uncleaned!$G$2:$G$2501>0)),Nike_Sales_Uncleaned!G10)} -> 6110.03 | H10: =IF(Nike_Sales_Uncleaned!H10="",0,IF(AND(Nike_Sales_Uncleaned!H10>=0,Nike_Sales_Uncleaned!H10<=1),Nike_Sales_Uncleaned!H10,0)) -> 0 | I10: 0 | J10: =IF(Nike_Sales_Uncleaned[[#This Row],[Order_Date]]="","",Nike_Sales_Uncleaned[[#This Row],[Order_Date]]) -> 45576 | K10: Online | L10: Hyderabad | M10: -731.18
A11: 2009 | B11: Men | C11: Soccer | D11: Mercurial Superfly | E11: =IF(Nike_Sales_Uncleaned!E11="","NA",IF(OR(Nike_Sales_Uncleaned!E11=0,Nike_Sales_Uncleaned!E11=-1),"NA",UPPER(Nike_Sales_Uncleaned!E11))) -> M | F11: {=IF(Nike_Sales_Uncleaned!F11="",MEDIAN(_xlfn._xlws.FILTER(Nike_Sales_Uncleaned!$F$2:$F$2501,Nike_Sales_Uncleaned!$F$2:$F$2501>0)),Nike_Sales_Uncleaned!F11)} -> 4 | G11: {=IF(OR(Nike_Sales_Uncleaned!G11="",Nike_Sales_Uncleaned!G11<=0),MEDIAN(_xlfn._xlws.FILTER(Nike_Sales_Uncleaned!$G$2:$G$2501,Nike_Sales_Uncleaned!$G$2:$G$2501>0)),Nike_Sales_Uncleaned!G11)} -> 6110.03 | H11: =IF(Nike_Sales_Uncleaned!H11="",0,IF(AND(Nike_Sales_Uncleaned!H11>=0,Nike_Sales_Uncleaned!H11<=1),Nike_Sales_Uncleaned!H11,0)) -> 0 | I11: 0 | J11: =IF(Nike_Sales_Uncleaned[[#This Row],[Order_Date]]="","",Nike_Sales_Uncleaned[[#This Row],[Order_Date]]) | K11: Online | L11: Pune | M11: 3929.61
A12: 2010 | B12: Kids | C12: Lifestyle | D12: Waffle One | E12: =IF(Nike_Sales_Uncleaned!E12="","NA",IF(OR(Nike_Sales_Uncleaned!E12=0,Nike_Sales_Uncleaned!E12=-1),"NA",UPPER(Nike_Sales_Uncleaned!E12))) -> L | F12: {=IF(Nike_Sales_Uncleaned!F12="",MEDIAN(_xlfn._xlws.FILTER(Nike_Sales_Uncleaned!$F$2:$F$2501,Nike_Sales_Uncleaned!$F$2:$F$2501>0)),Nike_Sales_Uncleaned!F12)} -> 1 | G12: {=IF(OR(Nike_Sales_Uncleaned!G12="",Nike_Sales_Uncleaned!G12<=0),MEDIAN(_xlfn._xlws.FILTER(Nike_Sales_Uncleaned!$G$2:$G$2501,Nike_Sales_Uncleaned!$G$2:$G$2501>0)),Nike_Sales_Uncleaned!G12)} -> 7949.83 | H12: =IF(Nike_Sales_Uncleaned!H12="",0,IF(AND(Nike_Sales_Uncleaned!H12>=0,Nike_Sales_Uncleaned!H12<=1),Nike_Sales_Uncleaned!H12,0)) -> 0 | I12: 0 | J12: =IF(Nike_Sales_Uncleaned[[#This Row],[Order_Date]]="","",Nike_Sales_Uncleaned[[#This Row],[Order_Date]]) -> 45673 | K12: Online | L12: Pune | M12: 1965.56
A13: 2011 | B13: Women | C13: Training | D13: Flex Trainer | E13: =IF(Nike_Sales_Uncleaned!E13="","NA",IF(OR(Nike_Sales_Uncleaned!E13=0,Nike_Sales_Uncleaned!E13=-1),"NA",UPPER(Nike_Sales_Uncleaned!E13))) -> L | F13: {=IF(Nike_Sales_Uncleaned!F13="",MEDIAN(_xlfn._xlws.FILTER(Nike_Sales_Uncleaned!$F$2:$F$2501,Nike_Sales_Uncleaned!$F$2:$F$2501>0)),Nike_Sales_Uncleaned!F13)} -> -1 | G13: {=IF(OR(Nike_Sales_Uncleaned!G13="",Nike_Sales_Uncleaned!G13<=0),MEDIAN(_xlfn._xlws.FILTER(Nike_Sales_Uncleaned!$G$2:$G$2501,Nike_Sales_Uncleaned!$G$2:$G$2501>0)),Nike_Sales_Uncleaned!G13)} -> 9586.08 | H13: =IF(Nike_Sales_Uncleaned!H13="",0,IF(AND(Nike_Sales_Uncleaned!H13>=0,Nike_Sales_Uncleaned!H13<=1),Nike_Sales_Uncleaned!H13,0)) -> 0 | I13: 0 | J13: =IF(Nike_Sales_Uncleaned[[#This Row],[Order_Date]]="","",Nike_Sales_Uncleaned[[#This Row],[Order_Date]]) | K13: Retail | L13: Hyderabad | M13: 1667.08
... A19: 2017 | B19: Women | C19: Basketball | D19: Air Jordan | E19: =IF(Nike_Sales_Uncleaned!E19="","NA",IF(OR(Nike_Sales_Uncleaned!E19=0,Nike_Sales_Uncleaned!E19=-1),"NA",UPPER(Nike_Sales_Uncleaned!E19))) -> 9 | F19: {=IF(Nike_Sales_Uncleaned!F19="",MEDIAN(_xlfn._xlws.FILTER(Nike_Sales_Uncleaned!$F$2:$F$2501,Nike_Sales_Uncleaned!$F$2:$F$2501>0)),Nike_Sales_Uncleaned!F19)} -> 4 | G19: {=IF(OR(Nike_Sales_Uncleaned!G19="",Nike_Sales_Uncleaned!G19<=0),MEDIAN(_xlfn._xlws.FILTER(Nike_Sales_Uncleaned!$G$2:$G$2501,Nike_Sales_Uncleaned!$G$2:$G$2501>0)),Nike_Sales_Uncleaned!G19)} -> 6110.03 | H19: =IF(Nike_Sales_Uncleaned!H19="",0,IF(AND(Nike_Sales_Uncleaned!H19>=0,Nike_Sales_Uncleaned!H19<=1),Nike_Sales_Uncleaned!H19,0)) -> 0 | I19: 0 | J19: =IF(Nike_Sales_Uncleaned[[#This Row],[Order_Date]]="","",Nike_Sales_Uncleaned[[#This Row],[Order_Date]]) -> 45733 | K19: Retail | L19: Delhi | M19: 1946.24
A20: 2019 | B20: Kids | C20: Running | D20: Air Zoom | E20: =IF(Nike_Sales_Uncleaned!E21="","NA",IF(OR(Nike_Sales_Uncleaned!E21=0,Nike_Sales_Uncleaned!E21=-1),"NA",UPPER(Nike_Sales_Uncleaned!E21))) -> 6 | F20: {=IF(Nike_Sales_Uncleaned!F21="",MEDIAN(_xlfn._xlws.FILTER(Nike_Sales_Uncleaned!$F$2:$F$2501,Nike_Sales_Uncleaned!$F$2:$F$2501>0)),Nike_Sales_Uncleaned!F21)} -> 0 | G20: {=IF(OR(Nike_Sales_Uncleaned!G21="",Nike_Sales_Uncleaned!G21<=0),MEDIAN(_xlfn._xlws.FILTER(Nike_Sales_Uncleaned!$G$2:$G$2501,Nike_Sales_Uncleaned!$G$2:$G$2501>0)),Nike_Sales_Uncleaned!G21)} -> 3424.06 | H20: =IF(Nike_Sales_Uncleaned!H21="",0,IF(AND(Nike_Sales_Uncleaned!H21>=0,Nike_Sales_Uncleaned!H21<=1),Nike_Sales_Uncleaned!H21,0)) -> 0.32 | I20: 0 | J20: =IF(Nike_Sales_Uncleaned[[#This Row],[Order_Date]]="","",Nike_Sales_Uncleaned[[#This Row],[Order_Date]]) | K20: Online | L20: Hyderabad | M20: 1915.24
A21: 2020 | B21: Kids | C21: Soccer | D21: Tiempo Legend | E21: =IF(Nike_Sales_Uncleaned!E22="","NA",IF(OR(Nike_Sales_Uncleaned!E22=0,Nike_Sales_Uncleaned!E22=-1),"NA",UPPER(Nike_Sales_Uncleaned!E22))) -> L | F21: {=IF(Nike_Sales_Uncleaned!F22="",MEDIAN(_xlfn._xlws.FILTER(Nike_Sales_Uncleaned!$F$2:$F$2501,Nike_Sales_Uncleaned!$F$2:$F$2501>0)),Nike_Sales_Uncleaned!F22)} -> -1 | G21: {=IF(OR(Nike_Sales_Uncleaned!G22="",Nike_Sales_Uncleaned!G22<=0),MEDIAN(_xlfn._xlws.FILTER(Nike_Sales_Uncleaned!$G$2:$G$2501,Nike_Sales_Uncleaned!$G$2:$G$2501>0)),Nike_Sales_Uncleaned!G22)} -> 6110.03 | H21: =IF(Nike_Sales_Uncleaned!H22="",0,IF(AND(Nike_Sales_Uncleaned!H22>=0,Nike_Sales_Uncleaned!H22<=1),Nike_Sales_Uncleaned!H22,0)) -> 0.67 | I21: 0 | J21: =IF(Nike_Sales_Uncleaned[[#This Row],[Order_Date]]="","",Nike_Sales_Uncleaned[[#This Row],[Order_Date]]) -> 45674 | K21: Retail | L21: Mumbai | M21: 439.96
A22: 2021 | B22: Men | C22: Running | D22: Free RN | E22: =IF(Nike_Sales_Uncleaned!E23="","NA",IF(OR(Nike_Sales_Uncleaned!E23=0,Nike_Sales_Uncleaned!E23=-1),"NA",UPPER(Nike_Sales_Uncleaned!E23))) -> L | F22: {=IF(Nike_Sales_Uncleaned!F23="",MEDIAN(_xlfn._xlws.FILTER(Nike_Sales_Uncleaned!$F$2:$F$2501,Nike_Sales_Uncleaned!$F$2:$F$2501>0)),Nike_Sales_Uncleaned!F23)} -> -1 | G22: {=IF(OR(Nike_Sales_Uncleaned!G23="",Nike_Sales_Uncleaned!G23<=0),MEDIAN(_xlfn._xlws.FILTER(Nike_Sales_Uncleaned!$G$2:$G$2501,Nike_Sales_Uncleaned!$G$2:$G$2501>0)),Nike_Sales_Uncleaned!G23)} -> 7086.7 | H22: =IF(Nike_Sales_Uncleaned!H23="",0,IF(AND(Nike_Sales_Uncleaned!H23>=0,Nike_Sales_Uncleaned!H23<=1),Nike_Sales_Uncleaned!H23,0)) -> 0.66 | I22: -2409.48 | J22: =IF(Nike_Sales_Uncleaned[[#This Row],[Order_Date]]="","",Nike_Sales_Uncleaned[[#This Row],[Order_Date]]) -> 45744 | K22: Retail | L22: Hyderabad | M22: -1120.49
A23: 2022 | B23: Women | C23: Soccer | D23: Premier III | E23: =IF(Nike_Sales_Uncleaned!E24="","NA",IF(OR(Nike_Sales_Uncleaned!E24=0,Nike_Sales_Uncleaned!E24=-1),"NA",UPPER(Nike_Sales_Uncleaned!E24))) -> M | F23: {=IF(Nike_Sales_Uncleaned!F24="",MEDIAN(_xlfn._xlws.FILTER(Nike_Sales_Uncleaned!$F$2:$F$2501,Nike_Sales_Uncleaned!$F$2:$F$2501>0)),Nike_Sales_Uncleaned!F24)} -> 2 | G23: {=IF(OR(Nike_Sales_Uncleaned!G24="",Nike_Sales_Uncleaned!G24<=0),MEDIAN(_xlfn._xlws.FILTER(Nike_Sales_Uncleaned!$G$2:$G$2501,Nike_Sales_Uncleaned!$G$2:$G$2501>0)),Nike_Sales_Uncleaned!G24)} -> 6110.03 | H23: =IF(Nike_Sales_Uncleaned!H24="",0,IF(AND(Nike_Sales_Uncleaned!H24>=0,Nike_Sales_Uncleaned!H24<=1),Nike_Sales_Uncleaned!H24,0)) -> 0 | I23: 0 | J23: =IF(Nike_Sales_Uncleaned[[#This Row],[Order_Date]]="","",Nike_Sales_Uncleaned[[#This Row],[Order_Date]]) -> 45615 | K23: Online | L23: Pune | M23: 3427.16
A24: 2023 | B24: Men | C24: Lifestyle | D24: Waffle One | E24: =IF(Nike_Sales_Uncleaned!E25="","NA",IF(OR(Nike_Sales_Uncleaned!E25=0,Nike_Sales_Uncleaned!E25=-1),"NA",UPPER(Nike_Sales_Uncleaned!E25))) -> M | F24: {=IF(Nike_Sales_Uncleaned!F25="",MEDIAN(_xlfn._xlws.FILTER(Nike_Sales_Uncleaned!$F$2:$F$2501,Nike_Sales_Uncleaned!$F$2:$F$2501>0)),Nike_Sales_Uncleaned!F25)} -> 2 | G24: {=IF(OR(Nike_Sales_Uncleaned!G25="",Nike_Sales_Uncleaned!G25<=0),MEDIAN(_xlfn._xlws.FILTER(Nike_Sales_Uncleaned!$G$2:$G$2501,Nike_Sales_Uncleaned!$G$2:$G$2501>0)),Nike_Sales_Uncleaned!G25)} -> 5003.95 | H24: =IF(Nike_Sales_Uncleaned!H25="",0,IF(AND(Nike_Sales_Uncleaned!H25>=0,Nike_Sales_Uncleaned!H25<=1),Nike_Sales_Uncleaned!H25,0)) -> 0 | I24: 0 | J24: =IF(Nike_Sales_Uncleaned[[#This Row],[Order_Date]]="","",Nike_Sales_Uncleaned[[#This Row],[Order_Date]]) -> 45559 | K24: Online | L24: Mumbai | M24: 1498.37
A25: 2024 | B25: Kids | C25: Training | D25: SuperRep Go | E25: =IF(Nike_Sales_Uncleaned!E26="","NA",IF(OR(Nike_Sales_Uncleaned!E26=0,Nike_Sales_Uncleaned!E26=-1),"NA",UPPER(Nike_Sales_Uncleaned!E26))) -> XL | F25: {=IF(Nike_Sales_Uncleaned!F26="",MEDIAN(_xlfn._xlws.FILTER(Nike_Sales_Uncleaned!$F$2:$F$2501,Nike_Sales_Uncleaned!$F$2:$F$2501>0)),Nike_Sales_Uncleaned!F26)} -> 0 | G25: {=IF(OR(Nike_Sales_Uncleaned!G26="",Nike_Sales_Uncleaned!G26<=0),MEDIAN(_xlfn._xlws.FILTER(Nike_Sales_Uncleaned!$G$2:$G$2501,Nike_Sales_Uncleaned!$G$2:$G$2501>0)),Nike_Sales_Uncleaned!G26)} -> 6110.03 | H25: =IF(Nike_Sales_Uncleaned!H26="",0,IF(AND(Nike_Sales_Uncleaned!H26>=0,Nike_Sales_Uncleaned!H26<=1),Nike_Sales_Uncleaned!H26,0)) -> 0.5 | I25: 0 | J25: =IF(Nike_Sales_Uncleaned[[#This Row],[Order_Date]]="","",Nike_Sales_Uncleaned[[#This Row],[Order_Date]]) -> 45667 | K25: Retail | L25: Bangalore | M25: 1842.35
A26: 2025 | B26: Women | C26: Basketball | D26: Kyrie Flytrap | E26: =IF(Nike_Sales_Uncleaned!E27="","NA",IF(OR(Nike_Sales_Uncleaned!E27=0,Nike_Sales_Uncleaned!E27=-1),"NA",UPPER(Nike_Sales_Uncleaned!E27))) -> M | F26: {=IF(Nike_Sales_Uncleaned!F27="",MEDIAN(_xlfn._xlws.FILTER(Nike_Sales_Uncleaned!$F$2:$F$2501,Nike_Sales_Uncleaned!$F$2:$F$2501>0)),Nike_Sales_Uncleaned!F27)} -> 3 | G26: {=IF(OR(Nike_Sales_Uncleaned!G27="",Nike_Sales_Uncleaned!G27<=0),MEDIAN(_xlfn._xlws.FILTER(Nike_Sales_Uncleaned!$G$2:$G$2501,Nike_Sales_Uncleaned!$G$2:$G$2501>0)),Nike_Sales_Uncleaned!G27)} -> 9820.5 | H26: =IF(Nike_Sales_Uncleaned!H27="",0,IF(AND(Nike_Sales_Uncleaned!H27>=0,Nike_Sales_Uncleaned!H27<=1),Nike_Sales_Uncleaned!H27,0)) -> 0 | I26: 0 | J26: =IF(Nike_Sales_Uncleaned[[#This Row],[Order_Date]]="","",Nike_Sales_Uncleaned[[#This Row],[Order_Date]]) -> 45654 | K26: Retail | L26: Mumbai | M26: 1900.15
A27: 2026 | B27: Kids | C27: Lifestyle | D27: Blazer Mid | E27: =IF(Nike_Sales_Uncleaned!E28="","NA",IF(OR(Nike_Sales_Uncleaned!E28=0,Nike_Sales_Uncleaned!E28=-1),"NA",UPPER(Nike_Sales_Uncleaned!E28))) -> XL | F27: {=IF(Nike_Sales_Uncleaned!F28="",MEDIAN(_xlfn._xlws.FILTER(Nike_Sales_Uncleaned!$F$2:$F$2501,Nike_Sales_Uncleaned!$F$2:$F$2501>0)),Nike_Sales_Uncleaned!F28)} -> 1 | G27: {=IF(OR(Nike_Sales_Uncleaned!G28="",Nike_Sales_Uncleaned!G28<=0),MEDIAN(_xlfn._xlws.FILTER(Nike_Sales_Uncleaned!$G$2:$G$2501,Nike_Sales_Uncleaned!$G$2:$G$2501>0)),Nike_Sales_Uncleaned!G28)} -> 6110.03 | H27: =IF(Nike_Sales_Uncleaned!H28="",0,IF(AND(Nike_Sales_Uncleaned!H28>=0,Nike_Sales_Uncleaned!H28<=1),Nike_Sales_Uncleaned!H28,0)) -> 0.16 | I27: 0 | J27: =IF(Nike_Sales_Uncleaned[[#This Row],[Order_Date]]="","",Nike_Sales_Uncleaned[[#This Row],[Order_Date]]) | K27: Retail | L27: Kolkata | M27: 2301.64
A28: 2027 | B28: Men | C28: Basketball | D28: Zoom Freak | E28: =IF(Nike_Sales_Uncleaned!E29="","NA",IF(OR(Nike_Sales_Uncleaned!E29=0,Nike_Sales_Uncleaned!E29=-1),"NA",UPPER(Nike_Sales_Uncleaned!E29))) -> XL | F28: {=IF(Nike_Sales_Uncleaned!F29="",MEDIAN(_xlfn._xlws.FILTER(Nike_Sales_Uncleaned!$F$2:$F$2501,Nike_Sales_Uncleaned!$F$2:$F$2501>0)),Nike_Sales_Uncleaned!F29)} -> 2 | G28: {=IF(OR(Nike_Sales_Uncleaned!G29="",Nike_Sales_Uncleaned!G29<=0),MEDIAN(_xlfn._xlws.FILTER(Nike_Sales_Uncleaned!$G$2:$G$2501,Nike_Sales_Uncleaned!$G$2:$G$2501>0)),Nike_Sales_Uncleaned!G29)} -> 6110.03 | H28: =IF(Nike_Sales_Uncleaned!H29="",0,IF(AND(Nike_Sales_Uncleaned!H29>=0,Nike_Sales_Uncleaned!H29<=1),Nike_Sales_Uncleaned!H29,0)) -> 0.22 | I28: 0 | J28: =IF(Nike_Sales_Uncleaned[[#This Row],[Order_Date]]="","",Nike_Sales_Uncleaned[[#This Row],[Order_Date]]) -> 45514 | K28: Online | L28: Pune | M28: -138.74
A29: 2028 | B29: Men | C29: Training | D29: Flex Trainer | E29: =IF(Nike_Sales_Uncleaned!E30="","NA",IF(OR(Nike_Sales_Uncleaned!E30=0,Nike_Sales_Uncleaned!E30=-1),"NA",UPPER(Nike_Sales_Uncleaned!E30))) -> 12 | F29: {=IF(Nike_Sales_Uncleaned!F30="",MEDIAN(_xlfn._xlws.FILTER(Nike_Sales_Uncleaned!$F$2:$F$2501,Nike_Sales_Uncleaned!$F$2:$F$2501>0)),Nike_Sales_Uncleaned!F30)} -> 2 | G29: {=IF(OR(Nike_Sales_Uncleaned!G30="",Nike_Sales_Uncleaned!G30<=0),MEDIAN(_xlfn._xlws.FILTER(Nike_Sales_Uncleaned!$G$2:$G$2501,Nike_Sales_Uncleaned!$G$2:$G$2501>0)),Nike_Sales_Uncleaned!G30)} -> 3270.23 | H29: =IF(Nike_Sales_Uncleaned!H30="",0,IF(AND(Nike_Sales_Uncleaned!H30>=0,Nike_Sales_Uncleaned!H30<=1),Nike_Sales_Uncleaned!H30,0)) -> 0 | I29: 0 | J29: =IF(Nike_Sales_Uncleaned[[#This Row],[Order_Date]]="","",Nike_Sales_Uncleaned[[#This Row],[Order_Date]]) | K29: Retail | L29: Delhi | M29: -946.86
A30: 2029 | B30: Men | C30: Training | D30: ZoomX Invincible | E30: =IF(Nike_Sales_Uncleaned!E31="","NA",IF(OR(Nike_Sales_Uncleaned!E31=0,Nike_Sales_Uncleaned!E31=-1),"NA",UPPER(Nike_Sales_Uncleaned!E31))) -> 12 | F30: {=IF(Nike_Sales_Uncleaned!F31="",MEDIAN(_xlfn._xlws.FILTER(Nike_Sales_Uncleaned!$F$2:$F$2501,Nike_Sales_Uncleaned!$F$2:$F$2501>0)),Nike_Sales_Uncleaned!F31)} -> 0 | G30: {=IF(OR(Nike_Sales_Uncleaned!G31="",Nike_Sales_Uncleaned!G31<=0),MEDIAN(_xlfn._xlws.FILTER(Nike_Sales_Uncleaned!$G$2:$G$2501,Nike_Sales_Uncleaned!$G$2:$G$2501>0)),Nike_Sales_Uncleaned!G31)} -> 6110.03 | H30: =IF(Nike_Sales_Uncleaned!H31="",0,IF(AND(Nike_Sales_Uncleaned!H31>=0,Nike_Sales_Uncleaned!H31<=1),Nike_Sales_Uncleaned!H31,0)) -> 0 | I30: 0 | J30: =IF(Nike_Sales_Uncleaned[[#This Row],[Order_Date]]="","",Nike_Sales_Uncleaned[[#This Row],[Order_Date]]) | K30: Online | L30: Bangalore | M30: -185.67
A31: 2030 | B31: Men | C31: Soccer | D31: Phantom GT | E31: =IF(Nike_Sales_Uncleaned!E32="","NA",IF(OR(Nike_Sales_Uncleaned!E32=0,Nike_Sales_Uncleaned!E32=-1),"NA",UPPER(Nike_Sales_Uncleaned!E32))) -> XL | F31: {=IF(Nike_Sales_Uncleaned!F32="",MEDIAN(_xlfn._xlws.FILTER(Nike_Sales_Uncleaned!$F$2:$F$2501,Nike_Sales_Uncleaned!$F$2:$F$2501>0)),Nike_Sales_Uncleaned!F32)} -> 2 | G31: {=IF(OR(Nike_Sales_Uncleaned!G32="",Nike_Sales_Uncleaned!G32<=0),MEDIAN(_xlfn._xlws.FILTER(Nike_Sales_Uncleaned!$G$2:$G$2501,Nike_Sales_Uncleaned!$G$2:$G$2501>0)),Nike_Sales_Uncleaned!G32)} -> 6110.03 | H31: =IF(Nike_Sales_Uncleaned!H32="",0,IF(AND(Nike_Sales_Uncleaned!H32>=0,Nike_Sales_Uncleaned!H32<=1),Nike_Sales_Uncleaned!H32,0)) -> 0 | I31: 0 | J31: =IF(Nike_Sales_Uncleaned[[#This Row],[Order_Date]]="","",Nike_Sales_Uncleaned[[#This Row],[Order_Date]]) -> 45227 | K31: Retail | L31: Hyderabad | M31: -122.93
... A40: 2039 | B40: Women | C40: Training | D40: Flex Trainer | E40: =IF(Nike_Sales_Uncleaned!E41="","NA",IF(OR(Nike_Sales_Uncleaned!E41=0,Nike_Sales_Uncleaned!E41=-1),"NA",UPPER(Nike_Sales_Uncleaned!E41))) -> M | F40: {=IF(Nike_Sales_Uncleaned!F41="",MEDIAN(_xlfn._xlws.FILTER(Nike_Sales_Uncleaned!$F$2:$F$2501,Nike_Sales_Uncleaned!$F$2:$F$2501>0)),Nike_Sales_Uncleaned!F41)} -> 2 | G40: {=IF(OR(Nike_Sales_Uncleaned!G41="",Nike_Sales_Uncleaned!G41<=0),MEDIAN(_xlfn._xlws.FILTER(Nike_Sales_Uncleaned!$G$2:$G$2501,Nike_Sales_Uncleaned!$G$2:$G$2501>0)),Nike_Sales_Uncleaned!G41)} -> 2767.7 | H40: =IF(Nike_Sales_Uncleaned!H41="",0,IF(AND(Nike_Sales_Uncleaned!H41>=0,Nike_Sales_Uncleaned!H41<=1),Nike_Sales_Uncleaned!H41,0)) -> 0.63 | I40: 0 | J40: =IF(Nike_Sales_Uncleaned[[#This Row],[Order_Date]]="","",Nike_Sales_Uncleaned[[#This Row],[Order_Date]]) | K40: Retail | L40: Hyderabad | M40: -336.3
A41: 2041 | B41: Kids | C41: Soccer | D41: Tiempo Legend | E41: =IF(Nike_Sales_Uncleaned!E43="","NA",IF(OR(Nike_Sales_Uncleaned!E43=0,Nike_Sales_Uncleaned!E43=-1),"NA",UPPER(Nike_Sales_Uncleaned!E43))) -> 12 | F41: {=IF(Nike_Sales_Uncleaned!F43="",MEDIAN(_xlfn._xlws.FILTER(Nike_Sales_Uncleaned!$F$2:$F$2501,Nike_Sales_Uncleaned!$F$2:$F$2501>0)),Nike_Sales_Uncleaned!F43)} -> 2 | G41: {=IF(OR(Nike_Sales_Uncleaned!G43="",Nike_Sales_Uncleaned!G43<=0),MEDIAN(_xlfn._xlws.FILTER(Nike_Sales_Uncleaned!$G$2:$G$2501,Nike_Sales_Uncleaned!$G$2:$G$2501>0)),Nike_Sales_Uncleaned!G43)} -> 5553.88 | H41: =IF(Nike_Sales_Uncleaned!H43="",0,IF(AND(Nike_Sales_Uncleaned!H43>=0,Nike_Sales_Uncleaned!H43<=1),Nike_Sales_Uncleaned!H43,0)) -> 0 | I41: 0 | J41: =IF(Nike_Sales_Uncleaned[[#This Row],[Order_Date]]="","",Nike_Sales_Uncleaned[[#This Row],[Order_Date]]) -> 45769 | K41: Online | L41: Hyderabad | M41: 2371.66
A42: 2042 | B42: Women | C42: Basketball | D42: Kyrie Flytrap | E42: =IF(Nike_Sales_Uncleaned!E44="","NA",IF(OR(Nike_Sales_Uncleaned!E44=0,Nike_Sales_Uncleaned!E44=-1),"NA",UPPER(Nike_Sales_Uncleaned!E44))) -> L | F42: {=IF(Nike_Sales_Uncleaned!F44="",MEDIAN(_xlfn._xlws.FILTER(Nike_Sales_Uncleaned!$F$2:$F$2501,Nike_Sales_Uncleaned!$F$2:$F$2501>0)),Nike_Sales_Uncleaned!F44)} -> 2 | G42: {=IF(OR(Nike_Sales_Uncleaned!G44="",Nike_Sales_Uncleaned!G44<=0),MEDIAN(_xlfn._xlws.FILTER(Nike_Sales_Uncleaned!$G$2:$G$2501,Nike_Sales_Uncleaned!$G$2:$G$2501>0)),Nike_Sales_Uncleaned!G44)} -> 6110.03 | H42: =IF(Nike_Sales_Uncleaned!H44="",0,IF(AND(Nike_Sales_Uncleaned!H44>=0,Nike_Sales_Uncleaned!H44<=1),Nike_Sales_Uncleaned!H44,0)) -> 0 | I42: 0 | J42: =IF(Nike_Sales_Uncleaned[[#This Row],[Order_Date]]="","",Nike_Sales_Uncleaned[[#This Row],[Order_Date]]) -> 45723 | K42: Online | L42: Hyderabad | M42: -862.16
A43: 2043 | B43: Men | C43: Soccer | D43: Premier III | E43: =IF(Nike_Sales_Uncleaned!E45="","NA",IF(OR(Nike_Sales_Uncleaned!E45=0,Nike_Sales_Uncleaned!E45=-1),"NA",UPPER(Nike_Sales_Uncleaned!E45))) -> XL | F43: {=IF(Nike_Sales_Uncleaned!F45="",MEDIAN(_xlfn._xlws.FILTER(Nike_Sales_Uncleaned!$F$2:$F$2501,Nike_Sales_Uncleaned!$F$2:$F$2501>0)),Nike_Sales_Uncleaned!F45)} -> 2 | G43: {=IF(OR(Nike_Sales_Uncleaned!G45="",Nike_Sales_Uncleaned!G45<=0),MEDIAN(_xlfn._xlws.FILTER(Nike_Sales_Uncleaned!$G$2:$G$2501,Nike_Sales_Uncleaned!$G$2:$G$2501>0)),Nike_Sales_Uncleaned!G45)} -> 3492.89 | H43: =IF(Nike_Sales_Uncleaned!H45="",0,IF(AND(Nike_Sales_Uncleaned!H45>=0,Nike_Sales_Uncleaned!H45<=1),Nike_Sales_Uncleaned!H45,0)) -> 0.77 | I43: 0 | J43: =IF(Nike_Sales_Uncleaned[[#This Row],[Order_Date]]="","",Nike_Sales_Uncleaned[[#This Row],[Order_Date]]) -> 45721 | K43: Retail | L43: Delhi | M43: 3770.75
A44: 2044 | B44: Kids | C44: Training | D44: SuperRep Go | E44: =IF(Nike_Sales_Uncleaned!E46="","NA",IF(OR(Nike_Sales_Uncleaned!E46=0,Nike_Sales_Uncleaned!E46=-1),"NA",UPPER(Nike_Sales_Uncleaned!E46))) -> NA | F44: {=IF(Nike_Sales_Uncleaned!F46="",MEDIAN(_xlfn._xlws.FILTER(Nike_Sales_Uncleaned!$F$2:$F$2501,Nike_Sales_Uncleaned!$F$2:$F$2501>0)),Nike_Sales_Uncleaned!F46)} -> 2 | G44: {=IF(OR(Nike_Sales_Uncleaned!G46="",Nike_Sales_Uncleaned!G46<=0),MEDIAN(_xlfn._xlws.FILTER(Nike_Sales_Uncleaned!$G$2:$G$2501,Nike_Sales_Uncleaned!$G$2:$G$2501>0)),Nike_Sales_Uncleaned!G46)} -> 6110.03 | H44: =IF(Nike_Sales_Uncleaned!H46="",0,IF(AND(Nike_Sales_Uncleaned!H46>=0,Nike_Sales_Uncleaned!H46<=1),Nike_Sales_Uncleaned!H46,0)) -> 0 | I44: 0 | J44: =IF(Nike_Sales_Uncleaned[[#This Row],[Order_Date]]="","",Nike_Sales_Uncleaned[[#This Row],[Order_Date]]) -> 45766 | K44: Online | L44: Delhi | M44: 2174.71
A45: 2045 | B45: Kids | C45: Lifestyle | D45: Dunk Low | E45: =IF(Nike_Sales_Uncleaned!E47="","NA",IF(OR(Nike_Sales_Uncleaned!E47=0,Nike_Sales_Uncleaned!E47=-1),"NA",UPPER(Nike_Sales_Uncleaned!E47))) -> XL | F45: {=IF(Nike_Sales_Uncleaned!F47="",MEDIAN(_xlfn._xlws.FILTER(Nike_Sales_Uncleaned!$F$2:$F$2501,Nike_Sales_Uncleaned!$F$2:$F$2501>0)),Nike_Sales_Uncleaned!F47)} -> 4 | G45: {=IF(OR(Nike_Sales_Uncleaned!G47="",Nike_Sales_Uncleaned!G47<=0),MEDIAN(_xlfn._xlws.FILTER(Nike_Sales_Uncleaned!$G$2:$G$2501,Nike_Sales_Uncleaned!$G$2:$G$2501>0)),Nike_Sales_Uncleaned!G47)} -> 6110.03 | H45: =IF(Nike_Sales_Uncleaned!H47="",0,IF(AND(Nike_Sales_Uncleaned!H47>=0,Nike_Sales_Uncleaned!H47<=1),Nike_Sales_Uncleaned!H47,0)) -> 0 | I45: 0 | J45: =IF(Nike_Sales_Uncleaned[[#This Row],[Order_Date]]="","",Nike_Sales_Uncleaned[[#This Row],[Order_Date]]) -> 45414 | K45: Retail | L45: Delhi | M45: 1833.94
A46: 2046 | B46: Kids | C46: Running | D46: Air Zoom | E46: =IF(Nike_Sales_Uncleaned!E48="","NA",IF(OR(Nike_Sales_Uncleaned!E48=0,Nike_Sales_Uncleaned!E48=-1),"NA",UPPER(Nike_Sales_Uncleaned!E48))) -> 12 | F46: {=IF(Nike_Sales_Uncleaned!F48="",MEDIAN(_xlfn._xlws.FILTER(Nike_Sales_Uncleaned!$F$2:$F$2501,Nike_Sales_Uncleaned!$F$2:$F$2501>0)),Nike_Sales_Uncleaned!F48)} -> 2 | G46: {=IF(OR(Nike_Sales_Uncleaned!G48="",Nike_Sales_Uncleaned!G48<=0),MEDIAN(_xlfn._xlws.FILTER(Nike_Sales_Uncleaned!$G$2:$G$2501,Nike_Sales_Uncleaned!$G$2:$G$2501>0)),Nike_Sales_Uncleaned!G48)} -> 6110.03 | H46: =IF(Nike_Sales_Uncleaned!H48="",0,IF(AND(Nike_Sales_Uncleaned!H48>=0,Nike_Sales_Uncleaned!H48<=1),Nike_Sales_Uncleaned!H48,0)) -> 0 | I46: 0 | J46: =IF(Nike_Sales_Uncleaned[[#This Row],[Order_Date]]="","",Nike_Sales_Uncleaned[[#This Row],[Order_Date]]) -> 45175 | K46: Online | L46: Kolkata | M46: 1284.33
A47: 2047 | B47: Women | C47: Training | D47: SuperRep Go | E47: =IF(Nike_Sales_Uncleaned!E49="","NA",IF(OR(Nike_Sales_Uncleaned!E49=0,Nike_Sales_Uncleaned!E49=-1),"NA",UPPER(Nike_Sales_Uncleaned!E49))) -> 10 | F47: {=IF(Nike_Sales_Uncleaned!F49="",MEDIAN(_xlfn._xlws.FILTER(Nike_Sales_Uncleaned!$F$2:$F$2501,Nike_Sales_Uncleaned!$F$2:$F$2501>0)),Nike_Sales_Uncleaned!F49)} -> 1 | G47: {=IF(OR(Nike_Sales_Uncleaned!G49="",Nike_Sales_Uncleaned!G49<=0),MEDIAN(_xlfn._xlws.FILTER(Nike_Sales_Uncleaned!$G$2:$G$2501,Nike_Sales_Uncleaned!$G$2:$G$2501>0)),Nike_Sales_Uncleaned!G49)} -> 8577.75 | H47: =IF(Nike_Sales_Uncleaned!H49="",0,IF(AND(Nike_Sales_Uncleaned!H49>=0,Nike_Sales_Uncleaned!H49<=1),Nike_Sales_Uncleaned!H49,0)) -> 0 | I47: 0 | J47: =IF(Nike_Sales_Uncleaned[[#This Row],[Order_Date]]="","",Nike_Sales_Uncleaned[[#This Row],[Order_Date]]) -> 45753 | K47: Retail | L47: Bangalore | M47: 2888.68
A48: 2048 | B48: Women | C48: Basketball | D48: Air Jordan | E48: =IF(Nike_Sales_Uncleaned!E50="","NA",IF(OR(Nike_Sales_Uncleaned!E50=0,Nike_Sales_Uncleaned!E50=-1),"NA",UPPER(Nike_Sales_Uncleaned!E50))) -> XL | F48: {=IF(Nike_Sales_Uncleaned!F50="",MEDIAN(_xlfn._xlws.FILTER(Nike_Sales_Uncleaned!$F$2:$F$2501,Nike_Sales_Uncleaned!$F$2:$F$2501>0)),Nike_Sales_Uncleaned!F50)} -> 2 | G48: {=IF(OR(Nike_Sales_Uncleaned!G50="",Nike_Sales_Uncleaned!G50<=0),MEDIAN(_xlfn._xlws.FILTER(Nike_Sales_Uncleaned!$G$2:$G$2501,Nike_Sales_Uncleaned!$G$2:$G$2501>0)),Nike_Sales_Uncleaned!G50)} -> 6110.03 | H48: =IF(Nike_Sales_Uncleaned!H50="",0,IF(AND(Nike_Sales_Uncleaned!H50>=0,Nike_Sales_Uncleaned!H50<=1),Nike_Sales_Uncleaned!H50,0)) -> 0 | I48: 0 | J48: =IF(Nike_Sales_Uncleaned[[#This Row],[Order_Date]]="","",Nike_Sales_Uncleaned[[#This Row],[Order_Date]]) | K48: Online | L48: Bangalore | M48: 2875.86
A49: 2049 | B49: Kids | C49: Soccer | D49: Tiempo Legend | E49: =IF(Nike_Sales_Uncleaned!E51="","NA",IF(OR(Nike_Sales_Uncleaned!E51=0,Nike_Sales_Uncleaned!E51=-1),"NA",UPPER(Nike_Sales_Uncleaned!E51))) -> L | F49: {=IF(Nike_Sales_Uncleaned!F51="",MEDIAN(_xlfn._xlws.FILTER(Nike_Sales_Uncleaned!$F$2:$F$2501,Nike_Sales_Uncleaned!$F$2:$F$2501>0)),Nike_Sales_Uncleaned!F51)} -> 1 | G49: {=IF(OR(Nike_Sales_Uncleaned!G51="",Nike_Sales_Uncleaned!G51<=0),MEDIAN(_xlfn._xlws.FILTER(Nike_Sales_Uncleaned!$G$2:$G$2501,Nike_Sales_Uncleaned!$G$2:$G$2501>0)),Nike_Sales_Uncleaned!G51)} -> 7767.2 | H49: =IF(Nike_Sales_Uncleaned!H51="",0,IF(AND(Nike_Sales_Uncleaned!H51>=0,Nike_Sales_Uncleaned!H51<=1),Nike_Sales_Uncleaned!H51,0)) -> 0 | I49: 0 | J49: =IF(Nike_Sales_Uncleaned[[#This Row],[Order_Date]]="","",Nike_Sales_Uncleaned[[#This Row],[Order_Date]]) -> 45456 | K49: Retail | L49: Pune | M49: 311.48
A50: 2050 | B50: Men | C50: Running | D50: Air Zoom | E50: =IF(Nike_Sales_Uncleaned!E52="","NA",IF(OR(Nike_Sales_Uncleaned!E52=0,Nike_Sales_Uncleaned!E52=-1),"NA",UPPER(Nike_Sales_Uncleaned!E52))) -> L | F50: {=IF(Nike_Sales_Uncleaned!F52="",MEDIAN(_xlfn._xlws.FILTER(Nike_Sales_Uncleaned!$F$2:$F$2501,Nike_Sales_Uncleaned!$F$2:$F$2501>0)),Nike_Sales_Uncleaned!F52)} -> 1 | G50: {=IF(OR(Nike_Sales_Uncleaned!G52="",Nike_Sales_Uncleaned!G52<=0),MEDIAN(_xlfn._xlws.FILTER(Nike_Sales_Uncleaned!$G$2:$G$2501,Nike_Sales_Uncleaned!$G$2:$G$2501>0)),Nike_Sales_Uncleaned!G52)} -> 6110.03 | H50: =IF(Nike_Sales_Uncleaned!H52="",0,IF(AND(Nike_Sales_Uncleaned!H52>=0,Nike_Sales_Uncleaned!H52<=1),Nike_Sales_Uncleaned!H52,0)) -> 0.57 | I50: 0 | J50: =IF(Nike_Sales_Uncleaned[[#This Row],[Order_Date]]="","",Nike_Sales_Uncleaned[[#This Row],[Order_Date]]) -> 45592 | K50: Retail | L50: Kolkata | M50: 682.12
A51: 2051 | B51: Women | C51: Basketball | D51: Air Jordan | E51: =IF(Nike_Sales_Uncleaned!E53="","NA",IF(OR(Nike_Sales_Uncleaned!E53=0,Nike_Sales_Uncleaned!E53=-1),"NA",UPPER(Nike_Sales_Uncleaned!E53))) -> XL | F51: {=IF(Nike_Sales_Uncleaned!F53="",MEDIAN(_xlfn._xlws.FILTER(Nike_Sales_Uncleaned!$F$2:$F$2501,Nike_Sales_Uncleaned!$F$2:$F$2501>0)),Nike_Sales_Uncleaned!F53)} -> 2 | G51: {=IF(OR(Nike_Sales_Uncleaned!G53="",Nike_Sales_Uncleaned!G53<=0),MEDIAN(_xlfn._xlws.FILTER(Nike_Sales_Uncleaned!$G$2:$G$2501,Nike_Sales_Uncleaned!$G$2:$G$2501>0)),Nike_Sales_Uncleaned!G53)} -> 6110.03 | H51: =IF(Nike_Sales_Uncleaned!H53="",0,IF(AND(Nike_Sales_Uncleaned!H53>=0,Nike_Sales_Uncleaned!H53<=1),Nike_Sales_Uncleaned!H53,0)) -> 0.37 | I51: 0 | J51: =IF(Nike_Sales_Uncleaned[[#This Row],[Order_Date]]="","",Nike_Sales_Uncleaned[[#This Row],[Order_Date]]) | K51: Retail | L51: Delhi | M51: 3135.98
A52: 2052 | B52: Men | C52: Training | D52: Flex Trainer | E52: =IF(Nike_Sales_Uncleaned!E54="","NA",IF(OR(Nike_Sales_Uncleaned!E54=0,Nike_Sales_Uncleaned!E54=-1),"NA",UPPER(Nike_Sales_Uncleaned!E54))) -> 10 | F52: {=IF(Nike_Sales_Uncleaned!F54="",MEDIAN(_xlfn._xlws.FILTER(Nike_Sales_Uncleaned!$F$2:$F$2501,Nike_Sales_Uncleaned!$F$2:$F$2501>0)),Nike_Sales_Uncleaned!F54)} -> 3 | G52: {=IF(OR(Nike_Sales_Uncleaned!G54="",Nike_Sales_Uncleaned!G54<=0),MEDIAN(_xlfn._xlws.FILTER(Nike_Sales_Uncleaned!$G$2:$G$2501,Nike_Sales_Uncleaned!$G$2:$G$2501>0)),Nike_Sales_Uncleaned!G54)} -> 9155.96 | H52: =IF(Nike_Sales_Uncleaned!H54="",0,IF(AND(Nike_Sales_Uncleaned!H54>=0,Nike_Sales_Uncleaned!H54<=1),Nike_Sales_Uncleaned!H54,0)) -> 0 | I52: 0 | J52: =IF(Nike_Sales_Uncleaned[[#This Row],[Order_Date]]="","",Nike_Sales_Uncleaned[[#This Row],[Order_Date]]) | K52: Retail | L52: Pune | M52: 2184.8
... A56: 2056 | B56: Men | C56: Running | D56: React Infinity | E56: =IF(Nike_Sales_Uncleaned!E58="","NA",IF(OR(Nike_Sales_Uncleaned!E58=0,Nike_Sales_Uncleaned!E58=-1),"NA",UPPER(Nike_Sales_Uncleaned!E58))) -> L | F56: {=IF(Nike_Sales_Uncleaned!F58="",MEDIAN(_xlfn._xlws.FILTER(Nike_Sales_Uncleaned!$F$2:$F$2501,Nike_Sales_Uncleaned!$F$2:$F$2501>0)),Nike_Sales_Uncleaned!F58)} -> 3 | G56: {=IF(OR(Nike_Sales_Uncleaned!G58="",Nike_Sales_Uncleaned!G58<=0),MEDIAN(_xlfn._xlws.FILTER(Nike_Sales_Uncleaned!$G$2:$G$2501,Nike_Sales_Uncleaned!$G$2:$G$2501>0)),Nike_Sales_Uncleaned!G58)} -> 6110.03 | H56: =IF(Nike_Sales_Uncleaned!H58="",0,IF(AND(Nike_Sales_Uncleaned!H58>=0,Nike_Sales_Uncleaned!H58<=1),Nike_Sales_Uncleaned!H58,0)) -> 0 | I56: 0 | J56: =IF(Nike_Sales_Uncleaned[[#This Row],[Order_Date]]="","",Nike_Sales_Uncleaned[[#This Row],[Order_Date]]) -> 45831 | K56: Retail | L56: Bangalore | M56: -244.44
A57: 2058 | B57: Women | C57: Training | D57: Flex Trainer | E57: =IF(Nike_Sales_Uncleaned!E60="","NA",IF(OR(Nike_Sales_Uncleaned!E60=0,Nike_Sales_Uncleaned!E60=-1),"NA",UPPER(Nike_Sales_Uncleaned!E60))) -> 11 | F57: {=IF(Nike_Sales_Uncleaned!F60="",MEDIAN(_xlfn._xlws.FILTER(Nike_Sales_Uncleaned!$F$2:$F$2501,Nike_Sales_Uncleaned!$F$2:$F$2501>0)),Nike_Sales_Uncleaned!F60)} -> 2 | G57: {=IF(OR(Nike_Sales_Uncleaned!G60="",Nike_Sales_Uncleaned!G60<=0),MEDIAN(_xlfn._xlws.FILTER(Nike_Sales_Uncleaned!$G$2:$G$2501,Nike_Sales_Uncleaned!$G$2:$G$2501>0)),Nike_Sales_Uncleaned!G60)} -> 4985.92 | H57: =IF(Nike_Sales_Uncleaned!H60="",0,IF(AND(Nike_Sales_Uncleaned!H60>=0,Nike_Sales_Uncleaned!H60<=1),Nike_Sales_Uncleaned!H60,0)) -> 0 | I57: 0 | J57: =IF(Nike_Sales_Uncleaned[[#This Row],[Order_Date]]="","",Nike_Sales_Uncleaned[[#This Row],[Order_Date]]) -> 45591 | K57: Online | L57: Kolkata | M57: 361.54
A58: 2059 | B58: Kids | C58: Soccer | D58: Phantom GT | E58: =IF(Nike_Sales_Uncleaned!E61="","NA",IF(OR(Nike_Sales_Uncleaned!E61=0,Nike_Sales_Uncleaned!E61=-1),"NA",UPPER(Nike_Sales_Uncleaned!E61))) -> NA | F58: {=IF(Nike_Sales_Uncleaned!F61="",MEDIAN(_xlfn._xlws.FILTER(Nike_Sales_Uncleaned!$F$2:$F$2501,Nike_Sales_Uncleaned!$F$2:$F$2501>0)),Nike_Sales_Uncleaned!F61)} -> -1 | G58: {=IF(OR(Nike_Sales_Uncleaned!G61="",Nike_Sales_Uncleaned!G61<=0),MEDIAN(_xlfn._xlws.FILTER(Nike_Sales_Uncleaned!$G$2:$G$2501,Nike_Sales_Uncleaned!$G$2:$G$2501>0)),Nike_Sales_Uncleaned!G61)} -> 9507.54 | H58: =IF(Nike_Sales_Uncleaned!H61="",0,IF(AND(Nike_Sales_Uncleaned!H61>=0,Nike_Sales_Uncleaned!H61<=1),Nike_Sales_Uncleaned!H61,0)) -> 0 | I58: 0 | J58: =IF(Nike_Sales_Uncleaned[[#This Row],[Order_Date]]="","",Nike_Sales_Uncleaned[[#This Row],[Order_Date]]) -> 45443 | K58: Retail | L58: Delhi | M58: 291.28
A59: 2060 | B59: Men | C59: Lifestyle | D59: Waffle One | E59: =IF(Nike_Sales_Uncleaned!E62="","NA",IF(OR(Nike_Sales_Uncleaned!E62=0,Nike_Sales_Uncleaned!E62=-1),"NA",UPPER(Nike_Sales_Uncleaned!E62))) -> L | F59: {=IF(Nike_Sales_Uncleaned!F62="",MEDIAN(_xlfn._xlws.FILTER(Nike_Sales_Uncleaned!$F$2:$F$2501,Nike_Sales_Uncleaned!$F$2:$F$2501>0)),Nike_Sales_Uncleaned!F62)} -> 2 | G59: {=IF(OR(Nike_Sales_Uncleaned!G62="",Nike_Sales_Uncleaned!G62<=0),MEDIAN(_xlfn._xlws.FILTER(Nike_Sales_Uncleaned!$G$2:$G$2501,Nike_Sales_Uncleaned!$G$2:$G$2501>0)),Nike_Sales_Uncleaned!G62)} -> 7979.26 | H59: =IF(Nike_Sales_Uncleaned!H62="",0,IF(AND(Nike_Sales_Uncleaned!H62>=0,Nike_Sales_Uncleaned!H62<=1),Nike_Sales_Uncleaned!H62,0)) -> 0 | I59: 0 | J59: =IF(Nike_Sales_Uncleaned[[#This Row],[Order_Date]]="","",Nike_Sales_Uncleaned[[#This Row],[Order_Date]]) -> 45549 | K59: Online | L59: Bangalore | M59: 2821.59
A60: 2061 | B60: Women | C60: Basketball | D60: LeBron 20 | E60: =IF(Nike_Sales_Uncleaned!E63="","NA",IF(OR(Nike_Sales_Uncleaned!E63=0,Nike_Sales_Uncleaned!E63=-1),"NA",UPPER(Nike_Sales_Uncleaned!E63))) -> L | F60: {=IF(Nike_Sales_Uncleaned!F63="",MEDIAN(_xlfn._xlws.FILTER(Nike_Sales_Uncleaned!$F$2:$F$2501,Nike_Sales_Uncleaned!$F$2:$F$2501>0)),Nike_Sales_Uncleaned!F63)} -> 2 | G60: {=IF(OR(Nike_Sales_Uncleaned!G63="",Nike_Sales_Uncleaned!G63<=0),MEDIAN(_xlfn._xlws.FILTER(Nike_Sales_Uncleaned!$G$2:$G$2501,Nike_Sales_Uncleaned!$G$2:$G$2501>0)),Nike_Sales_Uncleaned!G63)} -> 6110.03 | H60: =IF(Nike_Sales_Uncleaned!H63="",0,IF(AND(Nike_Sales_Uncleaned!H63>=0,Nike_Sales_Uncleaned!H63<=1),Nike_Sales_Uncleaned!H63,0)) -> 0 | I60: 0 | J60: =IF(Nike_Sales_Uncleaned[[#This Row],[Order_Date]]="","",Nike_Sales_Uncleaned[[#This Row],[Order_Date]]) | K60: Online | L60: Mumbai | M60: -501.68
A61: 2062 | B61: Men | C61: Basketball | D61: Air Jordan | E61: =IF(Nike_Sales_Uncleaned!E64="","NA",IF(OR(Nike_Sales_Uncleaned!E64=0,Nike_Sales_Uncleaned!E64=-1),"NA",UPPER(Nike_Sales_Uncleaned!E64))) -> NA | F61: {=IF(Nike_Sales_Uncleaned!F64="",MEDIAN(_xlfn._xlws.FILTER(Nike_Sales_Uncleaned!$F$2:$F$2501,Nike_Sales_Uncleaned!$F$2:$F$2501>0)),Nike_Sales_Uncleaned!F64)} -> 2 | G61: {=IF(OR(Nike_Sales_Uncleaned!G64="",Nike_Sales_Uncleaned!G64<=0),MEDIAN(_xlfn._xlws.FILTER(Nike_Sales_Uncleaned!$G$2:$G$2501,Nike_Sales_Uncleaned!$G$2:$G$2501>0)),Nike_Sales_Uncleaned!G64)} -> 6110.03 | H61: =IF(Nike_Sales_Uncleaned!H64="",0,IF(AND(Nike_Sales_Uncleaned!H64>=0,Nike_Sales_Uncleaned!H64<=1),Nike_Sales_Uncleaned!H64,0)) -> 0 | I61: 0 | J61: =IF(Nike_Sales_Uncleaned[[#This Row],[Order_Date]]="","",Nike_Sales_Uncleaned[[#This Row],[Order_Date]]) -> 45287 | K61: Online | L61: Bangalore | M61: 1823.91
A62: 2063 | B62: Women | C62: Basketball | D62: Air Jordan | E62: =IF(Nike_Sales_Uncleaned!E65="","NA",IF(OR(Nike_Sales_Uncleaned!E65=0,Nike_Sales_Uncleaned!E65=-1),"NA",UPPER(Nike_Sales_Uncleaned!E65))) -> M | F62: {=IF(Nike_Sales_Uncleaned!F65="",MEDIAN(_xlfn._xlws.FILTER(Nike_Sales_Uncleaned!$F$2:$F$2501,Nike_Sales_Uncleaned!$F$2:$F$2501>0)),Nike_Sales_Uncleaned!F65)} -> 1 | G62: {=IF(OR(Nike_Sales_Uncleaned!G65="",Nike_Sales_Uncleaned!G65<=0),MEDIAN(_xlfn._xlws.FILTER(Nike_Sales_Uncleaned!$G$2:$G$2501,Nike_Sales_Uncleaned!$G$2:$G$2501>0)),Nike_Sales_Uncleaned!G65)} -> 9751 | H62: =IF(Nike_Sales_Uncleaned!H65="",0,IF(AND(Nike_Sales_Uncleaned!H65>=0,Nike_Sales_Uncleaned!H65<=1),Nike_Sales_Uncleaned!H65,0)) -> 0.16 | I62: 8190.84 | J62: =IF(Nike_Sales_Uncleaned[[#This Row],[Order_Date]]="","",Nike_Sales_Uncleaned[[#This Row],[Order_Date]]) -> 45484 | K62: Retail | L62: Pune | M62: 1130.31
A63: 2064 | B63: Kids | C63: Running | D63: React Infinity | E63: =IF(Nike_Sales_Uncleaned!E66="","NA",IF(OR(Nike_Sales_Uncleaned!E66=0,Nike_Sales_Uncleaned!E66=-1),"NA",UPPER(Nike_Sales_Uncleaned!E66))) -> L | F63: {=IF(Nike_Sales_Uncleaned!F66="",MEDIAN(_xlfn._xlws.FILTER(Nike_Sales_Uncleaned!$F$2:$F$2501,Nike_Sales_Uncleaned!$F$2:$F$2501>0)),Nike_Sales_Uncleaned!F66)} -> 2 | G63: {=IF(OR(Nike_Sales_Uncleaned!G66="",Nike_Sales_Uncleaned!G66<=0),MEDIAN(_xlfn._xlws.FILTER(Nike_Sales_Uncleaned!$G$2:$G$2501,Nike_Sales_Uncleaned!$G$2:$G$2501>0)),Nike_Sales_Uncleaned!G66)} -> 7557.71 | H63: =IF(Nike_Sales_Uncleaned!H66="",0,IF(AND(Nike_Sales_Uncleaned!H66>=0,Nike_Sales_Uncleaned!H66<=1),Nike_Sales_Uncleaned!H66,0)) -> 0 | I63: 0 | J63: =IF(Nike_Sales_Uncleaned[[#This Row],[Order_Date]]="","",Nike_Sales_Uncleaned[[#This Row],[Order_Date]]) -> 45545 | K63: Online | L63: Bangalore | M63: 3277.44
A64: 2065 | B64: Women | C64: Lifestyle | D64: Waffle One | E64: =IF(Nike_Sales_Uncleaned!E67="","NA",IF(OR(Nike_Sales_Uncleaned!E67=0,Nike_Sales_Uncleaned!E67=-1),"NA",UPPER(Nike_Sales_Uncleaned!E67))) -> 10 | F64: {=IF(Nike_Sales_Uncleaned!F67="",MEDIAN(_xlfn._xlws.FILTER(Nike_Sales_Uncleaned!$F$2:$F$2501,Nike_Sales_Uncleaned!$F$2:$F$2501>0)),Nike_Sales_Uncleaned!F67)} -> 2 | G64: {=IF(OR(Nike_Sales_Uncleaned!G67="",Nike_Sales_Uncleaned!G67<=0),MEDIAN(_xlfn._xlws.FILTER(Nike_Sales_Uncleaned!$G$2:$G$2501,Nike_Sales_Uncleaned!$G$2:$G$2501>0)),Nike_Sales_Uncleaned!G67)} -> 6110.03 | H64: =IF(Nike_Sales_Uncleaned!H67="",0,IF(AND(Nike_Sales_Uncleaned!H67>=0,Nike_Sales_Uncleaned!H67<=1),Nike_Sales_Uncleaned!H67,0)) -> 0.78 | I64: 0 | J64: =IF(Nike_Sales_Uncleaned[[#This Row],[Order_Date]]="","",Nike_Sales_Uncleaned[[#This Row],[Order_Date]]) -> 45814 | K64: Retail | L64: Hyderabad | M64: 21.58
A65: 2066 | B65: Men | C65: Soccer | D65: Phantom GT | E65: =IF(Nike_Sales_Uncleaned!E68="","NA",IF(OR(Nike_Sales_Uncleaned!E68=0,Nike_Sales_Uncleaned!E68=-1),"NA",UPPER(Nike_Sales_Uncleaned!E68))) -> XL | F65: {=IF(Nike_Sales_Uncleaned!F68="",MEDIAN(_xlfn._xlws.FILTER(Nike_Sales_Uncleaned!$F$2:$F$2501,Nike_Sales_Uncleaned!$F$2:$F$2501>0)),Nike_Sales_Uncleaned!F68)} -> -1 | G65: {=IF(OR(Nike_Sales_Uncleaned!G68="",Nike_Sales_Uncleaned!G68<=0),MEDIAN(_xlfn._xlws.FILTER(Nike_Sales_Uncleaned!$G$2:$G$2501,Nike_Sales_Uncleaned!$G$2:$G$2501>0)),Nike_Sales_Uncleaned!G68)} -> 5259.05 | H65: =IF(Nike_Sales_Uncleaned!H68="",0,IF(AND(Nike_Sales_Uncleaned!H68>=0,Nike_Sales_Uncleaned!H68<=1),Nike_Sales_Uncleaned!H68,0)) -> 0 | I65: 0 | J65: =IF(Nike_Sales_Uncleaned[[#This Row],[Order_Date]]="","",Nike_Sales_Uncleaned[[#This Row],[Order_Date]]) -> 45541 | K65: Online | L65: Mumbai | M65: 1022.82
A66: 2067 | B66: Kids | C66: Basketball | D66: LeBron 20 | E66: =IF(Nike_Sales_Uncleaned!E69="","NA",IF(OR(Nike_Sales_Uncleaned!E69=0,Nike_Sales_Uncleaned!E69=-1),"NA",UPPER(Nike_Sales_Uncleaned!E69))) -> L | F66: {=IF(Nike_Sales_Uncleaned!F69="",MEDIAN(_xlfn._xlws.FILTER(Nike_Sales_Uncleaned!$F$2:$F$2501,Nike_Sales_Uncleaned!$F$2:$F$2501>0)),Nike_Sales_Uncleaned!F69)} -> 4 | G66: {=IF(OR(Nike_Sales_Uncleaned!G69="",Nike_Sales_Uncleaned!G69<=0),MEDIAN(_xlfn._xlws.FILTER(Nike_Sales_Uncleaned!$G$2:$G$2501,Nike_Sales_Uncleaned!$G$2:$G$2501>0)),Nike_Sales_Uncleaned!G69)} -> 3588.38 | H66: =IF(Nike_Sales_Uncleaned!H69="",0,IF(AND(Nike_Sales_Uncleaned!H69>=0,Nike_Sales_Uncleaned!H69<=1),Nike_Sales_Uncleaned!H69,0)) -> 0 | I66: 0 | J66: =IF(Nike_Sales_Uncleaned[[#This Row],[Order_Date]]="","",Nike_Sales_Uncleaned[[#This Row],[Order_Date]]) -> 45718 | K66: Online | L66: Kolkata | M66: 161.5
A67: 2068 | B67: Men | C67: Running | D67: Free RN | E67: =IF(Nike_Sales_Uncleaned!E70="","NA",IF(OR(Nike_Sales_Uncleaned!E70=0,Nike_Sales_Uncleaned!E70=-1),"NA",UPPER(Nike_Sales_Uncleaned!E70))) -> NA | F67: {=IF(Nike_Sales_Uncleaned!F70="",MEDIAN(_xlfn._xlws.FILTER(Nike_Sales_Uncleaned!$F$2:$F$2501,Nike_Sales_Uncleaned!$F$2:$F$2501>0)),Nike_Sales_Uncleaned!F70)} -> 4 | G67: {=IF(OR(Nike_Sales_Uncleaned!G70="",Nike_Sales_Uncleaned!G70<=0),MEDIAN(_xlfn._xlws.FILTER(Nike_Sales_Uncleaned!$G$2:$G$2501,Nike_Sales_Uncleaned!$G$2:$G$2501>0)),Nike_Sales_Uncleaned!G70)} -> 2553.29 | H67: =IF(Nike_Sales_Uncleaned!H70="",0,IF(AND(Nike_Sales_Uncleaned!H70>=0,Nike_Sales_Uncleaned!H70<=1),Nike_Sales_Uncleaned!H70,0)) -> 0 | I67: 0 | J67: =IF(Nike_Sales_Uncleaned[[#This Row],[Order_Date]]="","",Nike_Sales_Uncleaned[[#This Row],[Order_Date]]) -> 45333 | K67: Retail | L67: Mumbai | M67: 984.9
A68: 2069 | B68: Women | C68: Training | D68: SuperRep Go | E68: =IF(Nike_Sales_Uncleaned!E71="","NA",IF(OR(Nike_Sales_Uncleaned!E71=0,Nike_Sales_Uncleaned!E71=-1),"NA",UPPER(Nike_Sales_Uncleaned!E71))) -> NA | F68: {=IF(Nike_Sales_Uncleaned!F71="",MEDIAN(_xlfn._xlws.FILTER(Nike_Sales_Uncleaned!$F$2:$F$2501,Nike_Sales_Uncleaned!$F$2:$F$2501>0)),Nike_Sales_Uncleaned!F71)} -> 2 | G68: {=IF(OR(Nike_Sales_Uncleaned!G71="",Nike_Sales_Uncleaned!G71<=0),MEDIAN(_xlfn._xlws.FILTER(Nike_Sales_Uncleaned!$G$2:$G$2501,Nike_Sales_Uncleaned!$G$2:$G$2501>0)),Nike_Sales_Uncleaned!G71)} -> 7502.24 | H68: =IF(Nike_Sales_Uncleaned!H71="",0,IF(AND(Nike_Sales_Uncleaned!H71>=0,Nike_Sales_Uncleaned!H71<=1),Nike_Sales_Uncleaned!H71,0)) -> 0 | I68: 0 | J68: =IF(Nike_Sales_Uncleaned[[#This Row],[Order_Date]]="","",Nike_Sales_Uncleaned[[#This Row],[Order_Date]]) -> 45636 | K68: Online | L68: Pune | M68: 3554.58
... A80: 2081 | B80: Men | C80: Training | D80: ZoomX Invincible | E80: =IF(Nike_Sales_Uncleaned!E83="","NA",IF(OR(Nike_Sales_Uncleaned!E83=0,Nike_Sales_Uncleaned!E83=-1),"NA",UPPER(Nike_Sales_Uncleaned!E83))) -> L | F80: {=IF(Nike_Sales_Uncleaned!F83="",MEDIAN(_xlfn._xlws.FILTER(Nike_Sales_Uncleaned!$F$2:$F$2501,Nike_Sales_Uncleaned!$F$2:$F$2501>0)),Nike_Sales_Uncleaned!F83)} -> 2 | G80: {=IF(OR(Nike_Sales_Uncleaned!G83="",Nike_Sales_Uncleaned!G83<=0),MEDIAN(_xlfn._xlws.FILTER(Nike_Sales_Uncleaned!$G$2:$G$2501,Nike_Sales_Uncleaned!$G$2:$G$2501>0)),Nike_Sales_Uncleaned!G83)} -> 6110.03 | H80: =IF(Nike_Sales_Uncleaned!H83="",0,IF(AND(Nike_Sales_Uncleaned!H83>=0,Nike_Sales_Uncleaned!H83<=1),Nike_Sales_Uncleaned!H83,0)) -> 0 | I80: 0 | J80: =IF(Nike_Sales_Uncleaned[[#This Row],[Order_Date]]="","",Nike_Sales_Uncleaned[[#This Row],[Order_Date]]) | K80: Online | L80: Mumbai | M80: 2810.49
A81: 2083 | B81: Men | C81: Running | D81: Free RN | E81: =IF(Nike_Sales_Uncleaned!E85="","NA",IF(OR(Nike_Sales_Uncleaned!E85=0,Nike_Sales_Uncleaned!E85=-1),"NA",UPPER(Nike_Sales_Uncleaned!E85))) -> NA | F81: {=IF(Nike_Sales_Uncleaned!F85="",MEDIAN(_xlfn._xlws.FILTER(Nike_Sales_Uncleaned!$F$2:$F$2501,Nike_Sales_Uncleaned!$F$2:$F$2501>0)),Nike_Sales_Uncleaned!F85)} -> 2 | G81: {=IF(OR(Nike_Sales_Uncleaned!G85="",Nike_Sales_Uncleaned!G85<=0),MEDIAN(_xlfn._xlws.FILTER(Nike_Sales_Uncleaned!$G$2:$G$2501,Nike_Sales_Uncleaned!$G$2:$G$2501>0)),Nike_Sales_Uncleaned!G85)} -> 9291.74 | H81: =IF(Nike_Sales_Uncleaned!H85="",0,IF(AND(Nike_Sales_Uncleaned!H85>=0,Nike_Sales_Uncleaned!H85<=1),Nike_Sales_Uncleaned!H85,0)) -> 0 | I81: 0 | J81: =IF(Nike_Sales_Uncleaned[[#This Row],[Order_Date]]="","",Nike_Sales_Uncleaned[[#This Row],[Order_Date]]) -> 45676 | K81: Retail | L81: Delhi | M81: -981.21
A82: 2084 | B82: Men | C82: Training | D82: Metcon 7 | E82: =IF(Nike_Sales_Uncleaned!E86="","NA",IF(OR(Nike_Sales_Uncleaned!E86=0,Nike_Sales_Uncleaned!E86=-1),"NA",UPPER(Nike_Sales_Uncleaned!E86))) -> M | F82: {=IF(Nike_Sales_Uncleaned!F86="",MEDIAN(_xlfn._xlws.FILTER(Nike_Sales_Uncleaned!$F$2:$F$2501,Nike_Sales_Uncleaned!$F$2:$F$2501>0)),Nike_Sales_Uncleaned!F86)} -> 2 | G82: {=IF(OR(Nike_Sales_Uncleaned!G86="",Nike_Sales_Uncleaned!G86<=0),MEDIAN(_xlfn._xlws.FILTER(Nike_Sales_Uncleaned!$G$2:$G$2501,Nike_Sales_Uncleaned!$G$2:$G$2501>0)),Nike_Sales_Uncleaned!G86)} -> 6110.03 | H82: =IF(Nike_Sales_Uncleaned!H86="",0,IF(AND(Nike_Sales_Uncleaned!H86>=0,Nike_Sales_Uncleaned!H86<=1),Nike_Sales_Uncleaned!H86,0)) -> 0 | I82: 0 | J82: =IF(Nike_Sales_Uncleaned[[#This Row],[Order_Date]]="","",Nike_Sales_Uncleaned[[#This Row],[Order_Date]]) -> 45747 | K82: Online | L82: Mumbai | M82: 408.39
A83: 2085 | B83: Men | C83: Basketball | D83: Kyrie Flytrap | E83: =IF(Nike_Sales_Uncleaned!E87="","NA",IF(OR(Nike_Sales_Uncleaned!E87=0,Nike_Sales_Uncleaned!E87=-1),"NA",UPPER(Nike_Sales_Uncleaned!E87))) -> NA | F83: {=IF(Nike_Sales_Uncleaned!F87="",MEDIAN(_xlfn._xlws.FILTER(Nike_Sales_Uncleaned!$F$2:$F$2501,Nike_Sales_Uncleaned!$F$2:$F$2501>0)),Nike_Sales_Uncleaned!F87)} -> 2 | G83: {=IF(OR(Nike_Sales_Uncleaned!G87="",Nike_Sales_Uncleaned!G87<=0),MEDIAN(_xlfn._xlws.FILTER(Nike_Sales_Uncleaned!$G$2:$G$2501,Nike_Sales_Uncleaned!$G$2:$G$2501>0)),Nike_Sales_Uncleaned!G87)} -> 7561.85 | H83: =IF(Nike_Sales_Uncleaned!H87="",0,IF(AND(Nike_Sales_Uncleaned!H87>=0,Nike_Sales_Uncleaned!H87<=1),Nike_Sales_Uncleaned!H87,0)) -> 0 | I83: 0 | J83: =IF(Nike_Sales_Uncleaned[[#This Row],[Order_Date]]="","",Nike_Sales_Uncleaned[[#This Row],[Order_Date]]) | K83: Retail | L83: Kolkata | M83: 98.72
A84: 2086 | B84: Men | C84: Soccer | D84: Mercurial Superfly | E84: =IF(Nike_Sales_Uncleaned!E88="","NA",IF(OR(Nike_Sales_Uncleaned!E88=0,Nike_Sales_Uncleaned!E88=-1),"NA",UPPER(Nike_Sales_Uncleaned!E88))) -> L | F84: {=IF(Nike_Sales_Uncleaned!F88="",MEDIAN(_xlfn._xlws.FILTER(Nike_Sales_Uncleaned!$F$2:$F$2501,Nike_Sales_Uncleaned!$F$2:$F$2501>0)),Nike_Sales_Uncleaned!F88)} -> 0 | G84: {=IF(OR(Nike_Sales_Uncleaned!G88="",Nike_Sales_Uncleaned!G88<=0),MEDIAN(_xlfn._xlws.FILTER(Nike_Sales_Uncleaned!$G$2:$G$2501,Nike_Sales_Uncleaned!$G$2:$G$2501>0)),Nike_Sales_Uncleaned!G88)} -> 6110.03 | H84: =IF(Nike_Sales_Uncleaned!H88="",0,IF(AND(Nike_Sales_Uncleaned!H88>=0,Nike_Sales_Uncleaned!H88<=1),Nike_Sales_Uncleaned!H88,0)) -> 0.45 | I84: 0 | J84: =IF(Nike_Sales_Uncleaned[[#This Row],[Order_Date]]="","",Nike_Sales_Uncleaned[[#This Row],[Order_Date]]) -> 45336 | K84: Online | L84: Kolkata | M84: 1742.66
A85: 2087 | B85: Kids | C85: Basketball | D85: Zoom Freak | E85: =IF(Nike_Sales_Uncleaned!E89="","NA",IF(OR(Nike_Sales_Uncleaned!E89=0,Nike_Sales_Uncleaned!E89=-1),"NA",UPPER(Nike_Sales_Uncleaned!E89))) -> NA | F85: {=IF(Nike_Sales_Uncleaned!F89="",MEDIAN(_xlfn._xlws.FILTER(Nike_Sales_Uncleaned!$F$2:$F$2501,Nike_Sales_Uncleaned!$F$2:$F$2501>0)),Nike_Sales_Uncleaned!F89)} -> 2 | G85: {=IF(OR(Nike_Sales_Uncleaned!G89="",Nike_Sales_Uncleaned!G89<=0),MEDIAN(_xlfn._xlws.FILTER(Nike_Sales_Uncleaned!$G$2:$G$2501,Nike_Sales_Uncleaned!$G$2:$G$2501>0)),Nike_Sales_Uncleaned!G89)} -> 4656.28 | H85: =IF(Nike_Sales_Uncleaned!H89="",0,IF(AND(Nike_Sales_Uncleaned!H89>=0,Nike_Sales_Uncleaned!H89<=1),Nike_Sales_Uncleaned!H89,0)) -> 0 | I85: 0 | J85: =IF(Nike_Sales_Uncleaned[[#This Row],[Order_Date]]="","",Nike_Sales_Uncleaned[[#This Row],[Order_Date]]) -> 45579 | K85: Online | L85: Kolkata | M85: 3777.5
A86: 2088 | B86: Women | C86: Running | D86: Free RN | E86: =IF(Nike_Sales_Uncleaned!E90="","NA",IF(OR(Nike_Sales_Uncleaned!E90=0,Nike_Sales_Uncleaned!E90=-1),"NA",UPPER(Nike_Sales_Uncleaned!E90))) -> XL | F86: {=IF(Nike_Sales_Uncleaned!F90="",MEDIAN(_xlfn._xlws.FILTER(Nike_Sales_Uncleaned!$F$2:$F$2501,Nike_Sales_Uncleaned!$F$2:$F$2501>0)),Nike_Sales_Uncleaned!F90)} -> 4 | G86: {=IF(OR(Nike_Sales_Uncleaned!G90="",Nike_Sales_Uncleaned!G90<=0),MEDIAN(_xlfn._xlws.FILTER(Nike_Sales_Uncleaned!$G$2:$G$2501,Nike_Sales_Uncleaned!$G$2:$G$2501>0)),Nike_Sales_Uncleaned!G90)} -> 6110.03 | H86: =IF(Nike_Sales_Uncleaned!H90="",0,IF(AND(Nike_Sales_Uncleaned!H90>=0,Nike_Sales_Uncleaned!H90<=1),Nike_Sales_Uncleaned!H90,0)) -> 0 | I86: 0 | J86: =IF(Nike_Sales_Uncleaned[[#This Row],[Order_Date]]="","",Nike_Sales_Uncleaned[[#This Row],[Order_Date]]) -> 45284 | K86: Online | L86: Bangalore | M86: 2702.93
A87: 2089 | B87: Women | C87: Training | D87: Flex Trainer | E87: =IF(Nike_Sales_Uncleaned!E91="","NA",IF(OR(Nike_Sales_Uncleaned!E91=0,Nike_Sales_Uncleaned!E91=-1),"NA",UPPER(Nike_Sales_Uncleaned!E91))) -> L | F87: {=IF(Nike_Sales_Uncleaned!F91="",MEDIAN(_xlfn._xlws.FILTER(Nike_Sales_Uncleaned!$F$2:$F$2501,Nike_Sales_Uncleaned!$F$2:$F$2501>0)),Nike_Sales_Uncleaned!F91)} -> 2 | G87: {=IF(OR(Nike_Sales_Uncleaned!G91="",Nike_Sales_Uncleaned!G91<=0),MEDIAN(_xlfn._xlws.FILTER(Nike_Sales_Uncleaned!$G$2:$G$2501,Nike_Sales_Uncleaned!$G$2:$G$2501>0)),Nike_Sales_Uncleaned!G91)} -> 6874.77 | H87: =IF(Nike_Sales_Uncleaned!H91="",0,IF(AND(Nike_Sales_Uncleaned!H91>=0,Nike_Sales_Uncleaned!H91<=1),Nike_Sales_Uncleaned!H91,0)) -> 0.6 | I87: 5499.82 | J87: =IF(Nike_Sales_Uncleaned[[#This Row],[Order_Date]]="","",Nike_Sales_Uncleaned[[#This Row],[Order_Date]]) -> 45643 | K87: Online | L87: Mumbai | M87: -1076.66
A88: 2090 | B88: Kids | C88: Lifestyle | D88: Dunk Low | E88: =IF(Nike_Sales_Uncleaned!E92="","NA",IF(OR(Nike_Sales_Uncleaned!E92=0,Nike_Sales_Uncleaned!E92=-1),"NA",UPPER(Nike_Sales_Uncleaned!E92))) -> 8 | F88: {=IF(Nike_Sales_Uncleaned!F92="",MEDIAN(_xlfn._xlws.FILTER(Nike_Sales_Uncleaned!$F$2:$F$2501,Nike_Sales_Uncleaned!$F$2:$F$2501>0)),Nike_Sales_Uncleaned!F92)} -> 2 | G88: {=IF(OR(Nike_Sales_Uncleaned!G92="",Nike_Sales_Uncleaned!G92<=0),MEDIAN(_xlfn._xlws.FILTER(Nike_Sales_Uncleaned!$G$2:$G$2501,Nike_Sales_Uncleaned!$G$2:$G$2501>0)),Nike_Sales_Uncleaned!G92)} -> 6110.03 | H88: =IF(Nike_Sales_Uncleaned!H92="",0,IF(AND(Nike_Sales_Uncleaned!H92>=0,Nike_Sales_Uncleaned!H92<=1),Nike_Sales_Uncleaned!H92,0)) -> 0 | I88: 0 | J88: =IF(Nike_Sales_Uncleaned[[#This Row],[Order_Date]]="","",Nike_Sales_Uncleaned[[#This Row],[Order_Date]]) -> 45576 | K88: Retail | L88: Bangalore | M88: 163.15
A89: 2091 | B89: Kids | C89: Running | D89: Air Zoom | E89: =IF(Nike_Sales_Uncleaned!E93="","NA",IF(OR(Nike_Sales_Uncleaned!E93=0,Nike_Sales_Uncleaned!E93=-1),"NA",UPPER(Nike_Sales_Uncleaned!E93))) -> 11 | F89: {=IF(Nike_Sales_Uncleaned!F93="",MEDIAN(_xlfn._xlws.FILTER(Nike_Sales_Uncleaned!$F$2:$F$2501,Nike_Sales_Uncleaned!$F$2:$F$2501>0)),Nike_Sales_Uncleaned!F93)} -> 2 | G89: {=IF(OR(Nike_Sales_Uncleaned!G93="",Nike_Sales_Uncleaned!G93<=0),MEDIAN(_xlfn._xlws.FILTER(Nike_Sales_Uncleaned!$G$2:$G$2501,Nike_Sales_Uncleaned!$G$2:$G$2501>0)),Nike_Sales_Uncleaned!G93)} -> 9246.88 | H89: =IF(Nike_Sales_Uncleaned!H93="",0,IF(AND(Nike_Sales_Uncleaned!H93>=0,Nike_Sales_Uncleaned!H93<=1),Nike_Sales_Uncleaned!H93,0)) -> 0 | I89: 0 | J89: =IF(Nike_Sales_Uncleaned[[#This Row],[Order_Date]]="","",Nike_Sales_Uncleaned[[#This Row],[Order_Date]]) -> 45597 | K89: Retail | L89: Mumbai | M89: 1917.55
A90: 2092 | B90: Kids | C90: Basketball | D90: Zoom Freak | E90: =IF(Nike_Sales_Uncleaned!E94="","NA",IF(OR(Nike_Sales_Uncleaned!E94=0,Nike_Sales_Uncleaned!E94=-1),"NA",UPPER(Nike_Sales_Uncleaned!E94))) -> XL | F90: {=IF(Nike_Sales_Uncleaned!F94="",MEDIAN(_xlfn._xlws.FILTER(Nike_Sales_Uncleaned!$F$2:$F$2501,Nike_Sales_Uncleaned!$F$2:$F$2501>0)),Nike_Sales_Uncleaned!F94)} -> 2 | G90: {=IF(OR(Nike_Sales_Uncleaned!G94="",Nike_Sales_Uncleaned!G94<=0),MEDIAN(_xlfn._xlws.FILTER(Nike_Sales_Uncleaned!$G$2:$G$2501,Nike_Sales_Uncleaned!$G$2:$G$2501>0)),Nike_Sales_Uncleaned!G94)} -> 6110.03 | H90: =IF(Nike_Sales_Uncleaned!H94="",0,IF(AND(Nike_Sales_Uncleaned!H94>=0,Nike_Sales_Uncleaned!H94<=1),Nike_Sales_Uncleaned!H94,0)) -> 0 | I90: 0 | J90: =IF(Nike_Sales_Uncleaned[[#This Row],[Order_Date]]="","",Nike_Sales_Uncleaned[[#This Row],[Order_Date]]) -> 45773 | K90: Online | L90: Delhi | M90: 207.2
A91: 2093 | B91: Men | C91: Running | D91: Free RN | E91: =IF(Nike_Sales_Uncleaned!E95="","NA",IF(OR(Nike_Sales_Uncleaned!E95=0,Nike_Sales_Uncleaned!E95=-1),"NA",UPPER(Nike_Sales_Uncleaned!E95))) -> XL | F91: {=IF(Nike_Sales_Uncleaned!F95="",MEDIAN(_xlfn._xlws.FILTER(Nike_Sales_Uncleaned!$F$2:$F$2501,Nike_Sales_Uncleaned!$F$2:$F$2501>0)),Nike_Sales_Uncleaned!F95)} -> 0 | G91: {=IF(OR(Nike_Sales_Uncleaned!G95="",Nike_Sales_Uncleaned!G95<=0),MEDIAN(_xlfn._xlws.FILTER(Nike_Sales_Uncleaned!$G$2:$G$2501,Nike_Sales_Uncleaned!$G$2:$G$2501>0)),Nike_Sales_Uncleaned!G95)} -> 6110.03 | H91: =IF(Nike_Sales_Uncleaned!H95="",0,IF(AND(Nike_Sales_Uncleaned!H95>=0,Nike_Sales_Uncleaned!H95<=1),Nike_Sales_Uncleaned!H95,0)) -> 0.29 | I91: 0 | J91: =IF(Nike_Sales_Uncleaned[[#This Row],[Order_Date]]="","",Nike_Sales_Uncleaned[[#This Row],[Order_Date]]) -> 45628 | K91: Online | L91: Kolkata | M91: -146.73
A92: 2094 | B92: Kids | C92: Training | D92: Flex Trainer | E92: =IF(Nike_Sales_Uncleaned!E96="","NA",IF(OR(Nike_Sales_Uncleaned!E96=0,Nike_Sales_Uncleaned!E96=-1),"NA",UPPER(Nike_Sales_Uncleaned!E96))) -> 10 | F92: {=IF(Nike_Sales_Uncleaned!F96="",MEDIAN(_xlfn._xlws.FILTER(Nike_Sales_Uncleaned!$F$2:$F$2501,Nike_Sales_Uncleaned!$F$2:$F$2501>0)),Nike_Sales_Uncleaned!F96)} -> 1 | G92: {=IF(OR(Nike_Sales_Uncleaned!G96="",Nike_Sales_Uncleaned!G96<=0),MEDIAN(_xlfn._xlws.FILTER(Nike_Sales_Uncleaned!$G$2:$G$2501,Nike_Sales_Uncleaned!$G$2:$G$2501>0)),Nike_Sales_Uncleaned!G96)} -> 4276.36 | H92: =IF(Nike_Sales_Uncleaned!H96="",0,IF(AND(Nike_Sales_Uncleaned!H96>=0,Nike_Sales_Uncleaned!H96<=1),Nike_Sales_Uncleaned!H96,0)) -> 0 | I92: 0 | J92: =IF(Nike_Sales_Uncleaned[[#This Row],[Order_Date]]="","",Nike_Sales_Uncleaned[[#This Row],[Order_Date]]) | K92: Retail | L92: Delhi | M92: 2974.58
... A118: 2120 | B118: Men | C118: Soccer | D118: Phantom GT | E118: =IF(Nike_Sales_Uncleaned!E122="","NA",IF(OR(Nike_Sales_Uncleaned!E122=0,Nike_Sales_Uncleaned!E122=-1),"NA",UPPER(Nike_Sales_Uncleaned!E122))) -> 12 | F118: {=IF(Nike_Sales_Uncleaned!F122="",MEDIAN(_xlfn._xlws.FILTER(Nike_Sales_Uncleaned!$F$2:$F$2501,Nike_Sales_Uncleaned!$F$2:$F$2501>0)),Nike_Sales_Uncleaned!F122)} -> 2 | G118: {=IF(OR(Nike_Sales_Uncleaned!G122="",Nike_Sales_Uncleaned!G122<=0),MEDIAN(_xlfn._xlws.FILTER(Nike_Sales_Uncleaned!$G$2:$G$2501,Nike_Sales_Uncleaned!$G$2:$G$2501>0)),Nike_Sales_Uncleaned!G122)} -> 6110.03 | H118: =IF(Nike_Sales_Uncleaned!H122="",0,IF(AND(Nike_Sales_Uncleaned!H122>=0,Nike_Sales_Uncleaned!H122<=1),Nike_Sales_Uncleaned!H122,0)) -> 0 | I118: 0 | J118: =IF(Nike_Sales_Uncleaned[[#This Row],[Order_Date]]="","",Nike_Sales_Uncleaned[[#This Row],[Order_Date]]) -> 45531 | K118: Retail | L118: Pune | M118: -328
A119: 2122 | B119: Kids | C119: Soccer | D119: Mercurial Superfly | E119: =IF(Nike_Sales_Uncleaned!E124="","NA",IF(OR(Nike_Sales_Uncleaned!E124=0,Nike_Sales_Uncleaned!E124=-1),"NA",UPPER(Nike_Sales_Uncleaned!E124))) -> NA | F119: {=IF(Nike_Sales_Uncleaned!F124="",MEDIAN(_xlfn._xlws.FILTER(Nike_Sales_Uncleaned!$F$2:$F$2501,Nike_Sales_Uncleaned!$F$2:$F$2501>0)),Nike_Sales_Uncleaned!F124)} -> 0 | G119: {=IF(OR(Nike_Sales_Uncleaned!G124="",Nike_Sales_Uncleaned!G124<=0),MEDIAN(_xlfn._xlws.FILTER(Nike_Sales_Uncleaned!$G$2:$G$2501,Nike_Sales_Uncleaned!$G$2:$G$2501>0)),Nike_Sales_Uncleaned!G124)} -> 6110.03 | H119: =IF(Nike_Sales_Uncleaned!H124="",0,IF(AND(Nike_Sales_Uncleaned!H124>=0,Nike_Sales_Uncleaned!H124<=1),Nike_Sales_Uncleaned!H124,0)) -> 0 | I119: 0 | J119: =IF(Nike_Sales_Uncleaned[[#This Row],[Order_Date]]="","",Nike_Sales_Uncleaned[[#This Row],[Order_Date]]) -> 45595 | K119: Retail | L119: Bangalore | M119: 1078.48
A120: 2123 | B120: Men | C120: Running | D120: Air Zoom | E120: =IF(Nike_Sales_Uncleaned!E125="","NA",IF(OR(Nike_Sales_Uncleaned!E125=0,Nike_Sales_Uncleaned!E125=-1),"NA",UPPER(Nike_Sales_Uncleaned!E125))) -> L | F120: {=IF(Nike_Sales_Uncleaned!F125="",MEDIAN(_xlfn._xlws.FILTER(Nike_Sales_Uncleaned!$F$2:$F$2501,Nike_Sales_Uncleaned!$F$2:$F$2501>0)),Nike_Sales_Uncleaned!F125)} -> 2 | G120: {=IF(OR(Nike_Sales_Uncleaned!G125="",Nike_Sales_Uncleaned!G125<=0),MEDIAN(_xlfn._xlws.FILTER(Nike_Sales_Uncleaned!$G$2:$G$2501,Nike_Sales_Uncleaned!$G$2:$G$2501>0)),Nike_Sales_Uncleaned!G125)} -> 6110.03 | H120: =IF(Nike_Sales_Uncleaned!H125="",0,IF(AND(Nike_Sales_Uncleaned!H125>=0,Nike_Sales_Uncleaned!H125<=1),Nike_Sales_Uncleaned!H125,0)) -> 0 | I120: 0 | J120: =IF(Nike_Sales_Uncleaned[[#This Row],[Order_Date]]="","",Nike_Sales_Uncleaned[[#This Row],[Order_Date]]) -> 45190 | K120: Retail | L120: Hyderabad | M120: 2195.52
A121: 2124 | B121: Kids | C121: Basketball | D121: Kyrie Flytrap | E121: =IF(Nike_Sales_Uncleaned!E126="","NA",IF(OR(Nike_Sales_Uncleaned!E126=0,Nike_Sales_Uncleaned!E126=-1),"NA",UPPER(Nike_Sales_Uncleaned!E126))) -> L | F121: {=IF(Nike_Sales_Uncleaned!F126="",MEDIAN(_xlfn._xlws.FILTER(Nike_Sales_Uncleaned!$F$2:$F$2501,Nike_Sales_Uncleaned!$F$2:$F$2501>0)),Nike_Sales_Uncleaned!F126)} -> 2 | G121: {=IF(OR(Nike_Sales_Uncleaned!G126="",Nike_Sales_Uncleaned!G126<=0),MEDIAN(_xlfn._xlws.FILTER(Nike_Sales_Uncleaned!$G$2:$G$2501,Nike_Sales_Uncleaned!$G$2:$G$2501>0)),Nike_Sales_Uncleaned!G126)} -> 6436.11 | H121: =IF(Nike_Sales_Uncleaned!H126="",0,IF(AND(Nike_Sales_Uncleaned!H126>=0,Nike_Sales_Uncleaned!H126<=1),Nike_Sales_Uncleaned!H126,0)) -> 0 | I121: 0 | J121: =IF(Nike_Sales_Uncleaned[[#This Row],[Order_Date]]="","",Nike_Sales_Uncleaned[[#This Row],[Order_Date]]) -> 45752 | K121: Online | L121: Kolkata | M121: 432.04
A122: 2125 | B122: Women | C122: Soccer | D122: Tiempo Legend | E122: =IF(Nike_Sales_Uncleaned!E127="","NA",IF(OR(Nike_Sales_Uncleaned!E127=0,Nike_Sales_Uncleaned!E127=-1),"NA",UPPER(Nike_Sales_Uncleaned!E127))) -> M | F122: {=IF(Nike_Sales_Uncleaned!F127="",MEDIAN(_xlfn._xlws.FILTER(Nike_Sales_Uncleaned!$F$2:$F$2501,Nike_Sales_Uncleaned!$F$2:$F$2501>0)),Nike_Sales_Uncleaned!F127)} -> 2 | G122: {=IF(OR(Nike_Sales_Uncleaned!G127="",Nike_Sales_Uncleaned!G127<=0),MEDIAN(_xlfn._xlws.FILTER(Nike_Sales_Uncleaned!$G$2:$G$2501,Nike_Sales_Uncleaned!$G$2:$G$2501>0)),Nike_Sales_Uncleaned!G127)} -> 6110.03 | H122: =IF(Nike_Sales_Uncleaned!H127="",0,IF(AND(Nike_Sales_Uncleaned!H127>=0,Nike_Sales_Uncleaned!H127<=1),Nike_Sales_Uncleaned!H127,0)) -> 0 | I122: 0 | J122: =IF(Nike_Sales_Uncleaned[[#This Row],[Order_Date]]="","",Nike_Sales_Uncleaned[[#This Row],[Order_Date]]) -> 45640 | K122: Retail | L122: Hyderabad | M122: 1051.22
A123: 2126 | B123: Kids | C123: Running | D123: Pegasus Turbo | E123: =IF(Nike_Sales_Uncleaned!E128="","NA",IF(OR(Nike_Sales_Uncleaned!E128=0,Nike_Sales_Uncleaned!E128=-1),"NA",UPPER(Nike_Sales_Uncleaned!E128))) -> L | F123: {=IF(Nike_Sales_Uncleaned!F128="",MEDIAN(_xlfn._xlws.FILTER(Nike_Sales_Uncleaned!$F$2:$F$2501,Nike_Sales_Uncleaned!$F$2:$F$2501>0)),Nike_Sales_Uncleaned!F128)} -> -1 | G123: {=IF(OR(Nike_Sales_Uncleaned!G128="",Nike_Sales_Uncleaned!G128<=0),MEDIAN(_xlfn._xlws.FILTER(Nike_Sales_Uncleaned!$G$2:$G$2501,Nike_Sales_Uncleaned!$G$2:$G$2501>0)),Nike_Sales_Uncleaned!G128)} -> 5399.58 | H123: =IF(Nike_Sales_Uncleaned!H128="",0,IF(AND(Nike_Sales_Uncleaned!H128>=0,Nike_Sales_Uncleaned!H128<=1),Nike_Sales_Uncleaned!H128,0)) -> 0 | I123: 0 | J123: =IF(Nike_Sales_Uncleaned[[#This Row],[Order_Date]]="","",Nike_Sales_Uncleaned[[#This Row],[Order_Date]]) -> 45250 | K123: Retail | L123: Pune | M123: 2508.34
A124: 2127 | B124: Men | C124: Training | D124: Metcon 7 | E124: =IF(Nike_Sales_Uncleaned!E129="","NA",IF(OR(Nike_Sales_Uncleaned!E129=0,Nike_Sales_Uncleaned!E129=-1),"NA",UPPER(Nike_Sales_Uncleaned!E129))) -> L | F124: {=IF(Nike_Sales_Uncleaned!F129="",MEDIAN(_xlfn._xlws.FILTER(Nike_Sales_Uncleaned!$F$2:$F$2501,Nike_Sales_Uncleaned!$F$2:$F$2501>0)),Nike_Sales_Uncleaned!F129)} -> -1 | G124: {=IF(OR(Nike_Sales_Uncleaned!G129="",Nike_Sales_Uncleaned!G129<=0),MEDIAN(_xlfn._xlws.FILTER(Nike_Sales_Uncleaned!$G$2:$G$2501,Nike_Sales_Uncleaned!$G$2:$G$2501>0)),Nike_Sales_Uncleaned!G129)} -> 4020.5 | H124: =IF(Nike_Sales_Uncleaned!H129="",0,IF(AND(Nike_Sales_Uncleaned!H129>=0,Nike_Sales_Uncleaned!H129<=1),Nike_Sales_Uncleaned!H129,0)) -> 0 | I124: 0 | J124: =IF(Nike_Sales_Uncleaned[[#This Row],[Order_Date]]="","",Nike_Sales_Uncleaned[[#This Row],[Order_Date]]) | K124: Online | L124: Mumbai | M124: 3718.37
A125: 2128 | B125: Women | C125: Basketball | D125: LeBron 20 | E125: =IF(Nike_Sales_Uncleaned!E130="","NA",IF(OR(Nike_Sales_Uncleaned!E130=0,Nike_Sales_Uncleaned!E130=-1),"NA",UPPER(Nike_Sales_Uncleaned!E130))) -> L | F125: {=IF(Nike_Sales_Uncleaned!F130="",MEDIAN(_xlfn._xlws.FILTER(Nike_Sales_Uncleaned!$F$2:$F$2501,Nike_Sales_Uncleaned!$F$2:$F$2501>0)),Nike_Sales_Uncleaned!F130)} -> 2 | G125: {=IF(OR(Nike_Sales_Uncleaned!G130="",Nike_Sales_Uncleaned!G130<=0),MEDIAN(_xlfn._xlws.FILTER(Nike_Sales_Uncleaned!$G$2:$G$2501,Nike_Sales_Uncleaned!$G$2:$G$2501>0)),Nike_Sales_Uncleaned!G130)} -> 8750.71 | H125: =IF(Nike_Sales_Uncleaned!H130="",0,IF(AND(Nike_Sales_Uncleaned!H130>=0,Nike_Sales_Uncleaned!H130<=1),Nike_Sales_Uncleaned!H130,0)) -> 0 | I125: 0 | J125: =IF(Nike_Sales_Uncleaned[[#This Row],[Order_Date]]="","",Nike_Sales_Uncleaned[[#This Row],[Order_Date]]) -> 45550 | K125: Retail | L125: Bangalore | M125: 1411.29
A126: 2129 | B126: Men | C126: Basketball | D126: Zoom Freak | E126: =IF(Nike_Sales_Uncleaned!E131="","NA",IF(OR(Nike_Sales_Uncleaned!E131=0,Nike_Sales_Uncleaned!E131=-1),"NA",UPPER(Nike_Sales_Uncleaned!E131))) -> 9 | F126: {=IF(Nike_Sales_Uncleaned!F131="",MEDIAN(_xlfn._xlws.FILTER(Nike_Sales_Uncleaned!$F$2:$F$2501,Nike_Sales_Uncleaned!$F$2:$F$2501>0)),Nike_Sales_Uncleaned!F131)} -> 2 | G126: {=IF(OR(Nike_Sales_Uncleaned!G131="",Nike_Sales_Uncleaned!G131<=0),MEDIAN(_xlfn._xlws.FILTER(Nike_Sales_Uncleaned!$G$2:$G$2501,Nike_Sales_Uncleaned!$G$2:$G$2501>0)),Nike_Sales_Uncleaned!G131)} -> 6110.03 | H126: =IF(Nike_Sales_Uncleaned!H131="",0,IF(AND(Nike_Sales_Uncleaned!H131>=0,Nike_Sales_Uncleaned!H131<=1),Nike_Sales_Uncleaned!H131,0)) -> 0 | I126: 0 | J126: =IF(Nike_Sales_Uncleaned[[#This Row],[Order_Date]]="","",Nike_Sales_Uncleaned[[#This Row],[Order_Date]]) -> 45842 | K126: Retail | L126: Delhi | M126: 841.4
A127: 2130 | B127: Men | C127: Soccer | D127: Premier III | E127: =IF(Nike_Sales_Uncleaned!E132="","NA",IF(OR(Nike_Sales_Uncleaned!E132=0,Nike_Sales_Uncleaned!E132=-1),"NA",UPPER(Nike_Sales_Uncleaned!E132))) -> 10 | F127: {=IF(Nike_Sales_Uncleaned!F132="",MEDIAN(_xlfn._xlws.FILTER(Nike_Sales_Uncleaned!$F$2:$F$2501,Nike_Sales_Uncleaned!$F$2:$F$2501>0)),Nike_Sales_Uncleaned!F132)} -> 3 | G127: {=IF(OR(Nike_Sales_Uncleaned!G132="",Nike_Sales_Uncleaned!G132<=0),MEDIAN(_xlfn._xlws.FILTER(Nike_Sales_Uncleaned!$G$2:$G$2501,Nike_Sales_Uncleaned!$G$2:$G$2501>0)),Nike_Sales_Uncleaned!G132)} -> 6110.03 | H127: =IF(Nike_Sales_Uncleaned!H132="",0,IF(AND(Nike_Sales_Uncleaned!H132>=0,Nike_Sales_Uncleaned!H132<=1),Nike_Sales_Uncleaned!H132,0)) -> 0.24 | I127: 0 | J127: =IF(Nike_Sales_Uncleaned[[#This Row],[Order_Date]]="","",Nike_Sales_Uncleaned[[#This Row],[Order_Date]]) -> 45636 | K127: Online | L127: Bangalore | M127: 2962.75
A128: 2131 | B128: Kids | C128: Running | D128: Free RN | E128: =IF(Nike_Sales_Uncleaned!E133="","NA",IF(OR(Nike_Sales_Uncleaned!E133=0,Nike_Sales_Uncleaned!E133=-1),"NA",UPPER(Nike_Sales_Uncleaned!E133))) -> XL | F128: {=IF(Nike_Sales_Uncleaned!F133="",MEDIAN(_xlfn._xlws.FILTER(Nike_Sales_Uncleaned!$F$2:$F$2501,Nike_Sales_Uncleaned!$F$2:$F$2501>0)),Nike_Sales_Uncleaned!F133)} -> 2 | G128: {=IF(OR(Nike_Sales_Uncleaned!G133="",Nike_Sales_Uncleaned!G133<=0),MEDIAN(_xlfn._xlws.FILTER(Nike_Sales_Uncleaned!$G$2:$G$2501,Nike_Sales_Uncleaned!$G$2:$G$2501>0)),Nike_Sales_Uncleaned!G133)} -> 5561.82 | H128: =IF(Nike_Sales_Uncleaned!H133="",0,IF(AND(Nike_Sales_Uncleaned!H133>=0,Nike_Sales_Uncleaned!H133<=1),Nike_Sales_Uncleaned!H133,0)) -> 0 | I128: 0 | J128: =IF(Nike_Sales_Uncleaned[[#This Row],[Order_Date]]="","",Nike_Sales_Uncleaned[[#This Row],[Order_Date]]) -> 45640 | K128: Retail | L128: Mumbai | M128: 2227.48
A129: 2132 | B129: Men | C129: Running | D129: Free RN | E129: =IF(Nike_Sales_Uncleaned!E134="","NA",IF(OR(Nike_Sales_Uncleaned!E134=0,Nike_Sales_Uncleaned!E134=-1),"NA",UPPER(Nike_Sales_Uncleaned!E134))) -> L | F129: {=IF(Nike_Sales_Uncleaned!F134="",MEDIAN(_xlfn._xlws.FILTER(Nike_Sales_Uncleaned!$F$2:$F$2501,Nike_Sales_Uncleaned!$F$2:$F$2501>0)),Nike_Sales_Uncleaned!F134)} -> 2 | G129: {=IF(OR(Nike_Sales_Uncleaned!G134="",Nike_Sales_Uncleaned!G134<=0),MEDIAN(_xlfn._xlws.FILTER(Nike_Sales_Uncleaned!$G$2:$G$2501,Nike_Sales_Uncleaned!$G$2:$G$2501>0)),Nike_Sales_Uncleaned!G134)} -> 6110.03 | H129: =IF(Nike_Sales_Uncleaned!H134="",0,IF(AND(Nike_Sales_Uncleaned!H134>=0,Nike_Sales_Uncleaned!H134<=1),Nike_Sales_Uncleaned!H134,0)) -> 0 | I129: 0 | J129: =IF(Nike_Sales_Uncleaned[[#This Row],[Order_Date]]="","",Nike_Sales_Uncleaned[[#This Row],[Order_Date]]) -> 45157 | K129: Online | L129: Delhi | M129: 3882.22
A130: 2133 | B130: Men | C130: Training | D130: Metcon 7 | E130: =IF(Nike_Sales_Uncleaned!E135="","NA",IF(OR(Nike_Sales_Uncleaned!E135=0,Nike_Sales_Uncleaned!E135=-1),"NA",UPPER(Nike_Sales_Uncleaned!E135))) -> XL | F130: {=IF(Nike_Sales_Uncleaned!F135="",MEDIAN(_xlfn._xlws.FILTER(Nike_Sales_Uncleaned!$F$2:$F$2501,Nike_Sales_Uncleaned!$F$2:$F$2501>0)),Nike_Sales_Uncleaned!F135)} -> 2 | G130: {=IF(OR(Nike_Sales_Uncleaned!G135="",Nike_Sales_Uncleaned!G135<=0),MEDIAN(_xlfn._xlws.FILTER(Nike_Sales_Uncleaned!$G$2:$G$2501,Nike_Sales_Uncleaned!$G$2:$G$2501>0)),Nike_Sales_Uncleaned!G135)} -> 6789.53 | H130: =IF(Nike_Sales_Uncleaned!H135="",0,IF(AND(Nike_Sales_Uncleaned!H135>=0,Nike_Sales_Uncleaned!H135<=1),Nike_Sales_Uncleaned!H135,0)) -> 0 | I130: 0 | J130: =IF(Nike_Sales_Uncleaned[[#This Row],[Order_Date]]="","",Nike_Sales_Uncleaned[[#This Row],[Order_Date]]) | K130: Retail | L130: Pune | M130: -166.81
... A167: 2170 | B167: Kids | C167: Lifestyle | D167: Air Force 1 | E167: =IF(Nike_Sales_Uncleaned!E172="","NA",IF(OR(Nike_Sales_Uncleaned!E172=0,Nike_Sales_Uncleaned!E172=-1),"NA",UPPER(Nike_Sales_Uncleaned!E172))) -> M | F167: {=IF(Nike_Sales_Uncleaned!F172="",MEDIAN(_xlfn._xlws.FILTER(Nike_Sales_Uncleaned!$F$2:$F$2501,Nike_Sales_Uncleaned!$F$2:$F$2501>0)),Nike_Sales_Uncleaned!F172)} -> 0 | G167: {=IF(OR(Nike_Sales_Uncleaned!G172="",Nike_Sales_Uncleaned!G172<=0),MEDIAN(_xlfn._xlws.FILTER(Nike_Sales_Uncleaned!$G$2:$G$2501,Nike_Sales_Uncleaned!$G$2:$G$2501>0)),Nike_Sales_Uncleaned!G172)} -> 6110.03 | H167: =IF(Nike_Sales_Uncleaned!H172="",0,IF(AND(Nike_Sales_Uncleaned!H172>=0,Nike_Sales_Uncleaned!H172<=1),Nike_Sales_Uncleaned!H172,0)) -> 0 | I167: 0 | J167: =IF(Nike_Sales_Uncleaned[[#This Row],[Order_Date]]="","",Nike_Sales_Uncleaned[[#This Row],[Order_Date]]) -> 45607 | K167: Online | L167: Kolkata | M167: 3218.82
A168: 2172 | B168: Women | C168: Training | D168: ZoomX Invincible | E168: =IF(Nike_Sales_Uncleaned!E174="","NA",IF(OR(Nike_Sales_Uncleaned!E174=0,Nike_Sales_Uncleaned!E174=-1),"NA",UPPER(Nike_Sales_Uncleaned!E174))) -> M | F168: {=IF(Nike_Sales_Uncleaned!F174="",MEDIAN(_xlfn._xlws.FILTER(Nike_Sales_Uncleaned!$F$2:$F$2501,Nike_Sales_Uncleaned!$F$2:$F$2501>0)),Nike_Sales_Uncleaned!F174)} -> 2 | G168: {=IF(OR(Nike_Sales_Uncleaned!G174="",Nike_Sales_Uncleaned!G174<=0),MEDIAN(_xlfn._xlws.FILTER(Nike_Sales_Uncleaned!$G$2:$G$2501,Nike_Sales_Uncleaned!$G$2:$G$2501>0)),Nike_Sales_Uncleaned!G174)} -> 7988.99 | H168: =IF(Nike_Sales_Uncleaned!H174="",0,IF(AND(Nike_Sales_Uncleaned!H174>=0,Nike_Sales_Uncleaned!H174<=1),Nike_Sales_Uncleaned!H174,0)) -> 0 | I168: 0 | J168: =IF(Nike_Sales_Uncleaned[[#This Row],[Order_Date]]="","",Nike_Sales_Uncleaned[[#This Row],[Order_Date]]) -> 45689 | K168: Online | L168: Bangalore | M168: -909.86
A169: 2173 | B169: Men | C169: Running | D169: Free RN | E169: =IF(Nike_Sales_Uncleaned!E175="","NA",IF(OR(Nike_Sales_Uncleaned!E175=0,Nike_Sales_Uncleaned!E175=-1),"NA",UPPER(Nike_Sales_Uncleaned!E175))) -> L | F169: {=IF(Nike_Sales_Uncleaned!F175="",MEDIAN(_xlfn._xlws.FILTER(Nike_Sales_Uncleaned!$F$2:$F$2501,Nike_Sales_Uncleaned!$F$2:$F$2501>0)),Nike_Sales_Uncleaned!F175)} -> -1 | G169: {=IF(OR(Nike_Sales_Uncleaned!G175="",Nike_Sales_Uncleaned!G175<=0),MEDIAN(_xlfn._xlws.FILTER(Nike_Sales_Uncleaned!$G$2:$G$2501,Nike_Sales_Uncleaned!$G$2:$G$2501>0)),Nike_Sales_Uncleaned!G175)} -> 6620.78 | H169: =IF(Nike_Sales_Uncleaned!H175="",0,IF(AND(Nike_Sales_Uncleaned!H175>=0,Nike_Sales_Uncleaned!H175<=1),Nike_Sales_Uncleaned!H175,0)) -> 0 | I169: 0 | J169: =IF(Nike_Sales_Uncleaned[[#This Row],[Order_Date]]="","",Nike_Sales_Uncleaned[[#This Row],[Order_Date]]) | K169: Online | L169: Bangalore | M169: 3770.03
A170: 2174 | B170: Women | C170: Soccer | D170: Phantom GT | E170: =IF(Nike_Sales_Uncleaned!E176="","NA",IF(OR(Nike_Sales_Uncleaned!E176=0,Nike_Sales_Uncleaned!E176=-1),"NA",UPPER(Nike_Sales_Uncleaned!E176))) -> L | F170: {=IF(Nike_Sales_Uncleaned!F176="",MEDIAN(_xlfn._xlws.FILTER(Nike_Sales_Uncleaned!$F$2:$F$2501,Nike_Sales_Uncleaned!$F$2:$F$2501>0)),Nike_Sales_Uncleaned!F176)} -> 2 | G170: {=IF(OR(Nike_Sales_Uncleaned!G176="",Nike_Sales_Uncleaned!G176<=0),MEDIAN(_xlfn._xlws.FILTER(Nike_Sales_Uncleaned!$G$2:$G$2501,Nike_Sales_Uncleaned!$G$2:$G$2501>0)),Nike_Sales_Uncleaned!G176)} -> 3883.92 | H170: =IF(Nike_Sales_Uncleaned!H176="",0,IF(AND(Nike_Sales_Uncleaned!H176>=0,Nike_Sales_Uncleaned!H176<=1),Nike_Sales_Uncleaned!H176,0)) -> 0 | I170: 0 | J170: =IF(Nike_Sales_Uncleaned[[#This Row],[Order_Date]]="","",Nike_Sales_Uncleaned[[#This Row],[Order_Date]]) -> 45505 | K170: Retail | L170: Pune | M170: 428.5
A171: 2175 | B171: Women | C171: Lifestyle | D171: Blazer Mid | E171: =IF(Nike_Sales_Uncleaned!E177="","NA",IF(OR(Nike_Sales_Uncleaned!E177=0,Nike_Sales_Uncleaned!E177=-1),"NA",UPPER(Nike_Sales_Uncleaned!E177))) -> NA | F171: {=IF(Nike_Sales_Uncleaned!F177="",MEDIAN(_xlfn._xlws.FILTER(Nike_Sales_Uncleaned!$F$2:$F$2501,Nike_Sales_Uncleaned!$F$2:$F$2501>0)),Nike_Sales_Uncleaned!F177)} -> 2 | G171: {=IF(OR(Nike_Sales_Uncleaned!G177="",Nike_Sales_Uncleaned!G177<=0),MEDIAN(_xlfn._xlws.FILTER(Nike_Sales_Uncleaned!$G$2:$G$2501,Nike_Sales_Uncleaned!$G$2:$G$2501>0)),Nike_Sales_Uncleaned!G177)} -> 6110.03 | H171: =IF(Nike_Sales_Uncleaned!H177="",0,IF(AND(Nike_Sales_Uncleaned!H177>=0,Nike_Sales_Uncleaned!H177<=1),Nike_Sales_Uncleaned!H177,0)) -> 0 | I171: 0 | J171: =IF(Nike_Sales_Uncleaned[[#This Row],[Order_Date]]="","",Nike_Sales_Uncleaned[[#This Row],[Order_Date]]) -> 45640 | K171: Online | L171: Pune | M171: 2457.78
A172: 2176 | B172: Men | C172: Soccer | D172: Mercurial Superfly | E172: =IF(Nike_Sales_Uncleaned!E178="","NA",IF(OR(Nike_Sales_Uncleaned!E178=0,Nike_Sales_Uncleaned!E178=-1),"NA",UPPER(Nike_Sales_Uncleaned!E178))) -> NA | F172: {=IF(Nike_Sales_Uncleaned!F178="",MEDIAN(_xlfn._xlws.FILTER(Nike_Sales_Uncleaned!$F$2:$F$2501,Nike_Sales_Uncleaned!$F$2:$F$2501>0)),Nike_Sales_Uncleaned!F178)} -> 4 | G172: {=IF(OR(Nike_Sales_Uncleaned!G178="",Nike_Sales_Uncleaned!G178<=0),MEDIAN(_xlfn._xlws.FILTER(Nike_Sales_Uncleaned!$G$2:$G$2501,Nike_Sales_Uncleaned!$G$2:$G$2501>0)),Nike_Sales_Uncleaned!G178)} -> 6110.03 | H172: =IF(Nike_Sales_Uncleaned!H178="",0,IF(AND(Nike_Sales_Uncleaned!H178>=0,Nike_Sales_Uncleaned!H178<=1),Nike_Sales_Uncleaned!H178,0)) -> 0 | I172: 0 | J172: =IF(Nike_Sales_Uncleaned[[#This Row],[Order_Date]]="","",Nike_Sales_Uncleaned[[#This Row],[Order_Date]]) -> 45836 | K172: Online | L172: Bangalore | M172: 3908.28
A173: 2177 | B173: Women | C173: Lifestyle | D173: Waffle One | E173: =IF(Nike_Sales_Uncleaned!E179="","NA",IF(OR(Nike_Sales_Uncleaned!E179=0,Nike_Sales_Uncleaned!E179=-1),"NA",UPPER(Nike_Sales_Uncleaned!E179))) -> XL | F173: {=IF(Nike_Sales_Uncleaned!F179="",MEDIAN(_xlfn._xlws.FILTER(Nike_Sales_Uncleaned!$F$2:$F$2501,Nike_Sales_Uncleaned!$F$2:$F$2501>0)),Nike_Sales_Uncleaned!F179)} -> 2 | G173: {=IF(OR(Nike_Sales_Uncleaned!G179="",Nike_Sales_Uncleaned!G179<=0),MEDIAN(_xlfn._xlws.FILTER(Nike_Sales_Uncleaned!$G$2:$G$2501,Nike_Sales_Uncleaned!$G$2:$G$2501>0)),Nike_Sales_Uncleaned!G179)} -> 6110.03 | H173: =IF(Nike_Sales_Uncleaned!H179="",0,IF(AND(Nike_Sales_Uncleaned!H179>=0,Nike_Sales_Uncleaned!H179<=1),Nike_Sales_Uncleaned!H179,0)) -> 0 | I173: 0 | J173: =IF(Nike_Sales_Uncleaned[[#This Row],[Order_Date]]="","",Nike_Sales_Uncleaned[[#This Row],[Order_Date]]) -> 45228 | K173: Retail | L173: Mumbai | M173: 885.37
A174: 2178 | B174: Men | C174: Running | D174: Free RN | E174: =IF(Nike_Sales_Uncleaned!E180="","NA",IF(OR(Nike_Sales_Uncleaned!E180=0,Nike_Sales_Uncleaned!E180=-1),"NA",UPPER(Nike_Sales_Uncleaned!E180))) -> NA | F174: {=IF(Nike_Sales_Uncleaned!F180="",MEDIAN(_xlfn._xlws.FILTER(Nike_Sales_Uncleaned!$F$2:$F$2501,Nike_Sales_Uncleaned!$F$2:$F$2501>0)),Nike_Sales_Uncleaned!F180)} -> 1 | G174: {=IF(OR(Nike_Sales_Uncleaned!G180="",Nike_Sales_Uncleaned!G180<=0),MEDIAN(_xlfn._xlws.FILTER(Nike_Sales_Uncleaned!$G$2:$G$2501,Nike_Sales_Uncleaned!$G$2:$G$2501>0)),Nike_Sales_Uncleaned!G180)} -> 6110.03 | H174: =IF(Nike_Sales_Uncleaned!H180="",0,IF(AND(Nike_Sales_Uncleaned!H180>=0,Nike_Sales_Uncleaned!H180<=1),Nike_Sales_Uncleaned!H180,0)) -> 0 | I174: 0 | J174: =IF(Nike_Sales_Uncleaned[[#This Row],[Order_Date]]="","",Nike_Sales_Uncleaned[[#This Row],[Order_Date]]) -> 45643 | K174: Retail | L174: Bangalore | M174: -983.37
A175: 2179 | B175: Women | C175: Training | D175: ZoomX Invincible | E175: =IF(Nike_Sales_Uncleaned!E181="","NA",IF(OR(Nike_Sales_Uncleaned!E181=0,Nike_Sales_Uncleaned!E181=-1),"NA",UPPER(Nike_Sales_Uncleaned!E181))) -> M | F175: {=IF(Nike_Sales_Uncleaned!F181="",MEDIAN(_xlfn._xlws.FILTER(Nike_Sales_Uncleaned!$F$2:$F$2501,Nike_Sales_Uncleaned!$F$2:$F$2501>0)),Nike_Sales_Uncleaned!F181)} -> 3 | G175: {=IF(OR(Nike_Sales_Uncleaned!G181="",Nike_Sales_Uncleaned!G181<=0),MEDIAN(_xlfn._xlws.FILTER(Nike_Sales_Uncleaned!$G$2:$G$2501,Nike_Sales_Uncleaned!$G$2:$G$2501>0)),Nike_Sales_Uncleaned!G181)} -> 6110.03 | H175: =IF(Nike_Sales_Uncleaned!H181="",0,IF(AND(Nike_Sales_Uncleaned!H181>=0,Nike_Sales_Uncleaned!H181<=1),Nike_Sales_Uncleaned!H181,0)) -> 0 | I175: 0 | J175: =IF(Nike_Sales_Uncleaned[[#This Row],[Order_Date]]="","",Nike_Sales_Uncleaned[[#This Row],[Order_Date]]) -> 45745 | K175: Retail | L175: Pune | M175: 3135.92
A176: 2180 | B176: Women | C176: Basketball | D176: LeBron 20 | E176: =IF(Nike_Sales_Uncleaned!E182="","NA",IF(OR(Nike_Sales_Uncleaned!E182=0,Nike_Sales_Uncleaned!E182=-1),"NA",UPPER(Nike_Sales_Uncleaned!E182))) -> XL | F176: {=IF(Nike_Sales_Uncleaned!F182="",MEDIAN(_xlfn._xlws.FILTER(Nike_Sales_Uncleaned!$F$2:$F$2501,Nike_Sales_Uncleaned!$F$2:$F$2501>0)),Nike_Sales_Uncleaned!F182)} -> 2 | G176: {=IF(OR(Nike_Sales_Uncleaned!G182="",Nike_Sales_Uncleaned!G182<=0),MEDIAN(_xlfn._xlws.FILTER(Nike_Sales_Uncleaned!$G$2:$G$2501,Nike_Sales_Uncleaned!$G$2:$G$2501>0)),Nike_Sales_Uncleaned!G182)} -> 6110.03 | H176: =IF(Nike_Sales_Uncleaned!H182="",0,IF(AND(Nike_Sales_Uncleaned!H182>=0,Nike_Sales_Uncleaned!H182<=1),Nike_Sales_Uncleaned!H182,0)) -> 0 | I176: 0 | J176: =IF(Nike_Sales_Uncleaned[[#This Row],[Order_Date]]="","",Nike_Sales_Uncleaned[[#This Row],[Order_Date]]) | K176: Online | L176: Pune | M176: 2189.84
A177: 2181 | B177: Women | C177: Lifestyle | D177: Air Force 1 | E177: =IF(Nike_Sales_Uncleaned!E183="","NA",IF(OR(Nike_Sales_Uncleaned!E183=0,Nike_Sales_Uncleaned!E183=-1),"NA",UPPER(Nike_Sales_Uncleaned!E183))) -> XL | F177: {=IF(Nike_Sales_Uncleaned!F183="",MEDIAN(_xlfn._xlws.FILTER(Nike_Sales_Uncleaned!$F$2:$F$2501,Nike_Sales_Uncleaned!$F$2:$F$2501>0)),Nike_Sales_Uncleaned!F183)} -> 2 | G177: {=IF(OR(Nike_Sales_Uncleaned!G183="",Nike_Sales_Uncleaned!G183<=0),MEDIAN(_xlfn._xlws.FILTER(Nike_Sales_Uncleaned!$G$2:$G$2501,Nike_Sales_Uncleaned!$G$2:$G$2501>0)),Nike_Sales_Uncleaned!G183)} -> 6110.03 | H177: =IF(Nike_Sales_Uncleaned!H183="",0,IF(AND(Nike_Sales_Uncleaned!H183>=0,Nike_Sales_Uncleaned!H183<=1),Nike_Sales_Uncleaned!H183,0)) -> 0 | I177: 0 | J177: =IF(Nike_Sales_Uncleaned[[#This Row],[Order_Date]]="","",Nike_Sales_Uncleaned[[#This Row],[Order_Date]]) | K177: Retail | L177: Delhi | M177: 419.58
A178: 2182 | B178: Kids | C178: Basketball | D178: Zoom Freak | E178: =IF(Nike_Sales_Uncleaned!E184="","NA",IF(OR(Nike_Sales_Uncleaned!E184=0,Nike_Sales_Uncleaned!E184=-1),"NA",UPPER(Nike_Sales_Uncleaned!E184))) -> 11 | F178: {=IF(Nike_Sales_Uncleaned!F184="",MEDIAN(_xlfn._xlws.FILTER(Nike_Sales_Uncleaned!$F$2:$F$2501,Nike_Sales_Uncleaned!$F$2:$F$2501>0)),Nike_Sales_Uncleaned!F184)} -> 2 | G178: {=IF(OR(Nike_Sales_Uncleaned!G184="",Nike_Sales_Uncleaned!G184<=0),MEDIAN(_xlfn._xlws.FILTER(Nike_Sales_Uncleaned!$G$2:$G$2501,Nike_Sales_Uncleaned!$G$2:$G$2501>0)),Nike_Sales_Uncleaned!G184)} -> 7214.55 | H178: =IF(Nike_Sales_Uncleaned!H184="",0,IF(AND(Nike_Sales_Uncleaned!H184>=0,Nike_Sales_Uncleaned!H184<=1),Nike_Sales_Uncleaned!H184,0)) -> 0 | I178: 0 | J178: =IF(Nike_Sales_Uncleaned[[#This Row],[Order_Date]]="","",Nike_Sales_Uncleaned[[#This Row],[Order_Date]]) -> 45661 | K178: Online | L178: Mumbai | M178: -662.77
A179: 2183 | B179: Kids | C179: Lifestyle | D179: Waffle One | E179: =IF(Nike_Sales_Uncleaned!E185="","NA",IF(OR(Nike_Sales_Uncleaned!E185=0,Nike_Sales_Uncleaned!E185=-1),"NA",UPPER(Nike_Sales_Uncleaned!E185))) -> M | F179: {=IF(Nike_Sales_Uncleaned!F185="",MEDIAN(_xlfn._xlws.FILTER(Nike_Sales_Uncleaned!$F$2:$F$2501,Nike_Sales_Uncleaned!$F$2:$F$2501>0)),Nike_Sales_Uncleaned!F185)} -> 2 | G179: {=IF(OR(Nike_Sales_Uncleaned!G185="",Nike_Sales_Uncleaned!G185<=0),MEDIAN(_xlfn._xlws.FILTER(Nike_Sales_Uncleaned!$G$2:$G$2501,Nike_Sales_Uncleaned!$G$2:$G$2501>0)),Nike_Sales_Uncleaned!G185)} -> 5389.56 | H179: =IF(Nike_Sales_Uncleaned!H185="",0,IF(AND(Nike_Sales_Uncleaned!H185>=0,Nike_Sales_Uncleaned!H185<=1),Nike_Sales_Uncleaned!H185,0)) -> 0 | I179: 0 | J179: =IF(Nike_Sales_Uncleaned[[#This Row],[Order_Date]]="","",Nike_Sales_Uncleaned[[#This Row],[Order_Date]]) -> 45835 | K179: Online | L179: Pune | M179: 2927.93
... A206: 2210 | B206: Men | C206: Lifestyle | D206: Blazer Mid | E206: =IF(Nike_Sales_Uncleaned!E212="","NA",IF(OR(Nike_Sales_Uncleaned!E212=0,Nike_Sales_Uncleaned!E212=-1),"NA",UPPER(Nike_Sales_Uncleaned!E212))) -> XL | F206: {=IF(Nike_Sales_Uncleaned!F212="",MEDIAN(_xlfn._xlws.FILTER(Nike_Sales_Uncleaned!$F$2:$F$2501,Nike_Sales_Uncleaned!$F$2:$F$2501>0)),Nike_Sales_Uncleaned!F212)} -> 2 | G206: {=IF(OR(Nike_Sales_Uncleaned!G212="",Nike_Sales_Uncleaned!G212<=0),MEDIAN(_xlfn._xlws.FILTER(Nike_Sales_Uncleaned!$G$2:$G$2501,Nike_Sales_Uncleaned!$G$2:$G$2501>0)),Nike_Sales_Uncleaned!G212)} -> 6110.03 | H206: =IF(Nike_Sales_Uncleaned!H212="",0,IF(AND(Nike_Sales_Uncleaned!H212>=0,Nike_Sales_Uncleaned!H212<=1),Nike_Sales_Uncleaned!H212,0)) -> 0 | I206: 0 | J206: =IF(Nike_Sales_Uncleaned[[#This Row],[Order_Date]]="","",Nike_Sales_Uncleaned[[#This Row],[Order_Date]]) -> 45794 | K206: Retail | L206: Kolkata | M206: 701.02
A207: 2212 | B207: Women | C207: Lifestyle | D207: Blazer Mid | E207: =IF(Nike_Sales_Uncleaned!E214="","NA",IF(OR(Nike_Sales_Uncleaned!E214=0,Nike_Sales_Uncleaned!E214=-1),"NA",UPPER(Nike_Sales_Uncleaned!E214))) -> L | F207: {=IF(Nike_Sales_Uncleaned!F214="",MEDIAN(_xlfn._xlws.FILTER(Nike_Sales_Uncleaned!$F$2:$F$2501,Nike_Sales_Uncleaned!$F$2:$F$2501>0)),Nike_Sales_Uncleaned!F214)} -> 2 | G207: {=IF(OR(Nike_Sales_Uncleaned!G214="",Nike_Sales_Uncleaned!G214<=0),MEDIAN(_xlfn._xlws.FILTER(Nike_Sales_Uncleaned!$G$2:$G$2501,Nike_Sales_Uncleaned!$G$2:$G$2501>0)),Nike_Sales_Uncleaned!G214)} -> 7670.82 | H207: =IF(Nike_Sales_Uncleaned!H214="",0,IF(AND(Nike_Sales_Uncleaned!H214>=0,Nike_Sales_Uncleaned!H214<=1),Nike_Sales_Uncleaned!H214,0)) -> 0 | I207: 0 | J207: =IF(Nike_Sales_Uncleaned[[#This Row],[Order_Date]]="","",Nike_Sales_Uncleaned[[#This Row],[Order_Date]]) -> 45771 | K207: Online | L207: Kolkata | M207: -87.95
A208: 2213 | B208: Women | C208: Running | D208: Air Zoom | E208: =IF(Nike_Sales_Uncleaned!E215="","NA",IF(OR(Nike_Sales_Uncleaned!E215=0,Nike_Sales_Uncleaned!E215=-1),"NA",UPPER(Nike_Sales_Uncleaned!E215))) -> 9 | F208: {=IF(Nike_Sales_Uncleaned!F215="",MEDIAN(_xlfn._xlws.FILTER(Nike_Sales_Uncleaned!$F$2:$F$2501,Nike_Sales_Uncleaned!$F$2:$F$2501>0)),Nike_Sales_Uncleaned!F215)} -> 2 | G208: {=IF(OR(Nike_Sales_Uncleaned!G215="",Nike_Sales_Uncleaned!G215<=0),MEDIAN(_xlfn._xlws.FILTER(Nike_Sales_Uncleaned!$G$2:$G$2501,Nike_Sales_Uncleaned!$G$2:$G$2501>0)),Nike_Sales_Uncleaned!G215)} -> 5714.92 | H208: =IF(Nike_Sales_Uncleaned!H215="",0,IF(AND(Nike_Sales_Uncleaned!H215>=0,Nike_Sales_Uncleaned!H215<=1),Nike_Sales_Uncleaned!H215,0)) -> 0 | I208: 0 | J208: =IF(Nike_Sales_Uncleaned[[#This Row],[Order_Date]]="","",Nike_Sales_Uncleaned[[#This Row],[Order_Date]]) | K208: Online | L208: Delhi | M208: 3741.14
A209: 2214 | B209: Men | C209: Basketball | D209: LeBron 20 | E209: =IF(Nike_Sales_Uncleaned!E216="","NA",IF(OR(Nike_Sales_Uncleaned!E216=0,Nike_Sales_Uncleaned!E216=-1),"NA",UPPER(Nike_Sales_Uncleaned!E216))) -> XL | F209: {=IF(Nike_Sales_Uncleaned!F216="",MEDIAN(_xlfn._xlws.FILTER(Nike_Sales_Uncleaned!$F$2:$F$2501,Nike_Sales_Uncleaned!$F$2:$F$2501>0)),Nike_Sales_Uncleaned!F216)} -> 2 | G209: {=IF(OR(Nike_Sales_Uncleaned!G216="",Nike_Sales_Uncleaned!G216<=0),MEDIAN(_xlfn._xlws.FILTER(Nike_Sales_Uncleaned!$G$2:$G$2501,Nike_Sales_Uncleaned!$G$2:$G$2501>0)),Nike_Sales_Uncleaned!G216)} -> 5016.03 | H209: =IF(Nike_Sales_Uncleaned!H216="",0,IF(AND(Nike_Sales_Uncleaned!H216>=0,Nike_Sales_Uncleaned!H216<=1),Nike_Sales_Uncleaned!H216,0)) -> 0 | I209: 0 | J209: =IF(Nike_Sales_Uncleaned[[#This Row],[Order_Date]]="","",Nike_Sales_Uncleaned[[#This Row],[Order_Date]]) | K209: Retail | L209: Mumbai | M209: 1446
A210: 2215 | B210: Men | C210: Basketball | D210: Zoom Freak | E210: =IF(Nike_Sales_Uncleaned!E217="","NA",IF(OR(Nike_Sales_Uncleaned!E217=0,Nike_Sales_Uncleaned!E217=-1),"NA",UPPER(Nike_Sales_Uncleaned!E217))) -> XL | F210: {=IF(Nike_Sales_Uncleaned!F217="",MEDIAN(_xlfn._xlws.FILTER(Nike_Sales_Uncleaned!$F$2:$F$2501,Nike_Sales_Uncleaned!$F$2:$F$2501>0)),Nike_Sales_Uncleaned!F217)} -> 3 | G210: {=IF(OR(Nike_Sales_Uncleaned!G217="",Nike_Sales_Uncleaned!G217<=0),MEDIAN(_xlfn._xlws.FILTER(Nike_Sales_Uncleaned!$G$2:$G$2501,Nike_Sales_Uncleaned!$G$2:$G$2501>0)),Nike_Sales_Uncleaned!G217)} -> 6110.03 | H210: =IF(Nike_Sales_Uncleaned!H217="",0,IF(AND(Nike_Sales_Uncleaned!H217>=0,Nike_Sales_Uncleaned!H217<=1),Nike_Sales_Uncleaned!H217,0)) -> 0.36 | I210: 0 | J210: =IF(Nike_Sales_Uncleaned[[#This Row],[Order_Date]]="","",Nike_Sales_Uncleaned[[#This Row],[Order_Date]]) | K210: Online | L210: Kolkata | M210: 3254.06
A211: 2216 | B211: Women | C211: Lifestyle | D211: Air Force 1 | E211: =IF(Nike_Sales_Uncleaned!E218="","NA",IF(OR(Nike_Sales_Uncleaned!E218=0,Nike_Sales_Uncleaned!E218=-1),"NA",UPPER(Nike_Sales_Uncleaned!E218))) -> M | F211: {=IF(Nike_Sales_Uncleaned!F218="",MEDIAN(_xlfn._xlws.FILTER(Nike_Sales_Uncleaned!$F$2:$F$2501,Nike_Sales_Uncleaned!$F$2:$F$2501>0)),Nike_Sales_Uncleaned!F218)} -> 1 | G211: {=IF(OR(Nike_Sales_Uncleaned!G218="",Nike_Sales_Uncleaned!G218<=0),MEDIAN(_xlfn._xlws.FILTER(Nike_Sales_Uncleaned!$G$2:$G$2501,Nike_Sales_Uncleaned!$G$2:$G$2501>0)),Nike_Sales_Uncleaned!G218)} -> 3111.62 | H211: =IF(Nike_Sales_Uncleaned!H218="",0,IF(AND(Nike_Sales_Uncleaned!H218>=0,Nike_Sales_Uncleaned!H218<=1),Nike_Sales_Uncleaned!H218,0)) -> 0 | I211: 0 | J211: =IF(Nike_Sales_Uncleaned[[#This Row],[Order_Date]]="","",Nike_Sales_Uncleaned[[#This Row],[Order_Date]]) -> 45536 | K211: Online | L211: Hyderabad | M211: 2617.56
A212: 2217 | B212: Women | C212: Lifestyle | D212: Waffle One | E212: =IF(Nike_Sales_Uncleaned!E219="","NA",IF(OR(Nike_Sales_Uncleaned!E219=0,Nike_Sales_Uncleaned!E219=-1),"NA",UPPER(Nike_Sales_Uncleaned!E219))) -> L | F212: {=IF(Nike_Sales_Uncleaned!F219="",MEDIAN(_xlfn._xlws.FILTER(Nike_Sales_Uncleaned!$F$2:$F$2501,Nike_Sales_Uncleaned!$F$2:$F$2501>0)),Nike_Sales_Uncleaned!F219)} -> 2 | G212: {=IF(OR(Nike_Sales_Uncleaned!G219="",Nike_Sales_Uncleaned!G219<=0),MEDIAN(_xlfn._xlws.FILTER(Nike_Sales_Uncleaned!$G$2:$G$2501,Nike_Sales_Uncleaned!$G$2:$G$2501>0)),Nike_Sales_Uncleaned!G219)} -> 6110.03 | H212: =IF(Nike_Sales_Uncleaned!H219="",0,IF(AND(Nike_Sales_Uncleaned!H219>=0,Nike_Sales_Uncleaned!H219<=1),Nike_Sales_Uncleaned!H219,0)) -> 0 | I212: 0 | J212: =IF(Nike_Sales_Uncleaned[[#This Row],[Order_Date]]="","",Nike_Sales_Uncleaned[[#This Row],[Order_Date]]) -> 45513 | K212: Retail | L212: Delhi | M212: 2190.84
A213: 2218 | B213: Kids | C213: Soccer | D213: Premier III | E213: =IF(Nike_Sales_Uncleaned!E220="","NA",IF(OR(Nike_Sales_Uncleaned!E220=0,Nike_Sales_Uncleaned!E220=-1),"NA",UPPER(Nike_Sales_Uncleaned!E220))) -> 6 | F213: {=IF(Nike_Sales_Uncleaned!F220="",MEDIAN(_xlfn._xlws.FILTER(Nike_Sales_Uncleaned!$F$2:$F$2501,Nike_Sales_Uncleaned!$F$2:$F$2501>0)),Nike_Sales_Uncleaned!F220)} -> 2 | G213: {=IF(OR(Nike_Sales_Uncleaned!G220="",Nike_Sales_Uncleaned!G220<=0),MEDIAN(_xlfn._xlws.FILTER(Nike_Sales_Uncleaned!$G$2:$G$2501,Nike_Sales_Uncleaned!$G$2:$G$2501>0)),Nike_Sales_Uncleaned!G220)} -> 6110.03 | H213: =IF(Nike_Sales_Uncleaned!H220="",0,IF(AND(Nike_Sales_Uncleaned!H220>=0,Nike_Sales_Uncleaned!H220<=1),Nike_Sales_Uncleaned!H220,0)) -> 0 | I213: 0 | J213: =IF(Nike_Sales_Uncleaned[[#This Row],[Order_Date]]="","",Nike_Sales_Uncleaned[[#This Row],[Order_Date]]) -> 45349 | K213: Online | L213: Bangalore | M213: 1440.02
A214: 2219 | B214: Women | C214: Basketball | D214: Air Jordan | E214: =IF(Nike_Sales_Uncleaned!E221="","NA",IF(OR(Nike_Sales_Uncleaned!E221=0,Nike_Sales_Uncleaned!E221=-1),"NA",UPPER(Nike_Sales_Uncleaned!E221))) -> M | F214: {=IF(Nike_Sales_Uncleaned!F221="",MEDIAN(_xlfn._xlws.FILTER(Nike_Sales_Uncleaned!$F$2:$F$2501,Nike_Sales_Uncleaned!$F$2:$F$2501>0)),Nike_Sales_Uncleaned!F221)} -> -1 | G214: {=IF(OR(Nike_Sales_Uncleaned!G221="",Nike_Sales_Uncleaned!G221<=0),MEDIAN(_xlfn._xlws.FILTER(Nike_Sales_Uncleaned!$G$2:$G$2501,Nike_Sales_Uncleaned!$G$2:$G$2501>0)),Nike_Sales_Uncleaned!G221)} -> 6110.03 | H214: =IF(Nike_Sales_Uncleaned!H221="",0,IF(AND(Nike_Sales_Uncleaned!H221>=0,Nike_Sales_Uncleaned!H221<=1),Nike_Sales_Uncleaned!H221,0)) -> 0 | I214: 0 | J214: =IF(Nike_Sales_Uncleaned[[#This Row],[Order_Date]]="","",Nike_Sales_Uncleaned[[#This Row],[Order_Date]]) -> 45558 | K214: Online | L214: Bangalore | M214: 3305.72
...

Sheet Pivot Tables
B8: Sales by Product Line | E8: Sales by Region | I8: Sales By Gender
B9: Row Labels | C9: Sum of Revenue | E9: Row Labels | F9: Sum of Revenue | G9: Sum of Profit | I9: Row Labels | J9: Sum of Revenue | K9: Sum of Units_Sold
B10: Basketball | C10: 159372.33 | E10: Bangalore | F10: 102745.56 | G10: 608017.7 | I10: Kids | J10: 196029.84 | K10: 1394
B11: Lifestyle | C11: 136624.33 | E11: Delhi | F11: 97181.96 | G11: 560808.32 | I11: Men | J11: 262493.77 | K11: 1406
B12: Running | C12: 72075.95 | E12: Hyderabad | F12: 126847.67 | G12: 498376.83 | I12: Women | J12: 219942.99 | K12: 1340
B13: Soccer | C13: 114213.03 | E13: Kolkata | F13: 156634 | G13: 568729.41 | I13: Grand Total | J13: 678466.6 | K13: 4140
B14: Training | C14: 196180.96 | E14: Mumbai | F14: 93880.14 | G14: 555487.9
B15: Grand Total | C15: 678466.6 | E15: Pune | F15: 101177.27 | G15: 521704.46
E16: Grand Total | F16: 678466.6 | G16: 3313124.6
F20: Sales by Year And Month
F21: Row Labels | G21: Sum of Units_Sold | H21: Sum of Revenue
F22: <26-07-2023 | G22: 968 | H22: 139909.65
F23: 2023 | G23: 177 | H23: 43945.34
F24: 2024 | G24: 1544 | H24: 254762.53
F25: 2025 | G25: 1451 | H25: 239849.08
F26: Grand Total | G26: 4140 | H26: 678466.6

Sheet Fact_Sales
A1: Sales_ID | B1: Order_ID | C1: Product_Key | D1: Date_key_0 | E1: Region_key | F1: Channel_Key | G1: Gender_key | H1: Units_Sold | I1: MRP | J1: Discount_Applied | K1: Revenue | L1: Profit | M1: Product_Name | N1: Product_Line | O1: Size | P1: Product_temp | Q1: Order_Date | R1: Region | S1: Channel | T1: Gender_category | U1: Date_key | V1: Column2 | W1: Column1
A2: SID-01 | B2: =Cleaned_Data[[#This Row],[Order_ID]] -> 2000 | C2: =_xlfn.XLOOKUP(P2,Dim_Product!$E$2:$E$221,Dim_Product!$A$2:$A$221,"Not Found") -> PK-01 | D2: =_xlfn.XLOOKUP(Table5[[#This Row],[Order_Date]],Table8[Date],Table8[Date_Key],"") -> DK-228 | E2: =_xlfn.XLOOKUP(R2,Table4[Region],Table4[Region_Key]) -> RK-01 | F2: =_xlfn.XLOOKUP(S2,Table6[Sales_Channel],Table6[Channel_Key]) -> CK-01 | G2: =_xlfn.XLOOKUP(T2,Table7[Gender_Category],Table7[Gender_Key]) -> GK-01 | H2: =Cleaned_Data[[#This Row],[Units_Sold]] -> 2 | I2: =Cleaned_Data[[#This Row],[MRP]] -> 6110.03 | J2: =Cleaned_Data[[#This Row],[Discount_Applied]] -> 0.47 | K2: =Cleaned_Data[[#This Row],[Revenue]] -> 0 | L2: =Cleaned_Data[[#This Row],[Profit]] -> -770.45 | M2: =Cleaned_Data[[#This Row],[Product_Name]] -> SuperRep Go | N2: =Cleaned_Data[[#This Row],[Product_Line]] -> Training | O2: =Cleaned_Data[[#This Row],[Size]] -> M | P2: =TRIM(M2)&"|"&TRIM(N2)&"|"&TRIM(O2) -> SuperRep Go|Training|M | Q2: =Cleaned_Data[[#This Row],[Order_Date]] -> 45360 | R2: =Cleaned_Data[[#This Row],[Region]] -> Bangalore | S2: =Cleaned_Data[[#This Row],[Sales_Channel]] -> Online | T2: =Cleaned_Data[[#This Row],[Gender_Category]] -> Kids | U2: =IF(D2="",0,D2) -> DK-228
A3: SID-02 | B3: =Cleaned_Data[[#This Row],[Order_ID]] -> 2001 | C3: =_xlfn.XLOOKUP(P3,Dim_Product!$E$2:$E$221,Dim_Product!$A$2:$A$221,"Not Found") -> PK-02 | D3: =_xlfn.XLOOKUP(Table5[[#This Row],[Order_Date]],Table8[Date],Table8[Date_Key],"Not Found") -> DK-350 | E3: =_xlfn.XLOOKUP(R3,Table4[Region],Table4[Region_Key]) -> RK-02 | F3: =_xlfn.XLOOKUP(S3,Table6[Sales_Channel],Table6[Channel_Key]) -> CK-02 | G3: =_xlfn.XLOOKUP(T3,Table7[Gender_Category],Table7[Gender_Key]) -> GK-02 | H3: =Cleaned_Data[[#This Row],[Units_Sold]] -> 3 | I3: =Cleaned_Data[[#This Row],[MRP]] -> 4957.93 | J3: =Cleaned_Data[[#This Row],[Discount_Applied]] -> 0 | K3: =Cleaned_Data[[#This Row],[Revenue]] -> 0 | L3: =Cleaned_Data[[#This Row],[Profit]] -> -112.53 | M3: =Cleaned_Data[[#This Row],[Product_Name]] -> Tiempo Legend | N3: =Cleaned_Data[[#This Row],[Product_Line]] -> Soccer | O3: =Cleaned_Data[[#This Row],[Size]] -> M | P3: =TRIM(M3)&"|"&TRIM(N3)&"|"&TRIM(O3) -> Tiempo Legend|Soccer|M | Q3: =Cleaned_Data[[#This Row],[Order_Date]] -> 45482 | R3: =Cleaned_Data[[#This Row],[Region]] -> Hyderabad | S3: =Cleaned_Data[[#This Row],[Sales_Channel]] -> Retail | T3: =Cleaned_Data[[#This Row],[Gender_Category]] -> Women | U3: =IF(D3="",0,D3) -> DK-350
A4: SID-03 | B4: =Cleaned_Data[[#This Row],[Order_ID]] -> 2002 | C4: =_xlfn.XLOOKUP(P4,Dim_Product!$E$2:$E$221,Dim_Product!$A$2:$A$221,"Not Found") -> PK-03 | D4: =_xlfn.XLOOKUP(Table5[[#This Row],[Order_Date]],Table8[Date],Table8[Date_Key],"Not Found") -> Not Found | E4: =_xlfn.XLOOKUP(R4,Table4[Region],Table4[Region_Key]) -> RK-03 | F4: =_xlfn.XLOOKUP(S4,Table6[Sales_Channel],Table6[Channel_Key]) -> CK-02 | G4: =_xlfn.XLOOKUP(T4,Table7[Gender_Category],Table7[Gender_Key]) -> GK-02 | H4: =Cleaned_Data[[#This Row],[Units_Sold]] -> 4 | I4: =Cleaned_Data[[#This Row],[MRP]] -> 6110.03 | J4: =Cleaned_Data[[#This Row],[Discount_Applied]] -> 0 | K4: =Cleaned_Data[[#This Row],[Revenue]] -> 0 | L4: =Cleaned_Data[[#This Row],[Profit]] -> 3337.34 | M4: =Cleaned_Data[[#This Row],[Product_Name]] -> Premier III | N4: =Cleaned_Data[[#This Row],[Product_Line]] -> Soccer | O4: =Cleaned_Data[[#This Row],[Size]] -> M | P4: =TRIM(M4)&"|"&TRIM(N4)&"|"&TRIM(O4) -> Premier III|Soccer|M | Q4: =Cleaned_Data[[#This Row],[Order_Date]] | R4: =Cleaned_Data[[#This Row],[Region]] -> Mumbai | S4: =Cleaned_Data[[#This Row],[Sales_Channel]] -> Retail | T4: =Cleaned_Data[[#This Row],[Gender_Category]] -> Women | U4: =IF(D4="",0,D4) -> Not Found
A5: SID-04 | B5: =Cleaned_Data[[#This Row],[Order_ID]] -> 2003 | C5: =_xlfn.XLOOKUP(P5,Dim_Product!$E$2:$E$221,Dim_Product!$A$2:$A$221,"Not Found") -> PK-04 | D5: =_xlfn.XLOOKUP(Table5[[#This Row],[Order_Date]],Table8[Date],Table8[Date_Key],"Not Found") -> DK-437 | E5: =_xlfn.XLOOKUP(R5,Table4[Region],Table4[Region_Key]) -> RK-04 | F5: =_xlfn.XLOOKUP(S5,Table6[Sales_Channel],Table6[Channel_Key]) -> CK-01 | G5: =_xlfn.XLOOKUP(T5,Table7[Gender_Category],Table7[Gender_Key]) -> GK-01 | H5: =Cleaned_Data[[#This Row],[Units_Sold]] -> 2 | I5: =Cleaned_Data[[#This Row],[MRP]] -> 9673.57 | J5: =Cleaned_Data[[#This Row],[Discount_Applied]] -> 0 | K5: =Cleaned_Data[[#This Row],[Revenue]] -> 0 | L5: =Cleaned_Data[[#This Row],[Profit]] -> 3376.85 | M5: =Cleaned_Data[[#This Row],[Product_Name]] -> Blazer Mid | N5: =Cleaned_Data[[#This Row],[Product_Line]] -> Lifestyle | O5: =Cleaned_Data[[#This Row],[Size]] -> L | P5: =TRIM(M5)&"|"&TRIM(N5)&"|"&TRIM(O5) -> Blazer Mid|Lifestyle|L | Q5: =Cleaned_Data[[#This Row],[Order_Date]] -> 45569 | R5: =Cleaned_Data[[#This Row],[Region]] -> Pune | S5: =Cleaned_Data[[#This Row],[Sales_Channel]] -> Online | T5: =Cleaned_Data[[#This Row],[Gender_Category]] -> Kids | U5: =IF(D5="",0,D5) -> DK-437
A6: SID-05 | B6: =Cleaned_Data[[#This Row],[Order_ID]] -> 2004 | C6: =_xlfn.XLOOKUP(P6,Dim_Product!$E$2:$E$221,Dim_Product!$A$2:$A$221,"Not Found") -> PK-05 | D6: =_xlfn.XLOOKUP(Table5[[#This Row],[Order_Date]],Table8[Date],Table8[Date_Key],"Not Found") -> DK-415 | E6: =_xlfn.XLOOKUP(R6,Table4[Region],Table4[Region_Key]) -> RK-05 | F6: =_xlfn.XLOOKUP(S6,Table6[Sales_Channel],Table6[Channel_Key]) -> CK-02 | G6: =_xlfn.XLOOKUP(T6,Table7[Gender_Category],Table7[Gender_Key]) -> GK-01 | H6: =Cleaned_Data[[#This Row],[Units_Sold]] -> 2 | I6: =Cleaned_Data[[#This Row],[MRP]] -> 6110.03 | J6: =Cleaned_Data[[#This Row],[Discount_Applied]] -> 0 | K6: =Cleaned_Data[[#This Row],[Revenue]] -> 0 | L6: =Cleaned_Data[[#This Row],[Profit]] -> 187.89 | M6: =Cleaned_Data[[#This Row],[Product_Name]] -> React Infinity | N6: =Cleaned_Data[[#This Row],[Product_Line]] -> Running | O6: =Cleaned_Data[[#This Row],[Size]] -> XL | P6: =TRIM(M6)&"|"&TRIM(N6)&"|"&TRIM(O6) -> React Infinity|Running|XL | Q6: =Cleaned_Data[[#This Row],[Order_Date]] -> 45547 | R6: =Cleaned_Data[[#This Row],[Region]] -> Delhi | S6: =Cleaned_Data[[#This Row],[Sales_Channel]] -> Retail | T6: =Cleaned_Data[[#This Row],[Gender_Category]] -> Kids | U6: =IF(D6="",0,D6) -> DK-415
A7: SID-06 | B7: =Cleaned_Data[[#This Row],[Order_ID]] -> 2005 | C7: =_xlfn.XLOOKUP(P7,Dim_Product!$E$2:$E$221,Dim_Product!$A$2:$A$221,"Not Found") -> PK-06 | D7: =_xlfn.XLOOKUP(Table5[[#This Row],[Order_Date]],Table8[Date],Table8[Date_Key],"Not Found") -> Not Found | E7: =_xlfn.XLOOKUP(R7,Table4[Region],Table4[Region_Key]) -> RK-05 | F7: =_xlfn.XLOOKUP(S7,Table6[Sales_Channel],Table6[Channel_Key]) -> CK-02 | G7: =_xlfn.XLOOKUP(T7,Table7[Gender_Category],Table7[Gender_Key]) -> GK-02 | H7: =Cleaned_Data[[#This Row],[Units_Sold]] -> 1 | I7: =Cleaned_Data[[#This Row],[MRP]] -> 7363.96 | J7: =Cleaned_Data[[#This Row],[Discount_Applied]] -> 0 | K7: =Cleaned_Data[[#This Row],[Revenue]] -> 0 | L7: =Cleaned_Data[[#This Row],[Profit]] -> 1415.98 | M7: =Cleaned_Data[[#This Row],[Product_Name]] -> Flex Trainer | N7: =Cleaned_Data[[#This Row],[Product_Line]] -> Training | O7: =Cleaned_Data[[#This Row],[Size]] -> M | P7: =TRIM(M7)&"|"&TRIM(N7)&"|"&TRIM(O7) -> Flex Trainer|Training|M | Q7: =Cleaned_Data[[#This Row],[Order_Date]] | R7: =Cleaned_Data[[#This Row],[Region]] -> Delhi | S7: =Cleaned_Data[[#This Row],[Sales_Channel]] -> Retail | T7: =Cleaned_Data[[#This Row],[Gender_Category]] -> Women | U7: =IF(D7="",0,D7) -> Not Found
A8: SID-07 | B8: =Cleaned_Data[[#This Row],[Order_ID]] -> 2006 | C8: =_xlfn.XLOOKUP(P8,Dim_Product!$E$2:$E$221,Dim_Product!$A$2:$A$221,"Not Found") -> PK-01 | D8: =_xlfn.XLOOKUP(Table5[[#This Row],[Order_Date]],Table8[Date],Table8[Date_Key],"Not Found") -> DK-680 | E8: =_xlfn.XLOOKUP(R8,Table4[Region],Table4[Region_Key]) -> RK-01 | F8: =_xlfn.XLOOKUP(S8,Table6[Sales_Channel],Table6[Channel_Key]) -> CK-01 | G8: =_xlfn.XLOOKUP(T8,Table7[Gender_Category],Table7[Gender_Key]) -> GK-03 | H8: =Cleaned_Data[[#This Row],[Units_Sold]] -> 2 | I8: =Cleaned_Data[[#This Row],[MRP]] -> 6819.78 | J8: =Cleaned_Data[[#This Row],[Discount_Applied]] -> 0 | K8: =Cleaned_Data[[#This Row],[Revenue]] -> 0 | L8: =Cleaned_Data[[#This Row],[Profit]] -> 1802.09 | M8: =Cleaned_Data[[#This Row],[Product_Name]] -> SuperRep Go | N8: =Cleaned_Data[[#This Row],[Product_Line]] -> Training | O8: =Cleaned_Data[[#This Row],[Size]] -> M | P8: =TRIM(M8)&"|"&TRIM(N8)&"|"&TRIM(O8) -> SuperRep Go|Training|M | Q8: =Cleaned_Data[[#This Row],[Order_Date]] -> 45812 | R8: =Cleaned_Data[[#This Row],[Region]] -> Bangalore | S8: =Cleaned_Data[[#This Row],[Sales_Channel]] -> Online | T8: =Cleaned_Data[[#This Row],[Gender_Category]] -> Men | U8: =IF(D8="",0,D8) -> DK-680
A9: SID-08 | B9: =Cleaned_Data[[#This Row],[Order_ID]] -> 2007 | C9: =_xlfn.XLOOKUP(P9,Dim_Product!$E$2:$E$221,Dim_Product!$A$2:$A$221,"Not Found") -> PK-01 | D9: =_xlfn.XLOOKUP(Table5[[#This Row],[Order_Date]],Table8[Date],Table8[Date_Key],"Not Found") -> Not Found | E9: =_xlfn.XLOOKUP(R9,Table4[Region],Table4[Region_Key]) -> RK-01 | F9: =_xlfn.XLOOKUP(S9,Table6[Sales_Channel],Table6[Channel_Key]) -> CK-02 | G9: =_xlfn.XLOOKUP(T9,Table7[Gender_Category],Table7[Gender_Key]) -> GK-01 | H9: =Cleaned_Data[[#This Row],[Units_Sold]] -> 1 | I9: =Cleaned_Data[[#This Row],[MRP]] -> 6110.03 | J9: =Cleaned_Data[[#This Row],[Discount_Applied]] -> 0.32 | K9: =Cleaned_Data[[#This Row],[Revenue]] -> 0 | L9: =Cleaned_Data[[#This Row],[Profit]] -> 2928.36 | M9: =Cleaned_Data[[#This Row],[Product_Name]] -> SuperRep Go | N9: =Cleaned_Data[[#This Row],[Product_Line]] -> Training | O9: =Cleaned_Data[[#This Row],[Size]] -> M | P9: =TRIM(M9)&"|"&TRIM(N9)&"|"&TRIM(O9) -> SuperRep Go|Training|M | Q9: =Cleaned_Data[[#This Row],[Order_Date]] | R9: =Cleaned_Data[[#This Row],[Region]] -> Bangalore | S9: =Cleaned_Data[[#This Row],[Sales_Channel]] -> Retail | T9: =Cleaned_Data[[#This Row],[Gender_Category]] -> Kids | U9: =IF(D9="",0,D9) -> Not Found
A10: SID-09 | B10: =Cleaned_Data[[#This Row],[Order_ID]] -> 2008 | C10: =_xlfn.XLOOKUP(P10,Dim_Product!$E$2:$E$221,Dim_Product!$A$2:$A$221,"Not Found") -> PK-07 | D10: =_xlfn.XLOOKUP(Table5[[#This Row],[Order_Date]],Table8[Date],Table8[Date_Key],"Not Found") -> DK-444 | E10: =_xlfn.XLOOKUP(R10,Table4[Region],Table4[Region_Key]) -> RK-02 | F10: =_xlfn.XLOOKUP(S10,Table6[Sales_Channel],Table6[Channel_Key]) -> CK-01 | G10: =_xlfn.XLOOKUP(T10,Table7[Gender_Category],Table7[Gender_Key]) -> GK-02 | H10: =Cleaned_Data[[#This Row],[Units_Sold]] -> -1 | I10: =Cleaned_Data[[#This Row],[MRP]] -> 6110.03 | J10: =Cleaned_Data[[#This Row],[Discount_Applied]] -> 0 | K10: =Cleaned_Data[[#This Row],[Revenue]] -> 0 | L10: =Cleaned_Data[[#This Row],[Profit]] -> -731.18 | M10: =Cleaned_Data[[#This Row],[Product_Name]] -> Premier III | N10: =Cleaned_Data[[#This Row],[Product_Line]] -> Soccer | O10: =Cleaned_Data[[#This Row],[Size]] -> 11 | P10: =TRIM(M10)&"|"&TRIM(N10)&"|"&TRIM(O10) -> Premier III|Soccer|11 | Q10: =Cleaned_Data[[#This Row],[Order_Date]] -> 45576 | R10: =Cleaned_Data[[#This Row],[Region]] -> Hyderabad | S10: =Cleaned_Data[[#This Row],[Sales_Channel]] -> Online | T10: =Cleaned_Data[[#This Row],[Gender_Category]] -> Women | U10: =IF(D10="",0,D10) -> DK-444
A11: SID-10 | B11: =Cleaned_Data[[#This Row],[Order_ID]] -> 2009 | C11: =_xlfn.XLOOKUP(P11,Dim_Product!$E$2:$E$221,Dim_Product!$A$2:$A$221,"Not Found") -> PK-08 | D11: =_xlfn.XLOOKUP(Table5[[#This Row],[Order_Date]],Table8[Date],Table8[Date_Key],"Not Found") -> Not Found | E11: =_xlfn.XLOOKUP(R11,Table4[Region],Table4[Region_Key]) -> RK-04 | F11: =_xlfn.XLOOKUP(S11,Table6[Sales_Channel],Table6[Channel_Key]) -> CK-01 | G11: =_xlfn.XLOOKUP(T11,Table7[Gender_Category],Table7[Gender_Key]) -> GK-03 | H11: =Cleaned_Data[[#This Row],[Units_Sold]] -> 4 | I11: =Cleaned_Data[[#This Row],[MRP]] -> 6110.03 | J11: =Cleaned_Data[[#This Row],[Discount_Applied]] -> 0 | K11: =Cleaned_Data[[#This Row],[Revenue]] -> 0 | L11: =Cleaned_Data[[#This Row],[Profit]] -> 3929.61 | M11: =Cleaned_Data[[#This Row],[Product_Name]] -> Mercurial Superfly | N11: =Cleaned_Data[[#This Row],[Product_Line]] -> Soccer | O11: =Cleaned_Data[[#This Row],[Size]] -> M | P11: =TRIM(M11)&"|"&TRIM(N11)&"|"&TRIM(O11) -> Mercurial Superfly|Soccer|M | Q11: =Cleaned_Data[[#This Row],[Order_Date]] | R11: =Cleaned_Data[[#This Row],[Region]] -> Pune | S11: =Cleaned_Data[[#This Row],[Sales_Channel]] -> Online | T11: =Cleaned_Data[[#This Row],[Gender_Category]] -> Men | U11: =IF(D11="",0,D11) -> Not Found
A12: SID-11 | B12: =Cleaned_Data[[#This Row],[Order_ID]] -> 2010 | C12: =_xlfn.XLOOKUP(P12,Dim_Product!$E$2:$E$221,Dim_Product!$A$2:$A$221,"Not Found") -> PK-09 | D12: =_xlfn.XLOOKUP(Table5[[#This Row],[Order_Date]],Table8[Date],Table8[Date_Key],"Not Found") -> DK-541 | E12: =_xlfn.XLOOKUP(R12,Table4[Region],Table4[Region_Key]) -> RK-04 | F12: =_xlfn.XLOOKUP(S12,Table6[Sales_Channel],Table6[Channel_Key]) -> CK-01 | G12: =_xlfn.XLOOKUP(T12,Table7[Gender_Category],Table7[Gender_Key]) -> GK-01 | H12: =Cleaned_Data[[#This Row],[Units_Sold]] -> 1 | I12: =Cleaned_Data[[#This Row],[MRP]] -> 7949.83 | J12: =Cleaned_Data[[#This Row],[Discount_Applied]] -> 0 | K12: =Cleaned_Data[[#This Row],[Revenue]] -> 0 | L12: =Cleaned_Data[[#This Row],[Profit]] -> 1965.56 | M12: =Cleaned_Data[[#This Row],[Product_Name]] -> Waffle One | N12: =Cleaned_Data[[#This Row],[Product_Line]] -> Lifestyle | O12: =Cleaned_Data[[#This Row],[Size]] -> L | P12: =TRIM(M12)&"|"&TRIM(N12)&"|"&TRIM(O12) -> Waffle One|Lifestyle|L | Q12: =Cleaned_Data[[#This Row],[Order_Date]] -> 45673 | R12: =Cleaned_Data[[#This Row],[Region]] -> Pune | S12: =Cleaned_Data[[#This Row],[Sales_Channel]] -> Online | T12: =Cleaned_Data[[#This Row],[Gender_Category]] -> Kids | U12: =IF(D12="",0,D12) -> DK-541
A13: SID-12 | B13: =Cleaned_Data[[#This Row],[Order_ID]] -> 2011 | C13: =_xlfn.XLOOKUP(P13,Dim_Product!$E$2:$E$221,Dim_Product!$A$2:$A$221,"Not Found") -> PK-10 | D13: =_xlfn.XLOOKUP(Table5[[#This Row],[Order_Date]],Table8[Date],Table8[Date_Key],"Not Found") -> Not Found | E13: =_xlfn.XLOOKUP(R13,Table4[Region],Table4[Region_Key]) -> RK-02 | F13: =_xlfn.XLOOKUP(S13,Table6[Sales_Channel],Table6[Channel_Key]) -> CK-02 | G13: =_xlfn.XLOOKUP(T13,Table7[Gender_Category],Table7[Gender_Key]) -> GK-02 | H13: =Cleaned_Data[[#This Row],[Units_Sold]] -> -1 | I13: =Cleaned_Data[[#This Row],[MRP]] -> 9586.08 | J13: =Cleaned_Data[[#This Row],[Discount_Applied]] -> 0 | K13: =Cleaned_Data[[#This Row],[Revenue]] -> 0 | L13: =Cleaned_Data[[#This Row],[Profit]] -> 1667.08 | M13: =Cleaned_Data[[#This Row],[Product_Name]] -> Flex Trainer | N13: =Cleaned_Data[[#This Row],[Product_Line]] -> Training | O13: =Cleaned_Data[[#This Row],[Size]] -> L | P13: =TRIM(M13)&"|"&TRIM(N13)&"|"&TRIM(O13) -> Flex Trainer|Training|L | Q13: =Cleaned_Data[[#This Row],[Order_Date]] | R13: =Cleaned_Data[[#This Row],[Region]] -> Hyderabad | S13: =Cleaned_Data[[#This Row],[Sales_Channel]] -> Retail | T13: =Cleaned_Data[[#This Row],[Gender_Category]] -> Women | U13: =IF(D13="",0,D13) -> Not Found
A14: SID-13 | B14: =Cleaned_Data[[#This Row],[Order_ID]] -> 2018 | C14: =_xlfn.XLOOKUP(P14,Dim_Product!$E$2:$E$221,Dim_Product!$A$2:$A$221,"Not Found") -> PK-11 | D14: =_xlfn.XLOOKUP(Table5[[#This Row],[Order_Date]],Table8[Date],Table8[Date_Key],"Not Found") -> DK-477 | E14: =_xlfn.XLOOKUP(R14,Table4[Region],Table4[Region_Key]) -> RK-05 | F14: =_xlfn.XLOOKUP(S14,Table6[Sales_Channel],Table6[Channel_Key]) -> CK-01 | G14: =_xlfn.XLOOKUP(T14,Table7[Gender_Category],Table7[Gender_Key]) -> GK-01 | H14: =Cleaned_Data[[#This Row],[Units_Sold]] -> -1 | I14: =Cleaned_Data[[#This Row],[MRP]] -> 6110.03 | J14: =Cleaned_Data[[#This Row],[Discount_Applied]] -> 0.86 | K14: =Cleaned_Data[[#This Row],[Revenue]] -> 0 | L14: =Cleaned_Data[[#This Row],[Profit]] -> 2109.48 | M14: =Cleaned_Data[[#This Row],[Product_Name]] -> Blazer Mid | N14: =Cleaned_Data[[#This Row],[Product_Line]] -> Lifestyle | O14: =Cleaned_Data[[#This Row],[Size]] -> NA | P14: =TRIM(M14)&"|"&TRIM(N14)&"|"&TRIM(O14) -> Blazer Mid|Lifestyle|NA | Q14: =Cleaned_Data[[#This Row],[Order_Date]] -> 45609 | R14: =Cleaned_Data[[#This Row],[Region]] -> Delhi | S14: =Cleaned_Data[[#This Row],[Sales_Channel]] -> Online | T14: =Cleaned_Data[[#This Row],[Gender_Category]] -> Kids | U14: =IF(D14="",0,D14) -> DK-477
... A2387: SID-2386 | B2387: =Cleaned_Data[[#This Row],[Order_ID]] -> 4499 | C2387: =_xlfn.XLOOKUP(P2387,Dim_Product!$E$2:$E$221,Dim_Product!$A$2:$A$221,"Not Found") -> PK-114 | D2387: =_xlfn.XLOOKUP(Table5[[#This Row],[Order_Date]],Table8[Date],Table8[Date_Key],"Not Found") -> DK-141 | E2387: =_xlfn.XLOOKUP(R2387,Table4[Region],Table4[Region_Key]) -> RK-03 | F2387: =_xlfn.XLOOKUP(S2387,Table6[Sales_Channel],Table6[Channel_Key]) -> CK-02 | G2387: =_xlfn.XLOOKUP(T2387,Table7[Gender_Category],Table7[Gender_Key]) -> GK-02 | H2387: =Cleaned_Data[[#This Row],[Units_Sold]] -> 2 | I2387: =Cleaned_Data[[#This Row],[MRP]] -> 5550.99 | J2387: =Cleaned_Data[[#This Row],[Discount_Applied]] -> 0 | K2387: =Cleaned_Data[[#This Row],[Revenue]] -> 0 | L2387: =Cleaned_Data[[#This Row],[Profit]] -> 2453.57 | M2387: =Cleaned_Data[[#This Row],[Product_Name]] -> Air Zoom | N2387: =Cleaned_Data[[#This Row],[Product_Line]] -> Running | O2387: =Cleaned_Data[[#This Row],[Size]] -> M | P2387: =TRIM(M2387)&"|"&TRIM(N2387)&"|"&TRIM(O2387) -> Air Zoom|Running|M | Q2387: =Cleaned_Data[[#This Row],[Order_Date]] -> 45273 | R2387: =Cleaned_Data[[#This Row],[Region]] -> Mumbai | S2387: =Cleaned_Data[[#This Row],[Sales_Channel]] -> Retail | T2387: =Cleaned_Data[[#This Row],[Gender_Category]] -> Women | U2387: =IF(D2387="",0,D2387) -> DK-141

Sheet Dim_Product
A1: Product_Key | B1: Product_Name | C1: Product_Line | D1: Size | E1: Product_Lookup_Key
A2: PK-01 | B2: SuperRep Go | C2: Training | D2: =IF(Nike_Sales_Uncleaned!E2="","NA",IF(OR(Nike_Sales_Uncleaned!E2=0,Nike_Sales_Uncleaned!E2=-1),"NA",UPPER(Nike_Sales_Uncleaned!E2))) -> M | E2: =TRIM(B2)&"|"&TRIM(C2)&"|"&TRIM(D2) -> SuperRep Go|Training|M
A3: PK-02 | B3: Tiempo Legend | C3: Soccer | D3: =IF(Nike_Sales_Uncleaned!E3="","NA",IF(OR(Nike_Sales_Uncleaned!E3=0,Nike_Sales_Uncleaned!E3=-1),"NA",UPPER(Nike_Sales_Uncleaned!E3))) -> M | E3: =TRIM(B3)&"|"&TRIM(C3)&"|"&TRIM(D3) -> Tiempo Legend|Soccer|M
A4: PK-03 | B4: Premier III | C4: Soccer | D4: =IF(Nike_Sales_Uncleaned!E4="","NA",IF(OR(Nike_Sales_Uncleaned!E4=0,Nike_Sales_Uncleaned!E4=-1),"NA",UPPER(Nike_Sales_Uncleaned!E4))) -> M | E4: =TRIM(B4)&"|"&TRIM(C4)&"|"&TRIM(D4) -> Premier III|Soccer|M
A5: PK-04 | B5: Blazer Mid | C5: Lifestyle | D5: =IF(Nike_Sales_Uncleaned!E5="","NA",IF(OR(Nike_Sales_Uncleaned!E5=0,Nike_Sales_Uncleaned!E5=-1),"NA",UPPER(Nike_Sales_Uncleaned!E5))) -> L | E5: =TRIM(B5)&"|"&TRIM(C5)&"|"&TRIM(D5) -> Blazer Mid|Lifestyle|L
A6: PK-05 | B6: React Infinity | C6: Running | D6: =IF(Nike_Sales_Uncleaned!E6="","NA",IF(OR(Nike_Sales_Uncleaned!E6=0,Nike_Sales_Uncleaned!E6=-1),"NA",UPPER(Nike_Sales_Uncleaned!E6))) -> XL | E6: =TRIM(B6)&"|"&TRIM(C6)&"|"&TRIM(D6) -> React Infinity|Running|XL
A7: PK-06 | B7: Flex Trainer | C7: Training | D7: =IF(Nike_Sales_Uncleaned!E7="","NA",IF(OR(Nike_Sales_Uncleaned!E7=0,Nike_Sales_Uncleaned!E7=-1),"NA",UPPER(Nike_Sales_Uncleaned!E7))) -> M | E7: =TRIM(B7)&"|"&TRIM(C7)&"|"&TRIM(D7) -> Flex Trainer|Training|M
A8: PK-07 | B8: Premier III | C8: Soccer | D8: =IF(Nike_Sales_Uncleaned!E10="","NA",IF(OR(Nike_Sales_Uncleaned!E10=0,Nike_Sales_Uncleaned!E10=-1),"NA",UPPER(Nike_Sales_Uncleaned!E10))) -> 11 | E8: =TRIM(B8)&"|"&TRIM(C8)&"|"&TRIM(D8) -> Premier III|Soccer|11
A9: PK-08 | B9: Mercurial Superfly | C9: Soccer | D9: =IF(Nike_Sales_Uncleaned!E11="","NA",IF(OR(Nike_Sales_Uncleaned!E11=0,Nike_Sales_Uncleaned!E11=-1),"NA",UPPER(Nike_Sales_Uncleaned!E11))) -> M | E9: =TRIM(B9)&"|"&TRIM(C9)&"|"&TRIM(D9) -> Mercurial Superfly|Soccer|M
A10: PK-09 | B10: Waffle One | C10: Lifestyle | D10: =IF(Nike_Sales_Uncleaned!E12="","NA",IF(OR(Nike_Sales_Uncleaned!E12=0,Nike_Sales_Uncleaned!E12=-1),"NA",UPPER(Nike_Sales_Uncleaned!E12))) -> L | E10: =TRIM(B10)&"|"&TRIM(C10)&"|"&TRIM(D10) -> Waffle One|Lifestyle|L
A11: PK-10 | B11: Flex Trainer | C11: Training | D11: =IF(Nike_Sales_Uncleaned!E13="","NA",IF(OR(Nike_Sales_Uncleaned!E13=0,Nike_Sales_Uncleaned!E13=-1),"NA",UPPER(Nike_Sales_Uncleaned!E13))) -> L | E11: =TRIM(B11)&"|"&TRIM(C11)&"|"&TRIM(D11) -> Flex Trainer|Training|L
A12: PK-11 | B12: Blazer Mid | C12: Lifestyle | D12: =IF(Nike_Sales_Uncleaned!E14="","NA",IF(OR(Nike_Sales_Uncleaned!E14=0,Nike_Sales_Uncleaned!E14=-1),"NA",UPPER(Nike_Sales_Uncleaned!E14))) -> NA | E12: =TRIM(B12)&"|"&TRIM(C12)&"|"&TRIM(D12) -> Blazer Mid|Lifestyle|NA
A13: PK-12 | B13: SuperRep Go | C13: Training | D13: =IF(Nike_Sales_Uncleaned!E15="","NA",IF(OR(Nike_Sales_Uncleaned!E15=0,Nike_Sales_Uncleaned!E15=-1),"NA",UPPER(Nike_Sales_Uncleaned!E15))) -> NA | E13: =TRIM(B13)&"|"&TRIM(C13)&"|"&TRIM(D13) -> SuperRep Go|Training|NA
A14: PK-13 | B14: React Infinity | C14: Running | D14: =IF(Nike_Sales_Uncleaned!E16="","NA",IF(OR(Nike_Sales_Uncleaned!E16=0,Nike_Sales_Uncleaned!E16=-1),"NA",UPPER(Nike_Sales_Uncleaned!E16))) -> 11 | E14: =TRIM(B14)&"|"&TRIM(C14)&"|"&TRIM(D14) -> React Infinity|Running|11
A15: PK-14 | B15: Air Jordan | C15: Basketball | D15: =IF(Nike_Sales_Uncleaned!E17="","NA",IF(OR(Nike_Sales_Uncleaned!E17=0,Nike_Sales_Uncleaned!E17=-1),"NA",UPPER(Nike_Sales_Uncleaned!E17))) -> NA | E15: =TRIM(B15)&"|"&TRIM(C15)&"|"&TRIM(D15) -> Air Jordan|Basketball|NA
A16: PK-15 | B16: Air Jordan | C16: Basketball | D16: =IF(Nike_Sales_Uncleaned!E18="","NA",IF(OR(Nike_Sales_Uncleaned!E18=0,Nike_Sales_Uncleaned!E18=-1),"NA",UPPER(Nike_Sales_Uncleaned!E18))) -> M | E16: =TRIM(B16)&"|"&TRIM(C16)&"|"&TRIM(D16) -> Air Jordan|Basketball|M
A17: PK-16 | B17: Air Jordan | C17: Basketball | D17: =IF(Nike_Sales_Uncleaned!E19="","NA",IF(OR(Nike_Sales_Uncleaned!E19=0,Nike_Sales_Uncleaned!E19=-1),"NA",UPPER(Nike_Sales_Uncleaned!E19))) -> 9 | E17: =TRIM(B17)&"|"&TRIM(C17)&"|"&TRIM(D17) -> Air Jordan|Basketball|9
A18: PK-17 | B18: Air Zoom | C18: Running | D18: =IF(Nike_Sales_Uncleaned!E21="","NA",IF(OR(Nike_Sales_Uncleaned!E21=0,Nike_Sales_Uncleaned!E21=-1),"NA",UPPER(Nike_Sales_Uncleaned!E21))) -> 6 | E18: =TRIM(B18)&"|"&TRIM(C18)&"|"&TRIM(D18) -> Air Zoom|Running|6
A19: PK-18 | B19: Tiempo Legend | C19: Soccer | D19: =IF(Nike_Sales_Uncleaned!E22="","NA",IF(OR(Nike_Sales_Uncleaned!E22=0,Nike_Sales_Uncleaned!E22=-1),"NA",UPPER(Nike_Sales_Uncleaned!E22))) -> L | E19: =TRIM(B19)&"|"&TRIM(C19)&"|"&TRIM(D19) -> Tiempo Legend|Soccer|L
A20: PK-19 | B20: Free RN | C20: Running | D20: =IF(Nike_Sales_Uncleaned!E23="","NA",IF(OR(Nike_Sales_Uncleaned!E23=0,Nike_Sales_Uncleaned!E23=-1),"NA",UPPER(Nike_Sales_Uncleaned!E23))) -> L | E20: =TRIM(B20)&"|"&TRIM(C20)&"|"&TRIM(D20) -> Free RN|Running|L
A21: PK-20 | B21: Waffle One | C21: Lifestyle | D21: =IF(Nike_Sales_Uncleaned!E25="","NA",IF(OR(Nike_Sales_Uncleaned!E25=0,Nike_Sales_Uncleaned!E25=-1),"NA",UPPER(Nike_Sales_Uncleaned!E25))) -> M | E21: =TRIM(B21)&"|"&TRIM(C21)&"|"&TRIM(D21) -> Waffle One|Lifestyle|M
A22: PK-21 | B22: SuperRep Go | C22: Training | D22: =IF(Nike_Sales_Uncleaned!E26="","NA",IF(OR(Nike_Sales_Uncleaned!E26=0,Nike_Sales_Uncleaned!E26=-1),"NA",UPPER(Nike_Sales_Uncleaned!E26))) -> XL | E22: =TRIM(B22)&"|"&TRIM(C22)&"|"&TRIM(D22) -> SuperRep Go|Training|XL
A23: PK-22 | B23: Kyrie Flytrap | C23: Basketball | D23: =IF(Nike_Sales_Uncleaned!E27="","NA",IF(OR(Nike_Sales_Uncleaned!E27=0,Nike_Sales_Uncleaned!E27=-1),"NA",UPPER(Nike_Sales_Uncleaned!E27))) -> M | E23: =TRIM(B23)&"|"&TRIM(C23)&"|"&TRIM(D23) -> Kyrie Flytrap|Basketball|M
A24: PK-23 | B24: Blazer Mid | C24: Lifestyle | D24: =IF(Nike_Sales_Uncleaned!E28="","NA",IF(OR(Nike_Sales_Uncleaned!E28=0,Nike_Sales_Uncleaned!E28=-1),"NA",UPPER(Nike_Sales_Uncleaned!E28))) -> XL | E24: =TRIM(B24)&"|"&TRIM(C24)&"|"&TRIM(D24) -> Blazer Mid|Lifestyle|XL
A25: PK-24 | B25: Zoom Freak | C25: Basketball | D25: =IF(Nike_Sales_Uncleaned!E29="","NA",IF(OR(Nike_Sales_Uncleaned!E29=0,Nike_Sales_Uncleaned!E29=-1),"NA",UPPER(Nike_Sales_Uncleaned!E29))) -> XL | E25: =TRIM(B25)&"|"&TRIM(C25)&"|"&TRIM(D25) -> Zoom Freak|Basketball|XL
A26: PK-25 | B26: Flex Trainer | C26: Training | D26: =IF(Nike_Sales_Uncleaned!E30="","NA",IF(OR(Nike_Sales_Uncleaned!E30=0,Nike_Sales_Uncleaned!E30=-1),"NA",UPPER(Nike_Sales_Uncleaned!E30))) -> 12 | E26: =TRIM(B26)&"|"&TRIM(C26)&"|"&TRIM(D26) -> Flex Trainer|Training|12
A27: PK-26 | B27: ZoomX Invincible | C27: Training | D27: =IF(Nike_Sales_Uncleaned!E31="","NA",IF(OR(Nike_Sales_Uncleaned!E31=0,Nike_Sales_Uncleaned!E31=-1),"NA",UPPER(Nike_Sales_Uncleaned!E31))) -> 12 | E27: =TRIM(B27)&"|"&TRIM(C27)&"|"&TRIM(D27) -> ZoomX Invincible|Training|12
A28: PK-27 | B28: Phantom GT | C28: Soccer | D28: =IF(Nike_Sales_Uncleaned!E32="","NA",IF(OR(Nike_Sales_Uncleaned!E32=0,Nike_Sales_Uncleaned!E32=-1),"NA",UPPER(Nike_Sales_Uncleaned!E32))) -> XL | E28: =TRIM(B28)&"|"&TRIM(C28)&"|"&TRIM(D28) -> Phantom GT|Soccer|XL
A29: PK-28 | B29: Premier III | C29: Soccer | D29: =IF(Nike_Sales_Uncleaned!E33="","NA",IF(OR(Nike_Sales_Uncleaned!E33=0,Nike_Sales_Uncleaned!E33=-1),"NA",UPPER(Nike_Sales_Uncleaned!E33))) -> NA | E29: =TRIM(B29)&"|"&TRIM(C29)&"|"&TRIM(D29) -> Premier III|Soccer|NA
A30: PK-29 | B30: Mercurial Superfly | C30: Soccer | D30: =IF(Nike_Sales_Uncleaned!E35="","NA",IF(OR(Nike_Sales_Uncleaned!E35=0,Nike_Sales_Uncleaned!E35=-1),"NA",UPPER(Nike_Sales_Uncleaned!E35))) -> XL | E30: =TRIM(B30)&"|"&TRIM(C30)&"|"&TRIM(D30) -> Mercurial Superfly|Soccer|XL
A31: PK-30 | B31: Air Jordan | C31: Basketball | D31: =IF(Nike_Sales_Uncleaned!E36="","NA",IF(OR(Nike_Sales_Uncleaned!E36=0,Nike_Sales_Uncleaned!E36=-1),"NA",UPPER(Nike_Sales_Uncleaned!E36))) -> 6 | E31: =TRIM(B31)&"|"&TRIM(C31)&"|"&TRIM(D31) -> Air Jordan|Basketball|6
A32: PK-31 | B32: Zoom Freak | C32: Basketball | D32: =IF(Nike_Sales_Uncleaned!E37="","NA",IF(OR(Nike_Sales_Uncleaned!E37=0,Nike_Sales_Uncleaned!E37=-1),"NA",UPPER(Nike_Sales_Uncleaned!E37))) -> NA | E32: =TRIM(B32)&"|"&TRIM(C32)&"|"&TRIM(D32) -> Zoom Freak|Basketball|NA
A33: PK-32 | B33: Metcon 7 | C33: Training | D33: =IF(Nike_Sales_Uncleaned!E38="","NA",IF(OR(Nike_Sales_Uncleaned!E38=0,Nike_Sales_Uncleaned!E38=-1),"NA",UPPER(Nike_Sales_Uncleaned!E38))) -> NA | E33: =TRIM(B33)&"|"&TRIM(C33)&"|"&TRIM(D33) -> Metcon 7|Training|NA
A34: PK-33 | B34: Pegasus Turbo | C34: Running | D34: =IF(Nike_Sales_Uncleaned!E39="","NA",IF(OR(Nike_Sales_Uncleaned!E39=0,Nike_Sales_Uncleaned!E39=-1),"NA",UPPER(Nike_Sales_Uncleaned!E39))) -> 7 | E34: =TRIM(B34)&"|"&TRIM(C34)&"|"&TRIM(D34) -> Pegasus Turbo|Running|7
A35: PK-34 | B35: Free RN | C35: Running | D35: =IF(Nike_Sales_Uncleaned!E40="","NA",IF(OR(Nike_Sales_Uncleaned!E40=0,Nike_Sales_Uncleaned!E40=-1),"NA",UPPER(Nike_Sales_Uncleaned!E40))) -> NA | E35: =TRIM(B35)&"|"&TRIM(C35)&"|"&TRIM(D35) -> Free RN|Running|NA
A36: PK-35 | B36: Tiempo Legend | C36: Soccer | D36: =IF(Nike_Sales_Uncleaned!E43="","NA",IF(OR(Nike_Sales_Uncleaned!E43=0,Nike_Sales_Uncleaned!E43=-1),"NA",UPPER(Nike_Sales_Uncleaned!E43))) -> 12 | E36: =TRIM(B36)&"|"&TRIM(C36)&"|"&TRIM(D36) -> Tiempo Legend|Soccer|12
A37: PK-36 | B37: Kyrie Flytrap | C37: Basketball | D37: =IF(Nike_Sales_Uncleaned!E44="","NA",IF(OR(Nike_Sales_Uncleaned!E44=0,Nike_Sales_Uncleaned!E44=-1),"NA",UPPER(Nike_Sales_Uncleaned!E44))) -> L | E37: =TRIM(B37)&"|"&TRIM(C37)&"|"&TRIM(D37) -> Kyrie Flytrap|Basketball|L
A38: PK-37 | B38: Premier III | C38: Soccer | D38: =IF(Nike_Sales_Uncleaned!E45="","NA",IF(OR(Nike_Sales_Uncleaned!E45=0,Nike_Sales_Uncleaned!E45=-1),"NA",UPPER(Nike_Sales_Uncleaned!E45))) -> XL | E38: =TRIM(B38)&"|"&TRIM(C38)&"|"&TRIM(D38) -> Premier III|Soccer|XL
A39: PK-38 | B39: Dunk Low | C39: Lifestyle | D39: =IF(Nike_Sales_Uncleaned!E47="","NA",IF(OR(Nike_Sales_Uncleaned!E47=0,Nike_Sales_Uncleaned!E47=-1),"NA",UPPER(Nike_Sales_Uncleaned!E47))) -> XL | E39: =TRIM(B39)&"|"&TRIM(C39)&"|"&TRIM(D39) -> Dunk Low|Lifestyle|XL
A40: PK-39 | B40: Air Zoom | C40: Running | D40: =IF(Nike_Sales_Uncleaned!E48="","NA",IF(OR(Nike_Sales_Uncleaned!E48=0,Nike_Sales_Uncleaned!E48=-1),"NA",UPPER(Nike_Sales_Uncleaned!E48))) -> 12 | E40: =TRIM(B40)&"|"&TRIM(C40)&"|"&TRIM(D40) -> Air Zoom|Running|12
A41: PK-40 | B41: SuperRep Go | C41: Training | D41: =IF(Nike_Sales_Uncleaned!E49="","NA",IF(OR(Nike_Sales_Uncleaned!E49=0,Nike_Sales_Uncleaned!E49=-1),"NA",UPPER(Nike_Sales_Uncleaned!E49))) -> 10 | E41: =TRIM(B41)&"|"&TRIM(C41)&"|"&TRIM(D41) -> SuperRep Go|Training|10
A42: PK-41 | B42: Air Jordan | C42: Basketball | D42: =IF(Nike_Sales_Uncleaned!E50="","NA",IF(OR(Nike_Sales_Uncleaned!E50=0,Nike_Sales_Uncleaned!E50=-1),"NA",UPPER(Nike_Sales_Uncleaned!E50))) -> XL | E42: =TRIM(B42)&"|"&TRIM(C42)&"|"&TRIM(D42) -> Air Jordan|Basketball|XL
A43: PK-42 | B43: Air Zoom | C43: Running | D43: =IF(Nike_Sales_Uncleaned!E52="","NA",IF(OR(Nike_Sales_Uncleaned!E52=0,Nike_Sales_Uncleaned!E52=-1),"NA",UPPER(Nike_Sales_Uncleaned!E52))) -> L | E43: =TRIM(B43)&"|"&TRIM(C43)&"|"&TRIM(D43) -> Air Zoom|Running|L
A44: PK-43 | B44: Flex Trainer | C44: Training | D44: =IF(Nike_Sales_Uncleaned!E54="","NA",IF(OR(Nike_Sales_Uncleaned!E54=0,Nike_Sales_Uncleaned!E54=-1),"NA",UPPER(Nike_Sales_Uncleaned!E54))) -> 10 | E44: =TRIM(B44)&"|"&TRIM(C44)&"|"&TRIM(D44) -> Flex Trainer|Training|10
A45: PK-44 | B45: Air Force 1 | C45: Lifestyle | D45: =IF(Nike_Sales_Uncleaned!E55="","NA",IF(OR(Nike_Sales_Uncleaned!E55=0,Nike_Sales_Uncleaned!E55=-1),"NA",UPPER(Nike_Sales_Uncleaned!E55))) -> XL | E45: =TRIM(B45)&"|"&TRIM(C45)&"|"&TRIM(D45) -> Air Force 1|Lifestyle|XL
A46: PK-45 | B46: Flex Trainer | C46: Training | D46: =IF(Nike_Sales_Uncleaned!E56="","NA",IF(OR(Nike_Sales_Uncleaned!E56=0,Nike_Sales_Uncleaned!E56=-1),"NA",UPPER(Nike_Sales_Uncleaned!E56))) -> 11 | E46: =TRIM(B46)&"|"&TRIM(C46)&"|"&TRIM(D46) -> Flex Trainer|Training|11
A47: PK-46 | B47: React Infinity | C47: Running | D47: =IF(Nike_Sales_Uncleaned!E58="","NA",IF(OR(Nike_Sales_Uncleaned!E58=0,Nike_Sales_Uncleaned!E58=-1),"NA",UPPER(Nike_Sales_Uncleaned!E58))) -> L | E47: =TRIM(B47)&"|"&TRIM(C47)&"|"&TRIM(D47) -> React Infinity|Running|L
A48: PK-47 | B48: Phantom GT | C48: Soccer | D48: =IF(Nike_Sales_Uncleaned!E61="","NA",IF(OR(Nike_Sales_Uncleaned!E61=0,Nike_Sales_Uncleaned!E61=-1),"NA",UPPER(Nike_Sales_Uncleaned!E61))) -> NA | E48: =TRIM(B48)&"|"&TRIM(C48)&"|"&TRIM(D48) -> Phantom GT|Soccer|NA
A49: PK-48 | B49: LeBron 20 | C49: Basketball | D49: =IF(Nike_Sales_Uncleaned!E63="","NA",IF(OR(Nike_Sales_Uncleaned!E63=0,Nike_Sales_Uncleaned!E63=-1),"NA",UPPER(Nike_Sales_Uncleaned!E63))) -> L | E49: =TRIM(B49)&"|"&TRIM(C49)&"|"&TRIM(D49) -> LeBron 20|Basketball|L
A50: PK-49 | B50: Waffle One | C50: Lifestyle | D50: =IF(Nike_Sales_Uncleaned!E67="","NA",IF(OR(Nike_Sales_Uncleaned!E67=0,Nike_Sales_Uncleaned!E67=-1),"NA",UPPER(Nike_Sales_Uncleaned!E67))) -> 10 | E50: =TRIM(B50)&"|"&TRIM(C50)&"|"&TRIM(D50) -> Waffle One|Lifestyle|10
A51: PK-50 | B51: Blazer Mid | C51: Lifestyle | D51: =IF(Nike_Sales_Uncleaned!E73="","NA",IF(OR(Nike_Sales_Uncleaned!E73=0,Nike_Sales_Uncleaned!E73=-1),"NA",UPPER(Nike_Sales_Uncleaned!E73))) -> M | E51: =TRIM(B51)&"|"&TRIM(C51)&"|"&TRIM(D51) -> Blazer Mid|Lifestyle|M
A52: PK-51 | B52: Flex Trainer | C52: Training | D52: =IF(Nike_Sales_Uncleaned!E74="","NA",IF(OR(Nike_Sales_Uncleaned!E74=0,Nike_Sales_Uncleaned!E74=-1),"NA",UPPER(Nike_Sales_Uncleaned!E74))) -> NA | E52: =TRIM(B52)&"|"&TRIM(C52)&"|"&TRIM(D52) -> Flex Trainer|Training|NA
A53: PK-52 | B53: Blazer Mid | C53: Lifestyle | D53: =IF(Nike_Sales_Uncleaned!E75="","NA",IF(OR(Nike_Sales_Uncleaned!E75=0,Nike_Sales_Uncleaned!E75=-1),"NA",UPPER(Nike_Sales_Uncleaned!E75))) -> 12 | E53: =TRIM(B53)&"|"&TRIM(C53)&"|"&TRIM(D53) -> Blazer Mid|Lifestyle|12
A54: PK-53 | B54: Air Jordan | C54: Basketball | D54: =IF(Nike_Sales_Uncleaned!E77="","NA",IF(OR(Nike_Sales_Uncleaned!E77=0,Nike_Sales_Uncleaned!E77=-1),"NA",UPPER(Nike_Sales_Uncleaned!E77))) -> L | E54: =TRIM(B54)&"|"&TRIM(C54)&"|"&TRIM(D54) -> Air Jordan|Basketball|L
A55: PK-54 | B55: ZoomX Invincible | C55: Training | D55: =IF(Nike_Sales_Uncleaned!E78="","NA",IF(OR(Nike_Sales_Uncleaned!E78=0,Nike_Sales_Uncleaned!E78=-1),"NA",UPPER(Nike_Sales_Uncleaned!E78))) -> 11 | E55: =TRIM(B55)&"|"&TRIM(C55)&"|"&TRIM(D55) -> ZoomX Invincible|Training|11
A56: PK-55 | B56: ZoomX Invincible | C56: Training | D56: =IF(Nike_Sales_Uncleaned!E79="","NA",IF(OR(Nike_Sales_Uncleaned!E79=0,Nike_Sales_Uncleaned!E79=-1),"NA",UPPER(Nike_Sales_Uncleaned!E79))) -> L | E56: =TRIM(B56)&"|"&TRIM(C56)&"|"&TRIM(D56) -> ZoomX Invincible|Training|L
A57: PK-56 | B57: LeBron 20 | C57: Basketball | D57: =IF(Nike_Sales_Uncleaned!E80="","NA",IF(OR(Nike_Sales_Uncleaned!E80=0,Nike_Sales_Uncleaned!E80=-1),"NA",UPPER(Nike_Sales_Uncleaned!E80))) -> NA | E57: =TRIM(B57)&"|"&TRIM(C57)&"|"&TRIM(D57) -> LeBron 20|Basketball|NA
A58: PK-57 | B58: Pegasus Turbo | C58: Running | D58: =IF(Nike_Sales_Uncleaned!E81="","NA",IF(OR(Nike_Sales_Uncleaned!E81=0,Nike_Sales_Uncleaned!E81=-1),"NA",UPPER(Nike_Sales_Uncleaned!E81))) -> XL | E58: =TRIM(B58)&"|"&TRIM(C58)&"|"&TRIM(D58) -> Pegasus Turbo|Running|XL
A59: PK-58 | B59: Metcon 7 | C59: Training | D59: =IF(Nike_Sales_Uncleaned!E86="","NA",IF(OR(Nike_Sales_Uncleaned!E86=0,Nike_Sales_Uncleaned!E86=-1),"NA",UPPER(Nike_Sales_Uncleaned!E86))) -> M | E59: =TRIM(B59)&"|"&TRIM(C59)&"|"&TRIM(D59) -> Metcon 7|Training|M
A60: PK-59 | B60: Kyrie Flytrap | C60: Basketball | D60: =IF(Nike_Sales_Uncleaned!E87="","NA",IF(OR(Nike_Sales_Uncleaned!E87=0,Nike_Sales_Uncleaned!E87=-1),"NA",UPPER(Nike_Sales_Uncleaned!E87))) -> NA | E60: =TRIM(B60)&"|"&TRIM(C60)&"|"&TRIM(D60) -> Kyrie Flytrap|Basketball|NA
A61: PK-60 | B61: Mercurial Superfly | C61: Soccer | D61: =IF(Nike_Sales_Uncleaned!E88="","NA",IF(OR(Nike_Sales_Uncleaned!E88=0,Nike_Sales_Uncleaned!E88=-1),"NA",UPPER(Nike_Sales_Uncleaned!E88))) -> L | E61: =TRIM(B61)&"|"&TRIM(C61)&"|"&TRIM(D61) -> Mercurial Superfly|Soccer|L
A62: PK-61 | B62: Free RN | C62: Running | D62: =IF(Nike_Sales_Uncleaned!E90="","NA",IF(OR(Nike_Sales_Uncleaned!E90=0,Nike_Sales_Uncleaned!E90=-1),"NA",UPPER(Nike_Sales_Uncleaned!E90))) -> XL | E62: =TRIM(B62)&"|"&TRIM(C62)&"|"&TRIM(D62) -> Free RN|Running|XL
A63: PK-62 | B63: Dunk Low | C63: Lifestyle | D63: =IF(Nike_Sales_Uncleaned!E92="","NA",IF(OR(Nike_Sales_Uncleaned!E92=0,Nike_Sales_Uncleaned!E92=-1),"NA",UPPER(Nike_Sales_Uncleaned!E92))) -> 8 | E63: =TRIM(B63)&"|"&TRIM(C63)&"|"&TRIM(D63) -> Dunk Low|Lifestyle|8
A64: PK-63 | B64: Air Zoom | C64: Running | D64: =IF(Nike_Sales_Uncleaned!E93="","NA",IF(OR(Nike_Sales_Uncleaned!E93=0,Nike_Sales_Uncleaned!E93=-1),"NA",UPPER(Nike_Sales_Uncleaned!E93))) -> 11 | E64: =TRIM(B64)&"|"&TRIM(C64)&"|"&TRIM(D64) -> Air Zoom|Running|11
A65: PK-64 | B65: ZoomX Invincible | C65: Training | D65: =IF(Nike_Sales_Uncleaned!E99="","NA",IF(OR(Nike_Sales_Uncleaned!E99=0,Nike_Sales_Uncleaned!E99=-1),"NA",UPPER(Nike_Sales_Uncleaned!E99))) -> XL | E65: =TRIM(B65)&"|"&TRIM(C65)&"|"&TRIM(D65) -> ZoomX Invincible|Training|XL
A66: PK-65 | B66: Phantom GT | C66: Soccer | D66: =IF(Nike_Sales_Uncleaned!E102="","NA",IF(OR(Nike_Sales_Uncleaned!E102=0,Nike_Sales_Uncleaned!E102=-1),"NA",UPPER(Nike_Sales_Uncleaned!E102))) -> 8 | E66: =TRIM(B66)&"|"&TRIM(C66)&"|"&TRIM(D66) -> Phantom GT|Soccer|8
A67: PK-66 | B67: LeBron 20 | C67: Basketball | D67: =IF(Nike_Sales_Uncleaned!E105="","NA",IF(OR(Nike_Sales_Uncleaned!E105=0,Nike_Sales_Uncleaned!E105=-1),"NA",UPPER(Nike_Sales_Uncleaned!E105))) -> XL | E67: =TRIM(B67)&"|"&TRIM(C67)&"|"&TRIM(D67) -> LeBron 20|Basketball|XL
A68: PK-67 | B68: React Infinity | C68: Running | D68: =IF(Nike_Sales_Uncleaned!E109="","NA",IF(OR(Nike_Sales_Uncleaned!E109=0,Nike_Sales_Uncleaned!E109=-1),"NA",UPPER(Nike_Sales_Uncleaned!E109))) -> M | E68: =TRIM(B68)&"|"&TRIM(C68)&"|"&TRIM(D68) -> React Infinity|Running|M
A69: PK-68 | B69: Zoom Freak | C69: Basketball | D69: =IF(Nike_Sales_Uncleaned!E111="","NA",IF(OR(Nike_Sales_Uncleaned!E111=0,Nike_Sales_Uncleaned!E111=-1),"NA",UPPER(Nike_Sales_Uncleaned!E111))) -> M | E69: =TRIM(B69)&"|"&TRIM(C69)&"|"&TRIM(D69) -> Zoom Freak|Basketball|M
A70: PK-69 | B70: Waffle One | C70: Lifestyle | D70: =IF(Nike_Sales_Uncleaned!E113="","NA",IF(OR(Nike_Sales_Uncleaned!E113=0,Nike_Sales_Uncleaned!E113=-1),"NA",UPPER(Nike_Sales_Uncleaned!E113))) -> NA | E70: =TRIM(B70)&"|"&TRIM(C70)&"|"&TRIM(D70) -> Waffle One|Lifestyle|NA
A71: PK-70 | B71: Flex Trainer | C71: Training | D71: =IF(Nike_Sales_Uncleaned!E116="","NA",IF(OR(Nike_Sales_Uncleaned!E116=0,Nike_Sales_Uncleaned!E116=-1),"NA",UPPER(Nike_Sales_Uncleaned!E116))) -> XL | E71: =TRIM(B71)&"|"&TRIM(C71)&"|"&TRIM(D71) -> Flex Trainer|Training|XL
A72: PK-71 | B72: Phantom GT | C72: Soccer | D72: =IF(Nike_Sales_Uncleaned!E117="","NA",IF(OR(Nike_Sales_Uncleaned!E117=0,Nike_Sales_Uncleaned!E117=-1),"NA",UPPER(Nike_Sales_Uncleaned!E117))) -> 6 | E72: =TRIM(B72)&"|"&TRIM(C72)&"|"&TRIM(D72) -> Phantom GT|Soccer|6
A73: PK-72 | B73: SuperRep Go | C73: Training | D73: =IF(Nike_Sales_Uncleaned!E119="","NA",IF(OR(Nike_Sales_Uncleaned!E119=0,Nike_Sales_Uncleaned!E119=-1),"NA",UPPER(Nike_Sales_Uncleaned!E119))) -> L | E73: =TRIM(B73)&"|"&TRIM(C73)&"|"&TRIM(D73) -> SuperRep Go|Training|L
A74: PK-73 | B74: Metcon 7 | C74: Training | D74: =IF(Nike_Sales_Uncleaned!E121="","NA",IF(OR(Nike_Sales_Uncleaned!E121=0,Nike_Sales_Uncleaned!E121=-1),"NA",UPPER(Nike_Sales_Uncleaned!E121))) -> 11 | E74: =TRIM(B74)&"|"&TRIM(C74)&"|"&TRIM(D74) -> Metcon 7|Training|11
A75: PK-74 | B75: Phantom GT | C75: Soccer | D75: =IF(Nike_Sales_Uncleaned!E122="","NA",IF(OR(Nike_Sales_Uncleaned!E122=0,Nike_Sales_Uncleaned!E122=-1),"NA",UPPER(Nike_Sales_Uncleaned!E122))) -> 12 | E75: =TRIM(B75)&"|"&TRIM(C75)&"|"&TRIM(D75) -> Phantom GT|Soccer|12
A76: PK-75 | B76: Mercurial Superfly | C76: Soccer | D76: =IF(Nike_Sales_Uncleaned!E124="","NA",IF(OR(Nike_Sales_Uncleaned!E124=0,Nike_Sales_Uncleaned!E124=-1),"NA",UPPER(Nike_Sales_Uncleaned!E124))) -> NA | E76: =TRIM(B76)&"|"&TRIM(C76)&"|"&TRIM(D76) -> Mercurial Superfly|Soccer|NA
A77: PK-76 | B77: Pegasus Turbo | C77: Running | D77: =IF(Nike_Sales_Uncleaned!E128="","NA",IF(OR(Nike_Sales_Uncleaned!E128=0,Nike_Sales_Uncleaned!E128=-1),"NA",UPPER(Nike_Sales_Uncleaned!E128))) -> L | E77: =TRIM(B77)&"|"&TRIM(C77)&"|"&TRIM(D77) -> Pegasus Turbo|Running|L
A78: PK-77 | B78: Metcon 7 | C78: Training | D78: =IF(Nike_Sales_Uncleaned!E129="","NA",IF(OR(Nike_Sales_Uncleaned!E129=0,Nike_Sales_Uncleaned!E129=-1),"NA",UPPER(Nike_Sales_Uncleaned!E129))) -> L | E78: =TRIM(B78)&"|"&TRIM(C78)&"|"&TRIM(D78) -> Metcon 7|Training|L
A79: PK-78 | B79: Zoom Freak | C79: Basketball | D79: =IF(Nike_Sales_Uncleaned!E131="","NA",IF(OR(Nike_Sales_Uncleaned!E131=0,Nike_Sales_Uncleaned!E131=-1),"NA",UPPER(Nike_Sales_Uncleaned!E131))) -> 9 | E79: =TRIM(B79)&"|"&TRIM(C79)&"|"&TRIM(D79) -> Zoom Freak|Basketball|9
A80: PK-79 | B80: Premier III | C80: Soccer | D80: =IF(Nike_Sales_Uncleaned!E132="","NA",IF(OR(Nike_Sales_Uncleaned!E132=0,Nike_Sales_Uncleaned!E132=-1),"NA",UPPER(Nike_Sales_Uncleaned!E132))) -> 10 | E80: =TRIM(B80)&"|"&TRIM(C80)&"|"&TRIM(D80) -> Premier III|Soccer|10
A81: PK-80 | B81: Metcon 7 | C81: Training | D81: =IF(Nike_Sales_Uncleaned!E135="","NA",IF(OR(Nike_Sales_Uncleaned!E135=0,Nike_Sales_Uncleaned!E135=-1),"NA",UPPER(Nike_Sales_Uncleaned!E135))) -> XL | E81: =TRIM(B81)&"|"&TRIM(C81)&"|"&TRIM(D81) -> Metcon 7|Training|XL
A82: PK-81 | B82: ZoomX Invincible | C82: Training | D82: =IF(Nike_Sales_Uncleaned!E136="","NA",IF(OR(Nike_Sales_Uncleaned!E136=0,Nike_Sales_Uncleaned!E136=-1),"NA",UPPER(Nike_Sales_Uncleaned!E136))) -> M | E82: =TRIM(B82)&"|"&TRIM(C82)&"|"&TRIM(D82) -> ZoomX Invincible|Training|M
A83: PK-82 | B83: Zoom Freak | C83: Basketball | D83: =IF(Nike_Sales_Uncleaned!E137="","NA",IF(OR(Nike_Sales_Uncleaned!E137=0,Nike_Sales_Uncleaned!E137=-1),"NA",UPPER(Nike_Sales_Uncleaned!E137))) -> L | E83: =TRIM(B83)&"|"&TRIM(C83)&"|"&TRIM(D83) -> Zoom Freak|Basketball|L
A84: PK-83 | B84: Pegasus Turbo | C84: Running | D84: =IF(Nike_Sales_Uncleaned!E140="","NA",IF(OR(Nike_Sales_Uncleaned!E140=0,Nike_Sales_Uncleaned!E140=-1),"NA",UPPER(Nike_Sales_Uncleaned!E140))) -> 11 | E84: =TRIM(B84)&"|"&TRIM(C84)&"|"&TRIM(D84) -> Pegasus Turbo|Running|11
A85: PK-84 | B85: Tiempo Legend | C85: Soccer | D85: =IF(Nike_Sales_Uncleaned!E143="","NA",IF(OR(Nike_Sales_Uncleaned!E143=0,Nike_Sales_Uncleaned!E143=-1),"NA",UPPER(Nike_Sales_Uncleaned!E143))) -> NA | E85: =TRIM(B85)&"|"&TRIM(C85)&"|"&TRIM(D85) -> Tiempo Legend|Soccer|NA
A86: PK-85 | B86: Blazer Mid | C86: Lifestyle | D86: =IF(Nike_Sales_Uncleaned!E147="","NA",IF(OR(Nike_Sales_Uncleaned!E147=0,Nike_Sales_Uncleaned!E147=-1),"NA",UPPER(Nike_Sales_Uncleaned!E147))) -> 6 | E86: =TRIM(B86)&"|"&TRIM(C86)&"|"&TRIM(D86) -> Blazer Mid|Lifestyle|6
A87: PK-86 | B87: Pegasus Turbo | C87: Running | D87: =IF(Nike_Sales_Uncleaned!E151="","NA",IF(OR(Nike_Sales_Uncleaned!E151=0,Nike_Sales_Uncleaned!E151=-1),"NA",UPPER(Nike_Sales_Uncleaned!E151))) -> NA | E87: =TRIM(B87)&"|"&TRIM(C87)&"|"&TRIM(D87) -> Pegasus Turbo|Running|NA
A88: PK-87 | B88: LeBron 20 | C88: Basketball | D88: =IF(Nike_Sales_Uncleaned!E152="","NA",IF(OR(Nike_Sales_Uncleaned!E152=0,Nike_Sales_Uncleaned!E152=-1),"NA",UPPER(Nike_Sales_Uncleaned!E152))) -> M | E88: =TRIM(B88)&"|"&TRIM(C88)&"|"&TRIM(D88) -> LeBron 20|Basketball|M
A89: PK-88 | B89: Free RN | C89: Running | D89: =IF(Nike_Sales_Uncleaned!E154="","NA",IF(OR(Nike_Sales_Uncleaned!E154=0,Nike_Sales_Uncleaned!E154=-1),"NA",UPPER(Nike_Sales_Uncleaned!E154))) -> 8 | E89: =TRIM(B89)&"|"&TRIM(C89)&"|"&TRIM(D89) -> Free RN|Running|8
A90: PK-89 | B90: React Infinity | C90: Running | D90: =IF(Nike_Sales_Uncleaned!E155="","NA",IF(OR(Nike_Sales_Uncleaned!E155=0,Nike_Sales_Uncleaned!E155=-1),"NA",UPPER(Nike_Sales_Uncleaned!E155))) -> NA | E90: =TRIM(B90)&"|"&TRIM(C90)&"|"&TRIM(D90) -> React Infinity|Running|NA
A91: PK-90 | B91: Air Zoom | C91: Running | D91: =IF(Nike_Sales_Uncleaned!E162="","NA",IF(OR(Nike_Sales_Uncleaned!E162=0,Nike_Sales_Uncleaned!E162=-1),"NA",UPPER(Nike_Sales_Uncleaned!E162))) -> XL | E91: =TRIM(B91)&"|"&TRIM(C91)&"|"&TRIM(D91) -> Air Zoom|Running|XL
A92: PK-91 | B92: Blazer Mid | C92: Lifestyle | D92: =IF(Nike_Sales_Uncleaned!E164="","NA",IF(OR(Nike_Sales_Uncleaned!E164=0,Nike_Sales_Uncleaned!E164=-1),"NA",UPPER(Nike_Sales_Uncleaned!E164))) -> 8 | E92: =TRIM(B92)&"|"&TRIM(C92)&"|"&TRIM(D92) -> Blazer Mid|Lifestyle|8
A93: PK-92 | B93: Dunk Low | C93: Lifestyle | D93: =IF(Nike_Sales_Uncleaned!E165="","NA",IF(OR(Nike_Sales_Uncleaned!E165=0,Nike_Sales_Uncleaned!E165=-1),"NA",UPPER(Nike_Sales_Uncleaned!E165))) -> 7 | E93: =TRIM(B93)&"|"&TRIM(C93)&"|"&TRIM(D93) -> Dunk Low|Lifestyle|7
A94: PK-93 | B94: Mercurial Superfly | C94: Soccer | D94: =IF(Nike_Sales_Uncleaned!E166="","NA",IF(OR(Nike_Sales_Uncleaned!E166=0,Nike_Sales_Uncleaned!E166=-1),"NA",UPPER(Nike_Sales_Uncleaned!E166))) -> 8 | E94: =TRIM(B94)&"|"&TRIM(C94)&"|"&TRIM(D94) -> Mercurial Superfly|Soccer|8
A95: PK-94 | B95: Air Force 1 | C95: Lifestyle | D95: =IF(Nike_Sales_Uncleaned!E168="","NA",IF(OR(Nike_Sales_Uncleaned!E168=0,Nike_Sales_Uncleaned!E168=-1),"NA",UPPER(Nike_Sales_Uncleaned!E168))) -> M | E95: =TRIM(B95)&"|"&TRIM(C95)&"|"&TRIM(D95) -> Air Force 1|Lifestyle|M
A96: PK-95 | B96: Phantom GT | C96: Soccer | D96: =IF(Nike_Sales_Uncleaned!E176="","NA",IF(OR(Nike_Sales_Uncleaned!E176=0,Nike_Sales_Uncleaned!E176=-1),"NA",UPPER(Nike_Sales_Uncleaned!E176))) -> L | E96: =TRIM(B96)&"|"&TRIM(C96)&"|"&TRIM(D96) -> Phantom GT|Soccer|L
A97: PK-96 | B97: Waffle One | C97: Lifestyle | D97: =IF(Nike_Sales_Uncleaned!E179="","NA",IF(OR(Nike_Sales_Uncleaned!E179=0,Nike_Sales_Uncleaned!E179=-1),"NA",UPPER(Nike_Sales_Uncleaned!E179))) -> XL | E97: =TRIM(B97)&"|"&TRIM(C97)&"|"&TRIM(D97) -> Waffle One|Lifestyle|XL
A98: PK-97 | B98: Zoom Freak | C98: Basketball | D98: =IF(Nike_Sales_Uncleaned!E184="","NA",IF(OR(Nike_Sales_Uncleaned!E184=0,Nike_Sales_Uncleaned!E184=-1),"NA",UPPER(Nike_Sales_Uncleaned!E184))) -> 11 | E98: =TRIM(B98)&"|"&TRIM(C98)&"|"&TRIM(D98) -> Zoom Freak|Basketball|11
A99: PK-98 | B99: Air Force 1 | C99: Lifestyle | D99: =IF(Nike_Sales_Uncleaned!E193="","NA",IF(OR(Nike_Sales_Uncleaned!E193=0,Nike_Sales_Uncleaned!E193=-1),"NA",UPPER(Nike_Sales_Uncleaned!E193))) -> 8 | E99: =TRIM(B99)&"|"&TRIM(C99)&"|"&TRIM(D99) -> Air Force 1|Lifestyle|8
A100: PK-99 | B100: Kyrie Flytrap | C100: Basketball | D100: =IF(Nike_Sales_Uncleaned!E194="","NA",IF(OR(Nike_Sales_Uncleaned!E194=0,Nike_Sales_Uncleaned!E194=-1),"NA",UPPER(Nike_Sales_Uncleaned!E194))) -> XL | E100: =TRIM(B100)&"|"&TRIM(C100)&"|"&TRIM(D100) -> Kyrie Flytrap|Basketball|XL
...

Sheet Dim_Region
A1: Region_Key | B1: Region
A2: RK-01 | B2: Bangalore
A3: RK-02 | B3: Hyderabad
A4: RK-03 | B4: Mumbai
A5: RK-04 | B5: Pune
A6: RK-05 | B6: Delhi
A7: RK-06 | B7: Kolkata

Sheet Dim_SalesChannel
A1: Channel_Key | B1: Sales_Channel
A2: CK-01 | B2: Online
A3: CK-02 | B3: Retail

Sheet Dim_Gender
A1: Gender_Key | B1: Gender_Category
A2: GK-01 | B2: Kids
A3: GK-02 | B3: Women
A4: GK-03 | B4: Men

Sheet Dim_Date
A1: Date_Key | B1: Date | C1: Year | D1: Quarter | E1: Month_Number | F1: Month | G1: Month_Year
A2: DK-01 | B2: =MIN('Cleaned Data'!J1:J2387) -> 45133 | C2: =TEXT(B2,"YYYY") -> 2023 | D2: ="Q"&ROUNDUP(MONTH(B2)/3,0) -> Q3 | E2: =MONTH(B2) -> 7 | F2: =TEXT(B2,"MMM") -> Jul | G2: =TEXT(B2,"mmm yyyy") -> Jul 2023
A3: DK-02 | B3: =B2+1 -> 45134 | C3: =TEXT(B3,"YYYY") -> 2023 | D3: ="Q"&ROUNDUP(MONTH(B3)/3,0) -> Q3 | E3: =MONTH(B3) -> 7 | F3: =TEXT(B3,"MMM") -> Jul | G3: =TEXT(B3,"mmm yyyy") -> Jul 2023
A4: DK-03 | B4: =B3+1 -> 45135 | C4: =TEXT(B4,"YYYY") -> 2023 | D4: ="Q"&ROUNDUP(MONTH(B4)/3,0) -> Q3 | E4: =MONTH(B4) -> 7 | F4: =TEXT(B4,"MMM") -> Jul | G4: =TEXT(B4,"mmm yyyy") -> Jul 2023
A5: DK-04 | B5: =B4+1 -> 45136 | C5: =TEXT(B5,"YYYY") -> 2023 | D5: ="Q"&ROUNDUP(MONTH(B5)/3,0) -> Q3 | E5: =MONTH(B5) -> 7 | F5: =TEXT(B5,"MMM") -> Jul | G5: =TEXT(B5,"mmm yyyy") -> Jul 2023
A6: DK-05 | B6: =B5+1 -> 45137 | C6: =TEXT(B6,"YYYY") -> 2023 | D6: ="Q"&ROUNDUP(MONTH(B6)/3,0) -> Q3 | E6: =MONTH(B6) -> 7 | F6: =TEXT(B6,"MMM") -> Jul | G6: =TEXT(B6,"mmm yyyy") -> Jul 2023
A7: DK-06 | B7: =B6+1 -> 45138 | C7: =TEXT(B7,"YYYY") -> 2023 | D7: ="Q"&ROUNDUP(MONTH(B7)/3,0) -> Q3 | E7: =MONTH(B7) -> 7 | F7: =TEXT(B7,"MMM") -> Jul | G7: =TEXT(B7,"mmm yyyy") -> Jul 2023
A8: DK-07 | B8: =B7+1 -> 45139 | C8: =TEXT(B8,"YYYY") -> 2023 | D8: ="Q"&ROUNDUP(MONTH(B8)/3,0) -> Q3 | E8: =MONTH(B8) -> 8 | F8: =TEXT(B8,"MMM") -> Aug | G8: =TEXT(B8,"mmm yyyy") -> Aug 2023
A9: DK-08 | B9: =B8+1 -> 45140 | C9: =TEXT(B9,"YYYY") -> 2023 | D9: ="Q"&ROUNDUP(MONTH(B9)/3,0) -> Q3 | E9: =MONTH(B9) -> 8 | F9: =TEXT(B9,"MMM") -> Aug | G9: =TEXT(B9,"mmm yyyy") -> Aug 2023
A10: DK-09 | B10: =B9+1 -> 45141 | C10: =TEXT(B10,"YYYY") -> 2023 | D10: ="Q"&ROUNDUP(MONTH(B10)/3,0) -> Q3 | E10: =MONTH(B10) -> 8 | F10: =TEXT(B10,"MMM") -> Aug | G10: =TEXT(B10,"mmm yyyy") -> Aug 2023
A11: DK-10 | B11: =B10+1 -> 45142 | C11: =TEXT(B11,"YYYY") -> 2023 | D11: ="Q"&ROUNDUP(MONTH(B11)/3,0) -> Q3 | E11: =MONTH(B11) -> 8 | F11: =TEXT(B11,"MMM") -> Aug | G11: =TEXT(B11,"mmm yyyy") -> Aug 2023
A12: DK-11 | B12: =B11+1 -> 45143 | C12: =TEXT(B12,"YYYY") -> 2023 | D12: ="Q"&ROUNDUP(MONTH(B12)/3,0) -> Q3 | E12: =MONTH(B12) -> 8 | F12: =TEXT(B12,"MMM") -> Aug | G12: =TEXT(B12,"mmm yyyy") -> Aug 2023
A13: DK-12 | B13: =B12+1 -> 45144 | C13: =TEXT(B13,"YYYY") -> 2023 | D13: ="Q"&ROUNDUP(MONTH(B13)/3,0) -> Q3 | E13: =MONTH(B13) -> 8 | F13: =TEXT(B13,"MMM") -> Aug | G13: =TEXT(B13,"mmm yyyy") -> Aug 2023
A14: DK-13 | B14: =B13+1 -> 45145 | C14: =TEXT(B14,"YYYY") -> 2023 | D14: ="Q"&ROUNDUP(MONTH(B14)/3,0) -> Q3 | E14: =MONTH(B14) -> 8 | F14: =TEXT(B14,"MMM") -> Aug | G14: =TEXT(B14,"mmm yyyy") -> Aug 2023
... A728: DK-727 | B728: =B727+1 -> 45859 | C728: =TEXT(B728,"YYYY") -> 2025 | D728: ="Q"&ROUNDUP(MONTH(B728)/3,0) -> Q3 | E728: =MONTH(B728) -> 7 | F728: =TEXT(B728,"MMM") -> Jul | G728: =TEXT(B728,"mmm yyyy") -> Jul 2025
A729: DK-728 | B729: =MAX('Cleaned Data'!J1:J2387) -> 45860 | C729: =TEXT(B729,"YYYY") -> 2025 | D729: ="Q"&ROUNDUP(MONTH(B729)/3,0) -> Q3 | E729: =MONTH(B729) -> 7 | F729: =TEXT(B729,"MMM") -> Jul | G729: =TEXT(B729,"mmm yyyy") -> Jul 2025
